{
  "system_name" : "iPhone OS",
  "system_version" : "9.1",
  "total_words" : 21,
  "completed_word" : 21,
  "language_name" : "English",
  "device_idiom" : "iPad",
  "sub_language" : "en_US",
  "device_name" : "MS-TabletPRO",
  "language" : "en",
  "words" : [
    {
      "word" : "the",
      "count" : 1,
      "type" : 1,
      "ink" : "UFdJQzEuMDUAADMAHwEAAAAA\/\/8U\/\/\/\/\/wMADTgCPAAAAAAAgEBwcJCQgcHBwfHx4QGWa\/\/\/\/\/8BEQGWa\/\/\/\/\/8BEQGWa\/\/\/\/\/8BEAGWa\/\/\/\/\/8AEwGWa\/\/\/\/\/8AEQGWa\/\/\/\/\/8BEQGWa\/\/\/\/\/8AEwGWN\/\/\/\/\/8BABAA8AGWN\/\/\/\/\/8MABAAQNEA8NDwwLCwoIGhcJInAZYW\/\/\/\/\/wTMARQBAAADBggaAZZr\/\/\/\/\/xABAZZr\/\/\/\/\/xICAZZr\/\/\/\/\/xICAZZr\/\/\/\/\/xYDAZZr\/\/\/\/\/xICAZZr\/\/\/\/\/xECAZY3\/\/\/\/\/xIRAQCqqqoKLx0NDRssKipJOTc4NxUoFxocAZYW\/\/\/\/\/xBgAwwAVREBAAASIkMyYXCRwMGw4NDQ8ODgAZY3\/\/\/\/\/wIAEADw4AGWN\/\/\/\/\/8CABAA4OABljf\/\/\/\/\/AgAQAPDQAZY3\/\/\/\/\/xYAEAAAAACqCtDQ4MDA0LCQoJBwkHCgcFBAgJDB4vMBlmv\/\/\/\/\/Be0Bljf\/\/\/\/\/AQXvAvUBljf\/\/\/\/\/GQfwqqqqAgAAANbGx7eWl4dmV0c2SRgFFiVVVWSllKPk0sMBljf\/\/\/\/\/EQIQAAAAAADy4\/Lj0tTDpKSVdHVUNEU1XwGWFv\/\/\/\/8L6AT8AAAAABEyRUZIS0w7Ty4+AZY3\/\/\/\/\/xQQAoCqqvr\/AB4eDx4sTEpJaWZldHJhcmNlWks7AZZr\/\/\/\/\/\/D\/AZY3\/\/\/\/\/wHw\/wEPAZZr\/\/\/\/\/+0DAZZr\/\/\/\/\/+4EAZZr\/\/\/\/\/+4GAZZr\/\/\/\/\/+0KAZZr\/\/\/\/\/+4KAZZr\/\/\/\/\/\/ALAZY3\/\/\/\/\/wLvDQXv3QGWN\/\/\/\/\/8L9BBVBQDp6OflxNHBoriZmgGWa\/\/\/\/\/8RBwGWa\/\/\/\/\/8SBgGWa\/\/\/\/\/8TBQGWa\/\/\/\/\/8aBAGWa\/\/\/\/\/8ZAwGWa\/\/\/\/\/8YAgGWa\/\/\/\/\/8fAAGWa\/\/\/\/\/8d\/wGWa\/\/\/\/\/8d\/gGWa\/\/\/\/\/8h\/AGWa\/\/\/\/\/8f+wGWO\/\/\/\/\/8BHPq6AZYAAAAAAAAAAA=="
    },
    {
      "word" : "quick",
      "count" : 1,
      "type" : 1,
      "ink" : "UFdJQzEuMDUAAD4AHwEAAAAA\/\/8U\/\/\/\/\/wMAS7QCGAH\/\/99VVVVVVQAAAICqqqqqVlUVMlNFNicpGRkbGgocCwobGykqODhHR1dmdXSEc4KCkoGQgXKEdHRmVkdJOCgrCQorOjp6aniZmIeXloWFc2OCYmIxUmFysbGy8fLiAZZr\/\/\/\/\/\/4SAZZr\/\/\/\/\/\/4SAZZr\/\/\/\/\/\/4SAZZr\/\/\/\/\/\/4VAZZr\/\/\/\/\/\/4UAZZr\/\/\/\/\/\/4TAZZr\/\/\/\/\/\/4XAZZr\/\/\/\/\/\/4UAZZr\/\/\/\/\/\/0TAZZr\/\/\/\/\/\/4UAZZr\/\/\/\/\/\/4RAZY3\/\/\/\/\/yD\/EBEAoKqqqqqqAPHgsbGRcnRFRRcZKFxqe6yru9zKyOnItrellYRjY3R0AZZr\/\/\/\/\/wrwAZYW\/\/\/\/\/wWMAwwBVQAjQ1Fy0QGWa\/\/\/\/\/8CEQGWa\/\/\/\/\/8DEwGWa\/\/\/\/\/8EFgGWa\/\/\/\/\/8EFAGWa\/\/\/\/\/8EEQGWN\/\/\/\/\/8SBREAAKCqCvTk1aWUhXRURjcWNleIqKj5+QGWa\/\/\/\/\/8H8AGWa\/\/\/\/\/8J7AGWa\/\/\/\/\/8H7QGWa\/\/\/\/\/8G7wGWa\/\/\/\/\/8H7AGWa\/\/\/\/\/8F7gGWa\/\/\/\/\/8F7wGWN\/\/\/\/\/8JBe8qAADVw8dCYXGwwMABljf\/\/\/\/\/AQAQAfEBlmv\/\/\/\/\/ABABlmv\/\/\/\/\/ABIBljf\/\/\/\/\/AQAQAPABljf\/\/\/\/\/CwAQAAAA4tHUs6SWhWRWRjUBlmv\/\/\/\/\/FgkBlhb\/\/\/\/\/EFAFPAFVAQAAACEyYmFxoMDg4MDRwrHCk4MBlmv\/\/\/\/\/Cx0Blhb\/\/\/\/\/CkQFjABVEQASMlNScYCRwJGBAZZr\/\/\/\/\/wUdAZYW\/\/\/\/\/yZoBjwBX1VVVVUAAICqChIlBwgLLiw8TEtaanhnppWkwsKx0rO0yJiYi2tbLh0tPks5WlhYAZZr\/\/\/\/\/x\/sAZYW\/\/\/\/\/w70BsgAVVVVBCIyYmJykqKR0cHB8eDRAZY3\/\/\/\/\/wIAEADw0AGWN\/\/\/\/\/8OABAAAAAA4NHx0cHhwsHCopKScnIBlmv\/\/\/\/\/CBYBlhb\/\/\/\/\/B\/QGeAGqKhEjJRQ4XG8Blmv\/\/\/\/\/FfcBlmv\/\/\/\/\/E\/YBlmv\/\/\/\/\/EvcBlmv\/\/\/\/\/FfUBlmv\/\/\/\/\/EvYBlmv\/\/\/\/\/EvYBlmv\/\/\/\/\/EvUBljf\/\/\/\/\/BxH2qiqvn4x7amlXAZZr\/\/\/\/\/xvvAZYW\/\/\/\/\/wQQB5QBAAAiNzpeAZZr\/\/\/\/\/xUJAZZr\/\/\/\/\/xcMAZZr\/\/\/\/\/xYOAZZr\/\/\/\/\/xgQAZY3\/\/\/\/\/wQTDQAArr2bigGWa\/\/\/\/\/8iHQGWAAAAAAAAAAA="
    },
    {
      "word" : "brown",
      "count" : 1,
      "type" : 1,
      "ink" : "UFdJQzEuMDUAADkAHwEAAAAA\/\/8U\/\/\/\/\/wMACqABKAD\/BwAxQmGTUhFAkaKyAZZr\/\/\/\/\/wIQAZZr\/\/\/\/\/wIQAZZr\/\/\/\/\/wIQAZZr\/\/\/\/\/wIUAZZr\/\/\/\/\/wITAZZr\/\/\/\/\/wETAZZr\/\/\/\/\/wEXAZZr\/\/\/\/\/wEWAZZr\/\/\/\/\/wEUAZZr\/\/\/\/\/wAZAZZr\/\/\/\/\/wAXAZZr\/\/\/\/\/\/8XAZZr\/\/\/\/\/\/4ZAZZr\/\/\/\/\/\/4XAZZr\/\/\/\/\/\/4WAZZr\/\/\/\/\/\/0WAZZr\/\/\/\/\/\/0TAZZr\/\/\/\/\/\/4RAZY3\/\/\/\/\/w3+EVWlqgLx0rGicZMwcYKT5PTlAZZr\/\/\/\/\/wbuAZZr\/\/\/\/\/wbvAZZr\/\/\/\/\/wbvAZZr\/\/\/\/\/wjuAZY3\/\/\/\/\/wEH7wL3AZY3\/\/\/\/\/yMI8KqqAAAAAFBVFdjHuZh4WUk4Chk5aXl4ubin59bF9NPS4tDAwrSkqJmKjm1eAZY3\/\/\/\/\/xDwBFX9\/78ATi4fHg0tKzpKV1Z0c2OhkAGWa\/\/\/\/\/8G6gGWFv\/\/\/\/8VLANkAQAAAKiqAlBggJDQ0NHhwaGxgYEgYJCgwPHg8QGWa\/\/\/\/\/8B8AGWN\/\/\/\/\/8ZAvCqqqqqAgAA4vPkxNW1laaGhWdmRUg2JiYWFUZFRmdXVgGWa\/\/\/\/\/8bFAGWFv\/\/\/\/8lvAQ8Af9VVVUVAACgqgISIyUUFjc5fGp5iZiGtrWj08PB0MLExqeIimtKPAwba2qJydfWAZY3\/\/\/\/\/xcF8Kr6\/19VFeTj8uLQwLKShGNURSYmFyc2WGhneHZmAZZr\/\/\/\/\/+0WAZYW\/\/\/\/\/z9gBSQBAAAAAAAAoKqqqgIAAICqKiBRgZCRkJHBwcHy09Pkw6S0lYR1ZUVFJSUYJ0ZFZHV0Y4RjU3RURSQXFTZGRmdnVldGRjY1JgYVJWZldMS0wwGWa\/\/\/\/\/8D8AGWN\/\/\/\/\/8BAvAC8gGWa\/\/\/\/\/8C7wGWN\/\/\/\/\/8BAe8C8gGWN\/\/\/\/\/8LAvCqqiriw8Okg4RjRFQ1RAGWa\/\/\/\/\/8R9QGWFv\/\/\/\/8ULAdsARUBFYGqACFRgZCRcICAcXGhgHFQQEBwoMDBAZZr\/\/\/\/\/wLvAZZr\/\/\/\/\/wLwAZZr\/\/\/\/\/wTvAZZr\/\/\/\/\/wXtAZZr\/\/\/\/\/wXvAZZr\/\/\/\/\/wbwAZY3\/\/\/\/\/xEH8KqqAgAA6Me5mIhqSTgaCChpeHfH1tUBlmv\/\/\/\/\/BREBlmv\/\/\/\/\/BBABlmv\/\/\/\/\/AxABlmv\/\/\/\/\/AxIBljf\/\/\/\/\/AQMRAPMBljf\/\/\/\/\/CAIQAAAA8uPj08TEpIQBlmv\/\/\/\/\/Dx4BlgAAAAAAAAAA"
    },
    {
      "word" : "fox",
      "count" : 1,
      "type" : 1,
      "ink" : "UFdJQzEuMDUAADAAHwEAAAAA\/\/8U\/\/\/\/\/wMAGhgDMAD\/\/1dVVVUFM1NHOCksHBweDQ0dLTtMSlp5d3empbXj0+IBljf\/\/\/\/\/Av8RAfHxAZZr\/\/\/\/\/wISAZZr\/\/\/\/\/wIRAZZr\/\/\/\/\/wQRAZZr\/\/\/\/\/wQTAZZr\/\/\/\/\/wURAZZr\/\/\/\/\/wQQAZZr\/\/\/\/\/wUTAZY3\/\/\/\/\/wEFEAD0AZY3\/\/\/\/\/w4FEQAAAADk1OTUxNS0o6ODYpJSZAGWFv\/\/\/\/8F1AH8ACoAITQYHA4Blmv\/\/\/\/\/FAEBlmv\/\/\/\/\/EgEBlmv\/\/\/\/\/EQEBlmv\/\/\/\/\/EwABlmv\/\/\/\/\/EQEBlmv\/\/\/\/\/EAABljf\/\/\/\/\/CxH\/qKoqDx4uLSwrOykpKCcBlmv\/\/\/\/\/GvoBABb\/\/\/\/\/LqwDGAH\/VVVVVQEAAKCqqgoSIycYCBgYSkpZi4l5qpeXxrTE0sHB08SlyJiYimtaSyoqGjpIiZeWxcTD8uLQAZY3\/\/\/\/\/xP\/8P\/\/\/1UV4tTlxaWmhmZnRjYZCDU0RGRjUwGWa\/\/\/\/\/\/1FgGWFv\/\/\/\/8GSAQMAQAAIyQ0aIuuAZZr\/\/\/\/\/xINAZY3\/\/\/\/\/wEQDQC\/AZZr\/\/\/\/\/xINAZY3\/\/\/\/\/wERDQDPAZZr\/\/\/\/\/xMOAZZr\/\/\/\/\/xEMAZZr\/\/\/\/\/xAMAZZr\/\/\/\/\/xEMAZY3\/\/\/\/\/wEQCwCuAZY3\/\/\/\/\/wsQCQAAIJ59fXxrWllIKhc\/AZYW\/\/\/\/\/wZABfwAVQUFFjdIu+wBlmv\/\/\/\/\/8xEBlmv\/\/\/\/\/8BYBlmv\/\/\/\/\/8hUBlmv\/\/\/\/\/9BQBlmv\/\/\/\/\/8xYBlmv\/\/\/\/\/9RQBlmv\/\/\/\/\/9RMBlmv\/\/\/\/\/9RQBlmv\/\/\/\/\/9xIBlmv\/\/\/\/\/9xEBlmv\/\/\/\/\/9xIBljf\/\/\/\/\/B\/kQVRXn1cSTk4NzAZZr\/\/\/\/\/\/QZAZYAAAAAAAAAAA=="
    },
    {
      "word" : "jumps",
      "count" : 1,
      "type" : 1,
      "ink" : "UFdJQzEuMDUAAC4AHwEAAAAA\/\/8U\/\/\/\/\/wMAEpACJAEAAAAAAIAgUGBgYZGRkrKxstHRseHgwQGWN\/\/\/\/\/8C\/xAF4uMBljf\/\/\/\/\/F\/oQVVVV1f8\/5ubpybnLm5mMalpLOioKGShZiIbX1dQBljf\/\/\/\/\/A\/3vP\/LyMQGWFv\/\/\/\/8KjAJYAFdVBRQUM0ODhKO0k4QBlmv\/\/\/\/\/8x8Blhb\/\/\/\/\/LzQDJAFFAAAAAICqqqqqAgAhMWBhcJChsdHSwuPSw9S0pKSFdFU1JSY2Z5emtubm5PXjw8OzkrKDdSJDUrOzwgGWa\/\/\/\/\/8DEQGWN\/\/\/\/\/8BAhAA8gGWN\/\/\/\/\/8FAhEAAOHCwrKjAZZr\/\/\/\/\/wslAZYW\/\/\/\/\/0psBGgBAAAAqqqqqgAAAACoqqoqAAAAADBRkaHC8sGhoYFhkjFSgpKRwrKispOTc2NTVUQHJVZldqalpLW0o5KDYnNDFDNTY3Okg5ODg2OEVUYmFiY3aXh4qZiHqIeHhnZWAZZr\/\/\/\/\/xUTAZYW\/\/\/\/\/wUABmQBAAAiMlJi0wGWa\/\/\/\/\/8FEAGWa\/\/\/\/\/8FEwGWa\/\/\/\/\/8GFwGWa\/\/\/\/\/8FFQGWa\/\/\/\/\/8FEgGWa\/\/\/\/\/8DFAGWa\/\/\/\/\/8DEQGWa\/\/\/\/\/8CEAGWN\/\/\/\/\/8KAhAA8A\/RsbGAcDBBkrHSAZZr\/\/\/\/\/\/\/tAZZr\/\/\/\/\/\/\/tAZZr\/\/\/\/\/wDtAZZr\/\/\/\/\/\/\/nAZZr\/\/\/\/\/wDpAZZr\/\/\/\/\/\/\/pAZZr\/\/\/\/\/wHnAZZr\/\/\/\/\/wLpAZZr\/\/\/\/\/wPsAZZr\/\/\/\/\/wXrAZY3\/\/\/\/\/ysE7qqqCgBAVVVVVasq9PXGpZZ2Vkc2JgcWNVRjc5KRkMKztNfHyNq6qauJiXpZV1o3I0RmZ4t9fQGWa\/\/\/\/\/8S9wGWa\/\/\/\/\/8S+AGWa\/\/\/\/\/8S+AGWa\/\/\/\/\/8W9wGWa\/\/\/\/\/8U9gGWa\/\/\/\/\/8T9wGWa\/\/\/\/\/8W9gGWa\/\/\/\/\/8T9wGWa\/\/\/\/\/8R+AGWa\/\/\/\/\/8T9gGWN\/\/\/\/\/8+EPiqqlVVVVUBAIgKVFVVVVUFjo58allXNkciM0SHmajLy8nbuLinhnWVZEAyJRYYCgkJGwkYHBgHJUVBU2SXl5nLuqq8rJqsm4qKaFdXRUUBlmv\/\/\/\/\/7g0BlgAAAAAAAAAA"
    },
    {
      "word" : "over",
      "count" : 1,
      "type" : 1,
      "ink" : "UFdJQzEuMDUAAC0AHwEAAAAA\/\/8U\/\/\/\/\/wMAETQC7AD\/V1VVASMzNycoGxo5a4uLzMvK+efWAZY3\/\/\/\/\/wL7EAXz8wGWN\/\/\/\/\/8L\/xAAAADw4fPlxtm6mp5vXgGWa\/\/\/\/\/8SAgGWN\/\/\/\/\/8BEQIADwGWN\/\/\/\/\/8IEf2qqgBOXYyqqObl1AGWa\/\/\/\/\/8C8AGWN\/\/\/\/\/8BAvAC4AGWa\/\/\/\/\/\/+7wGWN\/\/\/\/\/8B\/PAD5AGWN\/\/\/\/\/8O+O\/\/\/\/8F6Nnqybm6mIh3ZkVZNMQBlhb\/\/\/\/\/BQQDIAEAADBwgcPUAZZr\/\/\/\/\/wcSAZY3\/\/\/\/\/wEHEQD2AZY3\/\/\/\/\/xMJEQAAAKgq59jYt6enh2ZWRjUoBzVFZba1xQGWa\/\/\/\/\/8F7wGWa\/\/\/\/\/8F8AGWa\/\/\/\/\/8E7wGWa\/\/\/\/\/8F7QGWa\/\/\/\/\/8F7QGWa\/\/\/\/\/8E7wGWa\/\/\/\/\/8E7QGWN\/\/\/\/\/8QA\/CqqqoKAOTzxLOkhHRUVUU3JhcYCAYBlmv\/\/\/\/\/GgQBlhb\/\/\/\/\/BXgEcAECAEQDFxw+AZZr\/\/\/\/\/xMDAZZr\/\/\/\/\/xECAZZr\/\/\/\/\/xECAZZr\/\/\/\/\/xMCAZY3\/\/\/\/\/wERAQAfAZY3\/\/\/\/\/xcRAKqq+v9fFR4sTFlXhnVjgoFxg3RlaFk5LQwcX26OAZY3\/\/\/\/\/xTwC1VVVQAAAM\/e7uzJ2cemtZSSgXFxZWZHSjssAZZr\/\/\/\/\/xABAZZr\/\/\/\/\/xABAZZr\/\/\/\/\/xAAAZZr\/\/\/\/\/xT\/AZZr\/\/\/\/\/xP9AZZr\/\/\/\/\/xL9AZZr\/\/\/\/\/xX6AZZr\/\/\/\/\/xP5AZZr\/\/\/\/\/xH5AZZr\/\/\/\/\/xP3AZY3\/\/\/\/\/wcQ+Koqjp98ampoaAGWa\/\/\/\/\/8a7QGWFv\/\/\/\/84HAZQAQAAAICqqq+qqqoKAAAAADFShJS1xbWllZRzc2NShCIxgJGQkKDAwLHRsLDAoJGTgnN1VERFJiUZGBcWJjVFNEREQ1VEVETbAgAAAAAAAAAAAAA="
    },
    {
      "word" : "lazy",
      "count" : 1,
      "type" : 1,
      "ink" : "UFdJQzEuMDUAAB4AHwEAAAAA\/\/8U\/\/\/\/\/wMABuQBXAAAACFRYaLD4wGWN\/\/\/\/\/8IAxEAAADz0vLi4fHh4AGWN\/\/\/\/\/8CABAA8eABljf\/\/\/\/\/EQAQAAAAAADg0ODAwMCgkKCAcKBwkHBBVAIAABb\/\/\/\/\/VcgDSAF\/d1VVVVVVAQAAqKqqqgoAAAAAAAAAIyUkBhgKHQwMHz4+b29djnyKm4mIqJaEpJOSkZGBknJ0ZVdGOiopDAsqS0tpeoiIp5eGlZV0g2JjlCJgYXBhYIJzcoSEc4V0ZXdmZndnVkdFNTU0NQGWa\/\/\/\/\/8SCgGWFv\/\/\/\/8FlAQMAQAARAQJDQ8Blmv\/\/\/\/\/EQABlmv\/\/\/\/\/Ff8Bljf\/\/\/\/\/NhEAqgpQVVVVVRUAAAAAAAAfHhwbHBoXFUVAUmKVpaXIx8fo2Nfo17bGtJSjk3GxcVNTNEcnJxoaGhsLGgsKCQoICAkHChwBlhb\/\/\/\/\/CcAEqAGqqgIhMzNFNTUpPC4Blmv\/\/\/\/\/E\/wBljf\/\/\/\/\/ARD9Ai8Bljf\/\/\/\/\/AhD9CiwrAZZr\/\/\/\/\/yb5AQEW\/\/\/\/\/zngBVABqiIAAAAAAACoqqqqSlUBESMmFhgHFgUWFEREcoJxgYCRkIGBgXGCc2NUVTZHKDcaGhpLWVmamKe4tqa1pJOjgmKRMVFxwcHhAZZr\/\/\/\/\/\/8RAZZr\/\/\/\/\/\/8QAZZr\/\/\/\/\/\/8QAZZr\/\/\/\/\/\/8SAZZr\/\/\/\/\/wARAZZr\/\/\/\/\/\/8QAZZr\/\/\/\/\/\/8RAZY3\/\/\/\/\/wH+EAHyAZY3\/\/\/\/\/wL9EAX05AGWN\/\/\/\/\/8I+RBVVQDn6OrKu82dnAGWN\/\/\/\/\/8C8AgFfl0Blmv\/\/\/\/\/8AQBljf\/\/\/\/\/AfADAS4Bljf\/\/\/\/\/Au8BDx8tAZYAAAAAAAAAAA=="
    },
    {
      "word" : "dog",
      "count" : 1,
      "type" : 1,
      "ink" : "UFdJQzEuMDUAADcAHwEAAAAA\/\/8U\/\/\/\/\/wMAB8QCRAH\/PyMzRiYoKy0Blmv\/\/\/\/\/7v4Bljf\/\/\/\/\/Ae\/\/Ax8Blmv\/\/\/\/\/7v8Bljf\/\/\/\/\/AfD\/AQ8Bljf\/\/\/\/\/I\/AAVVVVAAAAqqoqHhwtO0ppeHa1pLPhwMHUtaaoiWpsTEsfHi1fbmysvKr66vgBlmv\/\/\/\/\/CO4Blmv\/\/\/\/\/Bu4Blmv\/\/\/\/\/Bu4Blmv\/\/\/\/\/BOoBlmv\/\/\/\/\/BOwBlmv\/\/\/\/\/A+0Blmv\/\/\/\/\/A+kBlmv\/\/\/\/\/AuoBlmv\/\/\/\/\/AewBlmv\/\/\/\/\/AegBlmv\/\/\/\/\/AeoBlmv\/\/\/\/\/AesBlmv\/\/\/\/\/AOkBlmv\/\/\/\/\/\/+wBlmv\/\/\/\/\/\/+4Bljf\/\/\/\/\/D\/7u\/\/9XFdKig2NDVDQkFSRTdMPj8gGWa\/\/\/\/\/\/\/FQGWa\/\/\/\/\/8AFAGWa\/\/\/\/\/8AFAGWa\/\/\/\/\/8CGgGWa\/\/\/\/\/8DGAGWa\/\/\/\/\/8EFwGWa\/\/\/\/\/8FGwGWa\/\/\/\/\/8HGQGWa\/\/\/\/\/8GFwGWa\/\/\/\/\/8JGgGWa\/\/\/\/\/8IGAGWa\/\/\/\/\/8IFgGWa\/\/\/\/\/8KFwGWa\/\/\/\/\/8KFAGWa\/\/\/\/\/8JEgGWN\/\/\/\/\/8FCREAAOm3t5d3AZZr\/\/\/\/\/xkcAZYW\/\/\/\/\/0D4AyABVVVVVQEAAKCqqqr\/\/19VVQADFRcGNTZXd3Z1hoR0o5OSsaCQs6SUl3hnako6LAsrS2ppmaiXxrWz08KxwLKTlYVmWDc4GhkYOUhnd4V1lINzAZZr\/\/\/\/\/\/caAZYW\/\/\/\/\/06wBUABX1VVVVUAAACqqqr\/HwAAAFBVVQUTFQYGFjk4R3p4ibiolsa0tMKiobGTg4dnZ1lJOCkJCCg4VnZ1dKOSkqGhkJGBYYJiU5IhMVNzc3STpJOysqLRsbHSsrTX2LjszLy\/v58Blmv\/\/\/\/\/7goBljf\/\/\/\/\/Ae8IAY8Blmv\/\/\/\/\/7QcBlmv\/\/\/\/\/7wYBlmv\/\/\/\/\/8AQBlmv\/\/\/\/\/7gQBlmv\/\/\/\/\/7gIBlmv\/\/\/\/\/7wIBlmv\/\/\/\/\/7QEBlmv\/\/\/\/\/7wEBlmv\/\/\/\/\/8P8Bljf\/\/\/\/\/CvD\/\/78KLyw8OTdYRWA1RgGWa\/\/\/\/\/8S9gGWAAAAAAAAAAA="
    },
    {
      "word" : "A B C D E",
      "count" : 5,
      "type" : 4,
      "ink" : "UFdJQzEuMDUAAIoAHwEAAAAA\/\/8U\/\/\/\/\/wMACAQBFAK\/qgBCUoKQkOHS4wGWa\/\/\/\/\/8E7wGWa\/\/\/\/\/8G7wGWa\/\/\/\/\/8F7gGWa\/\/\/\/\/8I6wGWa\/\/\/\/\/8I6wGWa\/\/\/\/\/8H7AGWa\/\/\/\/\/8J5wGWa\/\/\/\/\/8J6AGWa\/\/\/\/\/8I6QGWa\/\/\/\/\/8K5AGWa\/\/\/\/\/8J5wGWa\/\/\/\/\/8I5wGWa\/\/\/\/\/8K5AGWa\/\/\/\/\/8J5wGWa\/\/\/\/\/8J6AGWa\/\/\/\/\/8J5wGWa\/\/\/\/\/8J7QGWN\/\/\/\/\/8RCO+qqooAANm5d2lHRjkoJxcGFRUkgrLhAZZr\/\/\/\/\/wEWAZZr\/\/\/\/\/wAYAZZr\/\/\/\/\/wEYAZZr\/\/\/\/\/wEeAZZr\/\/\/\/\/wAdAZZr\/\/\/\/\/wEcAZZr\/\/\/\/\/wEgAZZr\/\/\/\/\/wEfAZZr\/\/\/\/\/wEdAZZr\/\/\/\/\/wEgAZZr\/\/\/\/\/wEeAZZr\/\/\/\/\/wEbAZZr\/\/\/\/\/wAdAZZr\/\/\/\/\/wEZAZZr\/\/\/\/\/wEWAZZr\/\/\/\/\/wEXAZZr\/\/\/\/\/wESAZZr\/\/\/\/\/wEQAZY3\/\/\/\/\/wgBEAAAAMGxoIFhcVGiAZYW\/\/\/\/\/wVAAQABigASEwgbDAGWa\/\/\/\/\/8T\/wGWa\/\/\/\/\/8SAAGWa\/\/\/\/\/8SAAGWa\/\/\/\/\/8WAAGWa\/\/\/\/\/8VAAGWa\/\/\/\/\/8UAAGWa\/\/\/\/\/8YAAGWa\/\/\/\/\/8WAAGWa\/\/\/\/\/8VAAGWa\/\/\/\/\/8XAAGWa\/\/\/\/\/8VAAGWa\/\/\/\/\/8UAAGWa\/\/\/\/\/8VAAGWa\/\/\/\/\/8TAAGWa\/\/\/\/\/8RAAEAFv\/\/\/\/8HaANIAFUREiJDQpHA8QGWa\/\/\/\/\/8AFQGWa\/\/\/\/\/\/\/FAGWa\/\/\/\/\/8AEwGWa\/\/\/\/\/8AFgGWa\/\/\/\/\/8AFQGWa\/\/\/\/\/8AEwGWa\/\/\/\/\/8AFwGWa\/\/\/\/\/8AFQGWa\/\/\/\/\/8AEwGWa\/\/\/\/\/8AFgGWa\/\/\/\/\/8AFAGWa\/\/\/\/\/8AEQGWN\/\/\/\/\/8MABIAoKoA8NDAoJDAQFBwsNDQAZZr\/\/\/\/\/wDuAZZr\/\/\/\/\/wDtAZZr\/\/\/\/\/wDuAZZr\/\/\/\/\/wDpAZZr\/\/\/\/\/wDqAZZr\/\/\/\/\/wDrAZZr\/\/\/\/\/wDnAZZr\/\/\/\/\/wHpAZZr\/\/\/\/\/wHqAZZr\/\/\/\/\/wLnAZZr\/\/\/\/\/wHpAZZr\/\/\/\/\/wHsAZZr\/\/\/\/\/wPqAZZr\/\/\/\/\/wLuAZZr\/\/\/\/\/wPvAZY3\/\/\/\/\/x0F8KqqqgAAAFAB5cSnh2hJSCkqGRkbGgo6WlmIh4alpLPSwcDy09QBljf\/\/\/\/\/NPgQVVVV1aqqqgoAAEBVVQDo2fzby8y8q5x6aVpHNys1MkNFaVlabUxNPz8uHx4MHSsrWkhWdnR0opGQw8W26drL7t++AZY3\/\/\/\/\/wLvDQW\/vgGWN\/\/\/\/\/8L8ApVVT2OfX5cWks5JwgXjQGWFv\/\/\/\/8ZsAVgAKr\/\/39VVQEwUGBQU0RGWUk4OzoaHBsLHDs6XGp6q7m5AZY3\/\/\/\/\/wL2EAX56QGWa\/\/\/\/\/\/4EgGWN\/\/\/\/\/8B+REB9gGWa\/\/\/\/\/\/6EwGWa\/\/\/\/\/\/8EQGWa\/\/\/\/\/\/9EAGWa\/\/\/\/\/\/\/EgGWN\/\/\/\/\/8B\/xAA8AGWN\/\/\/\/\/8dAhAAAAAAoKqqAvPj59a3upp6fGtLXTw8LSsaGxoZOjhIWUc2RkVEAZZr\/\/\/\/\/xLwAZYW\/\/\/\/\/wU0BgwAVQExYrHR4QGWa\/\/\/\/\/\/\/FAGWa\/\/\/\/\/8AEQGWa\/\/\/\/\/8AEQGWa\/\/\/\/\/\/\/EwGWa\/\/\/\/\/\/\/EwGWa\/\/\/\/\/8AEQGWa\/\/\/\/\/\/\/FQGWa\/\/\/\/\/\/\/EwGWa\/\/\/\/\/\/\/EgGWa\/\/\/\/\/\/\/FQGWa\/\/\/\/\/\/\/EgGWa\/\/\/\/\/\/\/EgGWa\/\/\/\/\/8AEwGWN\/\/\/\/\/8B\/xEB8QGWN\/\/\/\/\/8O\/xARVaoK8cDRoJGxcXEhYWBRYWIBlmv\/\/\/\/\/BukBABb\/\/\/\/\/O0gGIAAKAAAAAAAAUFVVVVVVVS0iFRY5WVp8e1l6WWlpaFd4d2d3dmaWhXSko5PCsbDhwsTm19j87Mvv3r3Pvp2vfXxsW0pJSSc5JhczkAGWFv\/\/\/\/8LYAdMAEUEFCExcHGAwbCw4NHRAZZr\/\/\/\/\/\/8QAZY3\/\/\/\/\/wH\/EAHyAZZr\/\/\/\/\/\/4SAZZr\/\/\/\/\/\/0SAZZr\/\/\/\/\/\/wRAZZr\/\/\/\/\/\/wUAZZr\/\/\/\/\/\/sTAZZr\/\/\/\/\/\/sRAZZr\/\/\/\/\/\/oUAZZr\/\/\/\/\/\/sSAZZr\/\/\/\/\/\/wQAZY3\/\/\/\/\/x37EVUVAACqqqoC9NPTs5GygXFDJiYXGgoaDRwbHRwrGykYKycnFVsBlhb\/\/\/\/\/EzgHRAGqggCIKhEjJxgYCQgbCgoLCwocChkZKCYBlmv\/\/\/\/\/F\/cBURb\/\/\/\/\/BEwHkACqADI2GiwBlmv\/\/\/\/\/Ff4Blmv\/\/\/\/\/F\/wBlmv\/\/\/\/\/GPsBlmv\/\/\/\/\/G\/oBlmv\/\/\/\/\/GPoBljv\/\/\/\/\/ART6qQGWAAAAAAAAAAA="
    },
    {
      "word" : "F G H I J",
      "count" : 5,
      "type" : 4,
      "ink" : "UFdJQzEuMDUAAIgAHwEAAAAA\/\/8U\/\/\/\/\/wMABRQBKAABAEQwUHHwAZZr\/\/\/\/\/wESAZZr\/\/\/\/\/wAVAZZr\/\/\/\/\/wEbAZZr\/\/\/\/\/wAYAZZr\/\/\/\/\/wAWAZZr\/\/\/\/\/wAYAZZr\/\/\/\/\/wAXAZZr\/\/\/\/\/wAVAZZr\/\/\/\/\/wAZAZZr\/\/\/\/\/wAWAZZr\/\/\/\/\/wAVAZZr\/\/\/\/\/wAXAZZr\/\/\/\/\/wAVAZZr\/\/\/\/\/wAUAZZr\/\/\/\/\/wAVAZZr\/\/\/\/\/wATAZZr\/\/\/\/\/wASAZY3\/\/\/\/\/wgAEQCAAPDQ0KCAoGBFAZYW\/\/\/\/\/ws0ARQAqgIAITM2FxgLDBwfLx4Blmv\/\/\/\/\/EQEBlmv\/\/\/\/\/EQEBlmv\/\/\/\/\/EAEBlmv\/\/\/\/\/EgABljf\/\/\/\/\/ARAAAB8Bljf\/\/\/\/\/CxH\/qKoqDh0uKyspGBcnF08Blhb\/\/\/\/\/BQQBBAGKABImCBwOAZZr\/\/\/\/\/xQAAZZr\/\/\/\/\/xEAAZZr\/\/\/\/\/xAAAZZr\/\/\/\/\/xP\/AZZr\/\/\/\/\/xIAAZZr\/\/\/\/\/xH\/AZZr\/\/\/\/\/xP\/AZY3\/\/\/\/\/wES\/wIvAZY3\/\/\/\/\/wUR\/qoCHy0uLCoBlmv\/\/\/\/\/JvkBlhb\/\/\/\/\/F7wDVAD\/\/1VVVRVCU1U1NicnFwkIGCs6Omx8fL69rf7s7AGWa\/\/\/\/\/\/zEgGWa\/\/\/\/\/\/1EAGWa\/\/\/\/\/\/3EAGWa\/\/\/\/\/\/2FAGWa\/\/\/\/\/\/3EgGWa\/\/\/\/\/\/4EQGWa\/\/\/\/\/\/5FQGWa\/\/\/\/\/\/6EwGWa\/\/\/\/\/\/7EgGWa\/\/\/\/\/\/9FAGWa\/\/\/\/\/\/9EgGWa\/\/\/\/\/\/+EAGWN\/\/\/\/\/9F\/hEEAACgqqqq6v\/\/j6qqqqqqqgLw4eKyo5V1ZVhINyoJCRs5OFloaId2dZSEg5KCgZFwcYFyY2NSU2RERjMEEiUmFxcpGSobLCssOyorKiopKCc2JhY4No8Blhb\/\/\/\/\/C3QEiABVFREiM3OSktHBwOHg0QGWa\/\/\/\/\/8AEAGWN\/\/\/\/\/8B\/xAA8AGWa\/\/\/\/\/\/\/EgGWN\/\/\/\/\/8B\/xEA8AGWN\/\/\/\/\/8N\/xFUEAAA4NHRwaCggXCgcKBhJwGWFv\/\/\/\/8WdAQUAaqqiACiChIjJhUXGRseDRwOHAwNCwsbCRcYFiYBlmv\/\/\/\/\/FvoBlhb\/\/\/\/\/BTQFCAAAAEAwgLDwAZZr\/\/\/\/\/wAUAZZr\/\/\/\/\/wAUAZZr\/\/\/\/\/wATAZZr\/\/\/\/\/wAWAZZr\/\/\/\/\/wAVAZZr\/\/\/\/\/wAUAZZr\/\/\/\/\/\/8XAZZr\/\/\/\/\/\/8WAZZr\/\/\/\/\/\/8VAZZr\/\/\/\/\/\/4YAZZr\/\/\/\/\/\/8WAZZr\/\/\/\/\/\/8VAZZr\/\/\/\/\/\/4XAZZr\/\/\/\/\/\/8WAZZr\/\/\/\/\/\/4UAZZr\/\/\/\/\/\/8VAZZr\/\/\/\/\/\/8UAZZr\/\/\/\/\/wARAZZr\/\/\/\/\/\/8TAZY3\/\/\/\/\/wcAEAAA4dCxkZFycgGWa\/\/\/\/\/8HGAGWFv\/\/\/\/8LTAY0AAAAADBwcKCw8ODB8OHQAZZr\/\/\/\/\/wEQAZY3\/\/\/\/\/wEAEADwAZZr\/\/\/\/\/wASAZZr\/\/\/\/\/wASAZZr\/\/\/\/\/wAQAZZr\/\/\/\/\/wAUAZZr\/\/\/\/\/\/8SAZZr\/\/\/\/\/\/8SAZZr\/\/\/\/\/\/4UAZZr\/\/\/\/\/\/4TAZZr\/\/\/\/\/\/4SAZZr\/\/\/\/\/\/4TAZZr\/\/\/\/\/\/0SAZZr\/\/\/\/\/\/4QAZY3\/\/\/\/\/wv+ElURAfLi4sGxoIFggVBQAZYW\/\/\/\/\/wTABSACqgAjJyodAZZr\/\/\/\/\/xf+AZZr\/\/\/\/\/xn\/AZZr\/\/\/\/\/xz+AZZr\/\/\/\/\/x7\/AZZr\/\/\/\/\/xj+AZY7\/\/\/\/\/wEU\/rsBlhb\/\/\/\/\/BeAFLACqAiEzOSwvAZZr\/\/\/\/\/xX\/AZZr\/\/\/\/\/xP\/AZZr\/\/\/\/\/xMAAZZr\/\/\/\/\/xf\/AZZr\/\/\/\/\/xUAAZZr\/\/\/\/\/xX\/AZZr\/\/\/\/\/xgAAZZr\/\/\/\/\/xb\/AZY7\/\/\/\/\/wEUALoBlhb\/\/\/\/\/BpQHQAABACFQY6XH2QGWN\/\/\/\/\/8CChEA+fgBljf\/\/\/\/\/AgkRAPfWAZZr\/\/\/\/\/wYQAZY3\/\/\/\/\/wEEEADkAZZr\/\/\/\/\/wISAZY3\/\/\/\/\/wEBEADxAZY3\/\/\/\/\/xf\/EFVVVVX9P\/Lk9ufY7Murvo2Nfl49Lg4NX219rKqYAZZr\/\/\/\/\/+XdAZYW\/\/\/\/\/wgoBywABQAAETJBVEVaOz0Blmv\/\/\/\/\/EwABlmv\/\/\/\/\/EwABlmv\/\/\/\/\/E\/4Blmv\/\/\/\/\/GPsBlmv\/\/\/\/\/GPoBlmv\/\/\/\/\/FvkBlmv\/\/\/\/\/GvgBlmv\/\/\/\/\/GPgBlmv\/\/\/\/\/FvgBlmv\/\/\/\/\/F\/kBlmv\/\/\/\/\/FPsBlmv\/\/\/\/\/EvwBogAAAAAAAAAA"
    },
    {
      "word" : "K L M N O",
      "count" : 5,
      "type" : 4,
      "ink" : "UFdJQzEuMDUAAK0AHwEAAAAA\/\/8U\/\/\/\/\/wMACjwBZAD\/AAAxQmFBcXGCwdHSAZZr\/\/\/\/\/wERAZZr\/\/\/\/\/wISAZZr\/\/\/\/\/wERAZZr\/\/\/\/\/wEVAZZr\/\/\/\/\/wEVAZZr\/\/\/\/\/wAUAZZr\/\/\/\/\/wEZAZZr\/\/\/\/\/wAXAZZr\/\/\/\/\/wEWAZZr\/\/\/\/\/wAZAZZr\/\/\/\/\/wAXAZZr\/\/\/\/\/wAVAZZr\/\/\/\/\/wAXAZZr\/\/\/\/\/wAVAZZr\/\/\/\/\/wASAZZr\/\/\/\/\/wAUAZZr\/\/\/\/\/wARAZZr\/\/\/\/\/wAQAZY3\/\/\/\/\/woAEAAAAODQwLCAoXFRQZUBlhb\/\/\/\/\/IYABNAGqqqqqqqqqqgIwMVFTUnVldZiYmMq7utvLyuzayuzaudu5mKmYdmdlRRgBlhb\/\/\/\/\/BVQBYAEAAAgFGDpNAZY3\/\/\/\/\/xoQBwAAAAAAAAB+bJ2ciqyqqaqpmKiXl5aGdYV0dXRjY2NTUgGWa\/\/\/\/\/8KEgGWFv\/\/\/\/8GiAMAAFUFIjIycaGxAZZr\/\/\/\/\/\/8QAZY3\/\/\/\/\/wH+EAHhAZZr\/\/\/\/\/\/0SAZZr\/\/\/\/\/\/0RAZZr\/\/\/\/\/\/4QAZZr\/\/\/\/\/\/wTAZZr\/\/\/\/\/\/0TAZZr\/\/\/\/\/\/wRAZZr\/\/\/\/\/\/wVAZZr\/\/\/\/\/\/wTAZZr\/\/\/\/\/\/wSAZZr\/\/\/\/\/\/sVAZZr\/\/\/\/\/\/oUAZZr\/\/\/\/\/\/sSAZZr\/\/\/\/\/\/oVAZZr\/\/\/\/\/\/sUAZZr\/\/\/\/\/\/sSAZZr\/\/\/\/\/\/wTAZY3\/\/\/\/\/yb8EFUVAICqqqqqqgrz8tOyoYJxcGBCNCYXBwcXKCkoOTkoKRcnFycXKxkXFxYbGRYWFgGWa\/\/\/\/\/8V+gGWFv\/\/\/\/8H+AQwAFUVIjN0YqLR8gGWa\/\/\/\/\/\/\/FQGWa\/\/\/\/\/\/+FAGWa\/\/\/\/\/\/+EgGWa\/\/\/\/\/\/9FwGWa\/\/\/\/\/\/+FgGWa\/\/\/\/\/\/9FQGWa\/\/\/\/\/\/8GQGWa\/\/\/\/\/\/8FgGWa\/\/\/\/\/\/8FQGWa\/\/\/\/\/\/8FwGWa\/\/\/\/\/\/7FQGWa\/\/\/\/\/\/8EwGWa\/\/\/\/\/\/8FAGWN\/\/\/\/\/8N\/BJVVaoC8\/PTsqKRYZIwcrLCwwGWa\/\/\/\/\/8F7gGWa\/\/\/\/\/8E7QGWa\/\/\/\/\/8E7gGWa\/\/\/\/\/8F6QGWa\/\/\/\/\/8E6gGWa\/\/\/\/\/8E6wGWa\/\/\/\/\/8F5wGWa\/\/\/\/\/8F6QGWa\/\/\/\/\/8E6wGWa\/\/\/\/\/8G5wGWa\/\/\/\/\/8F6wGWa\/\/\/\/\/8E7AGWa\/\/\/\/\/8G6wGWa\/\/\/\/\/8E7gGWa\/\/\/\/\/8F8AGWN\/\/\/\/\/9EBPCqqgAAAAAAAKqqqqqqqgIAAADltLSDZHVUFRREZGSUo7PU08Lj49Py07LCsZKykWFSQxJDYoODxMOz5OTj89PU08Szo5OCc2NDVCQjM3JygrGxseHg0AGWN\/\/\/\/\/8CARAA8eABlmv\/\/\/\/\/AREBljf\/\/\/\/\/AQEQAPEBlmv\/\/\/\/\/AhIBljf\/\/\/\/\/AQEQAPEBlmv\/\/\/\/\/ARIBlmv\/\/\/\/\/AhABlmv\/\/\/\/\/ARABlmv\/\/\/\/\/AREBljf\/\/\/\/\/DwIQAAAAAOHx0rHBooGRYmJzQkQzXAGWFv\/\/\/\/8GiAZUAFUEQVFhocDxAZZr\/\/\/\/\/\/8VAZZr\/\/\/\/\/\/8TAZZr\/\/\/\/\/\/8SAZZr\/\/\/\/\/\/4VAZZr\/\/\/\/\/\/4UAZZr\/\/\/\/\/\/0SAZZr\/\/\/\/\/\/0WAZZr\/\/\/\/\/\/wUAZZr\/\/\/\/\/\/0TAZZr\/\/\/\/\/\/sWAZZr\/\/\/\/\/\/sVAZZr\/\/\/\/\/\/wTAZZr\/\/\/\/\/\/sUAZZr\/\/\/\/\/\/sRAZY3\/\/\/\/\/w78EFXVqgr0w7OTgmKTc0BSgdPk4wGWa\/\/\/\/\/8E7QGWa\/\/\/\/\/8E7AGWa\/\/\/\/\/8E7QGWa\/\/\/\/\/8F6AGWa\/\/\/\/\/8E6QGWa\/\/\/\/\/8D6gGWa\/\/\/\/\/8F5gGWa\/\/\/\/\/8E6QGWa\/\/\/\/\/8D6wGWa\/\/\/\/\/8E6gGWa\/\/\/\/\/8E7AGWa\/\/\/\/\/8D7gGWa\/\/\/\/\/8D7QGWN\/\/\/\/\/8RA\/CqqgIAAOPjw6ODcmN0RAQjdHST1eTUAZZr\/\/\/\/\/wQSAZZr\/\/\/\/\/wQRAZZr\/\/\/\/\/wQRAZZr\/\/\/\/\/wQUAZZr\/\/\/\/\/wQTAZZr\/\/\/\/\/wQSAZZr\/\/\/\/\/wQVAZZr\/\/\/\/\/wQUAZZr\/\/\/\/\/wMSAZZr\/\/\/\/\/wQVAZZr\/\/\/\/\/wMSAZZr\/\/\/\/\/wMQAZY3\/\/\/\/\/xIEEQAAgKoK5NPTs5KDY1JSQwMzVHSExdTUAZZr\/\/\/\/\/wTvAZZr\/\/\/\/\/wTuAZZr\/\/\/\/\/wPuAZZr\/\/\/\/\/wPpAZZr\/\/\/\/\/wPrAZZr\/\/\/\/\/wPrAZZr\/\/\/\/\/wPmAZZr\/\/\/\/\/wLoAZZr\/\/\/\/\/wLpAZZr\/\/\/\/\/wLmAZZr\/\/\/\/\/wLqAZZr\/\/\/\/\/wLsAZZr\/\/\/\/\/wLrAZZr\/\/\/\/\/wLvAZY3\/\/\/\/\/woC8KqqCvLSo6NzY2VGNyYBlmv\/\/\/\/\/EP0Blhb\/\/\/\/\/EiQIaAD\/X1VVBRMkNSkpGRsZKUpYV3mXiNjH1gGWa\/\/\/\/\/\/6EAGWa\/\/\/\/\/\/6EAGWa\/\/\/\/\/\/7EAGWa\/\/\/\/\/\/7EwGWa\/\/\/\/\/\/8EwGWa\/\/\/\/\/\/8EQGWa\/\/\/\/\/\/9FAGWa\/\/\/\/\/\/+EwGWa\/\/\/\/\/\/+EgGWa\/\/\/\/\/\/\/EwGWa\/\/\/\/\/8AEgGWa\/\/\/\/\/8AEQGWN\/\/\/\/\/8RAxEAAKCqAvPk5qaXeWpKHg08b42b3evqAZZr\/\/\/\/\/wrtAZZr\/\/\/\/\/wnvAZZr\/\/\/\/\/wfuAZZr\/\/\/\/\/wbrAZZr\/\/\/\/\/wTtAZZr\/\/\/\/\/wPtAZZr\/\/\/\/\/wPrAZZr\/\/\/\/\/wLsAZZr\/\/\/\/\/wHvAZZr\/\/\/\/\/wDsAZZr\/\/\/\/\/\/\/uAZZr\/\/\/\/\/\/3wAZY3\/\/\/\/\/w387\/\/\/\/wP11de3l4loZ1k3NyoYAZZr\/\/\/\/\/+0AAZYAAAAAAAAAAA=="
    },
    {
      "word" : "P Q R S T",
      "count" : 5,
      "type" : 4,
      "ink" : "UFdJQzEuMDUAAJgAHwEAAAAA\/\/8U\/\/\/\/\/wMABMQAhAADACFAksMBlmv\/\/\/\/\/BhcBlmv\/\/\/\/\/BRoBlmv\/\/\/\/\/BhwBlmv\/\/\/\/\/BiEBlmv\/\/\/\/\/BR0Blmv\/\/\/\/\/BBoBlmv\/\/\/\/\/BRwBlmv\/\/\/\/\/AxgBlmv\/\/\/\/\/BBYBlmv\/\/\/\/\/AxcBlmv\/\/\/\/\/AhQBlmv\/\/\/\/\/AhEBljf\/\/\/\/\/DgERAAD+D\/HCwaGCoXFhckFxobPCAZY3\/\/\/\/\/wH88AP0AZZr\/\/\/\/\/\/zwAZZr\/\/\/\/\/\/vtAZZr\/\/\/\/\/\/vtAZZr\/\/\/\/\/\/vuAZZr\/\/\/\/\/\/vrAZZr\/\/\/\/\/\/vsAZZr\/\/\/\/\/\/ztAZZr\/\/\/\/\/\/zpAZZr\/\/\/\/\/\/3rAZZr\/\/\/\/\/\/3sAZZr\/\/\/\/\/\/7pAZZr\/\/\/\/\/\/7qAZZr\/\/\/\/\/\/7sAZZr\/\/\/\/\/wDqAZZr\/\/\/\/\/wDsAZZr\/\/\/\/\/wHtAZZr\/\/\/\/\/wLtAZZr\/\/\/\/\/wTuAZZr\/\/\/\/\/wXwAZY3\/\/\/\/\/ywH8KqqKgIAAFVVVVVVAPfYypp6bUs7LSsrDRsKOkpZmJeGxMTD8eHh9OXV2dm6vKuLjWxaTEspKxkIAZZr\/\/\/\/\/+QBAZYW\/\/\/\/\/wU8A0AA\/wMkNTkqLAGWN\/\/\/\/\/8C8P8HHw8Blmv\/\/\/\/\/8AABljf\/\/\/\/\/AfABAS8Blmv\/\/\/\/\/7wUBljf\/\/\/\/\/AfAFAV8Bljf\/\/\/\/\/CO8IVVUAj46uvLvs6ekBlmv\/\/\/\/\/+BEBlmv\/\/\/\/\/+REBlmv\/\/\/\/\/+hEBlmv\/\/\/\/\/+hUBlmv\/\/\/\/\/\/BQBlmv\/\/\/\/\/\/RMBlmv\/\/\/\/\/\/hcBlmv\/\/\/\/\/\/xUBlmv\/\/\/\/\/ABUBlmv\/\/\/\/\/ARcBlmv\/\/\/\/\/AxQBlmv\/\/\/\/\/BBMBlmv\/\/\/\/\/BhUBlmv\/\/\/\/\/BxEBlmv\/\/\/\/\/CBABljf\/\/\/\/\/CAoQAAAA6sq8nYxfTj4Blmv\/\/\/\/\/EQABlmv\/\/\/\/\/Ef4Blmv\/\/\/\/\/EPwBlmv\/\/\/\/\/EvkBljf\/\/\/\/\/ARD3Aq8Bljf\/\/\/\/\/AhDyCv79AZZr\/\/\/\/\/w3sAZZr\/\/\/\/\/wvtAZZr\/\/\/\/\/wrsAZZr\/\/\/\/\/wnoAZZr\/\/\/\/\/wjqAZZr\/\/\/\/\/wbqAZZr\/\/\/\/\/wXoAZZr\/\/\/\/\/wTqAZZr\/\/\/\/\/wPrAZZr\/\/\/\/\/wLpAZZr\/\/\/\/\/wDrAZZr\/\/\/\/\/wDtAZZr\/\/\/\/\/\/\/rAZZr\/\/\/\/\/\/3vAZZr\/\/\/\/\/\/3wAZY3\/\/\/\/\/w778P\/\/VwXVxbaHdmdINygIByg3NgGWa\/\/\/\/\/\/qDQGWFv\/\/\/\/8gtAJUASoAAAAAAAAAACAyFRgpbW18np2cvry8vbybvJqZmoh4h2ZVVUREZVTcAgAAFv\/\/\/\/8FLARwAEUAIVGQ0fABlmv\/\/\/\/\/ABUBlmv\/\/\/\/\/ARIBlmv\/\/\/\/\/AhIBlmv\/\/\/\/\/AhUBlmv\/\/\/\/\/AxMBlmv\/\/\/\/\/AhMBlmv\/\/\/\/\/AhUBlmv\/\/\/\/\/AhQBlmv\/\/\/\/\/AhMBlmv\/\/\/\/\/AhUBlmv\/\/\/\/\/AhIBlmv\/\/\/\/\/AhABljf\/\/\/\/\/DQIRAACqAvLR0bGQoYBwIGCQoKABlmv\/\/\/\/\/APABlmv\/\/\/\/\/\/vABlmv\/\/\/\/\/\/+8Blmv\/\/\/\/\/\/eoBlmv\/\/\/\/\/\/uwBlmv\/\/\/\/\/\/ewBlmv\/\/\/\/\/\/ugBlmv\/\/\/\/\/\/uoBlmv\/\/\/\/\/\/usBlmv\/\/\/\/\/\/ugBlmv\/\/\/\/\/\/+oBlmv\/\/\/\/\/\/+wBlmv\/\/\/\/\/AOkBlmv\/\/\/\/\/AO0Blmv\/\/\/\/\/AO4Blmv\/\/\/\/\/Au0Bljf\/\/\/\/\/TgLvqqqqCgAAAFVVVVUBAAAAAAAAAADz9dbFx5eXeFhJOjoaHAsLO1tZqZim5tTD8uDQ9OTW+dm5y7qainppWEg2NjMREyYXKEpKSmx8e6yciruqmbqol6aWlZSEc4NzcZJxcmIBlmv\/\/\/\/\/BxABABb\/\/\/\/\/V2QGHAD\/V1VVVVVVBQAAAAAAAABUVVVVVfU\/JCUmJxYHCBcpKTlbfHuerpzOzcvb2snZxrbUw6LCsJCik3SHeGhrW0tMSzs8SjpKSUhIVlZlVVNzYmKAcHGDhISXl5iZiXmKallJSTgoJxYYBhQ0Q1P2AZYW\/\/\/\/\/wX4BiAAAQBEIFCg4AGWa\/\/\/\/\/8AEAGWa\/\/\/\/\/8AFQGWa\/\/\/\/\/8AEwGWa\/\/\/\/\/8AEQGWa\/\/\/\/\/8AEwGWa\/\/\/\/\/8AEgGWa\/\/\/\/\/8AEAGWa\/\/\/\/\/8AEwGWa\/\/\/\/\/8AEwGWa\/\/\/\/\/8AEQGWa\/\/\/\/\/8AFQGWa\/\/\/\/\/8AEgGWa\/\/\/\/\/8AEgGWa\/\/\/\/\/8AEwGWa\/\/\/\/\/8AEgGWa\/\/\/\/\/8AEQGWN\/\/\/\/\/8KABEAAAjw4ODAoMCQcFFjAgAAFv\/\/\/\/8ESAYoAAAACAQHCgGWa\/\/\/\/\/8TAAGWa\/\/\/\/\/8XAAGWa\/\/\/\/\/8YAAGWa\/\/\/\/\/8eAAGWa\/\/\/\/\/8bAAGWa\/\/\/\/\/8ZAAGWa\/\/\/\/\/8b\/wGWa\/\/\/\/\/8YAAGWa\/\/\/\/\/8W\/wGWa\/\/\/\/\/8Y\/wGWa\/\/\/\/\/8V\/wGWa\/\/\/\/\/8U\/gGWa\/\/\/\/\/8V\/gGWa\/\/\/\/\/8S\/gGWa\/\/\/\/\/8R\/gGWN\/\/\/\/\/8FEP2qAi4bOyo4AZZr\/\/\/\/\/x\/2AZYAAAAAAAAAAA=="
    },
    {
      "word" : "U V W",
      "count" : 3,
      "type" : 4,
      "ink" : "UFdJQzEuMDUAAIAAHwEAAAAA\/\/8U\/\/\/\/\/wMABfAAWAACAEAwgNHxAZZr\/\/\/\/\/wEWAZZr\/\/\/\/\/wEUAZZr\/\/\/\/\/wESAZZr\/\/\/\/\/wEVAZZr\/\/\/\/\/wATAZZr\/\/\/\/\/wESAZZr\/\/\/\/\/wAWAZZr\/\/\/\/\/wAUAZZr\/\/\/\/\/wATAZZr\/\/\/\/\/wEXAZZr\/\/\/\/\/wEUAZZr\/\/\/\/\/wEUAZZr\/\/\/\/\/wIWAZZr\/\/\/\/\/wITAZZr\/\/\/\/\/wMSAZZr\/\/\/\/\/wQUAZY3\/\/\/\/\/wEDEQD0AZY3\/\/\/\/\/xEFEAAAoKoC1cW3pnd4VzgqGRlManq7utoBlmv\/\/\/\/\/CvABlmv\/\/\/\/\/Ce8Blmv\/\/\/\/\/CPABlmv\/\/\/\/\/CesBlmv\/\/\/\/\/B+wBlmv\/\/\/\/\/BuwBlmv\/\/\/\/\/BukBlmv\/\/\/\/\/BukBlmv\/\/\/\/\/BOsBlmv\/\/\/\/\/BecBlmv\/\/\/\/\/BOoBlmv\/\/\/\/\/A+oBlmv\/\/\/\/\/AugBlmv\/\/\/\/\/AusBlmv\/\/\/\/\/AewBlmv\/\/\/\/\/AesBlmv\/\/\/\/\/Ae4Blmv\/\/\/\/\/AfABljf\/\/\/\/\/DQDwqioAAODBsJCAkWFTMGGRocIBlmv\/\/\/\/\/AhABlmv\/\/\/\/\/AhABlmv\/\/\/\/\/AhEBlmv\/\/\/\/\/AxUBlmv\/\/\/\/\/AhQBlmv\/\/\/\/\/AxMBlmv\/\/\/\/\/AhcBlmv\/\/\/\/\/AxYBlmv\/\/\/\/\/AhUBlmv\/\/\/\/\/AxgBlmv\/\/\/\/\/AxUBlmv\/\/\/\/\/AxQBlmv\/\/\/\/\/BBYBlmv\/\/\/\/\/BBQBlmv\/\/\/\/\/AxIBlmv\/\/\/\/\/BBQBljf\/\/\/\/\/BwQRAAD09NXFppV1AZZr\/\/\/\/\/xQaAZYW\/\/\/\/\/wZoA0AAFQAENFGj1PYBlmv\/\/\/\/\/CBQBlmv\/\/\/\/\/BxIBlmv\/\/\/\/\/BhEBlmv\/\/\/\/\/BxQBlmv\/\/\/\/\/BhMBlmv\/\/\/\/\/BhEBlmv\/\/\/\/\/BxQBlmv\/\/\/\/\/BhIBlmv\/\/\/\/\/BhEBlmv\/\/\/\/\/BhMBlmv\/\/\/\/\/BREBlmv\/\/\/\/\/BRABlmv\/\/\/\/\/BREBljf\/\/\/\/\/FQUQAAAAqKoC5PbVtbWVhHVVREY3BRY1Z3aW19b2AZZr\/\/\/\/\/wftAZZr\/\/\/\/\/wbtAZZr\/\/\/\/\/wbsAZZr\/\/\/\/\/wboAZZr\/\/\/\/\/wbpAZZr\/\/\/\/\/wXqAZZr\/\/\/\/\/wXlAZZr\/\/\/\/\/wXoAZZr\/\/\/\/\/wXpAZZr\/\/\/\/\/wXnAZZr\/\/\/\/\/wXpAZZr\/\/\/\/\/wXrAZZr\/\/\/\/\/wXpAZZr\/\/\/\/\/wXsAZZr\/\/\/\/\/wXuAZY3\/\/\/\/\/wgG8KqqAMWldmVGNiYlAZZr\/\/\/\/\/xX7AZYW\/\/\/\/\/wVcBRAAAABAcHDA8gGWa\/\/\/\/\/8BEQGWa\/\/\/\/\/8DFwGWa\/\/\/\/\/8CFgGWa\/\/\/\/\/8DFAGWa\/\/\/\/\/8CGQGWa\/\/\/\/\/8DFgGWa\/\/\/\/\/8CFQGWa\/\/\/\/\/8DGQGWa\/\/\/\/\/8BFgGWa\/\/\/\/\/8CFQGWa\/\/\/\/\/8BGAGWa\/\/\/\/\/8CFQGWa\/\/\/\/\/8BEwGWa\/\/\/\/\/8CFAGWN\/\/\/\/\/8SAhEAAKCqCvLywrKigmNkRAQVNXaXmOno6AGWa\/\/\/\/\/8I7gGWN\/\/\/\/\/8BB\/AC9gGWN\/\/\/\/\/8SB++qqgoAAPbm5sWlpHRTVEMFM1Rjg7TE0wGWa\/\/\/\/\/8EEAGWN\/\/\/\/\/8BBBAA9AGWa\/\/\/\/\/8EEgGWN\/\/\/\/\/8BBBEA8wGWN\/\/\/\/\/8QBREAAKCqAOTDtaSDdFRTNSUlRFWmtsYBlmv\/\/\/\/\/Bu4Blmv\/\/\/\/\/B+4Blmv\/\/\/\/\/Bu0Blmv\/\/\/\/\/B+YBlmv\/\/\/\/\/BucBlmv\/\/\/\/\/BuYBlmv\/\/\/\/\/B+ABlmv\/\/\/\/\/BuIBlmv\/\/\/\/\/BuQBlmv\/\/\/\/\/Bt8Blmv\/\/\/\/\/B+EBlmv\/\/\/\/\/BuMBlmv\/\/\/\/\/COQBlmv\/\/\/\/\/B+oBljf\/\/\/\/\/Cwbuqqoq6KaHZ1c3NycVKBgBlmv\/\/\/\/\/FP8BlgAAAAAAAAAA"
    },
    {
      "word" : "X Y Z",
      "count" : 3,
      "type" : 4,
      "ink" : "UFdJQzEuMDUAAFoAHwEAAAAA\/\/8U\/\/\/\/\/wMAB2QBHAABACExMlSJrL0Blmv\/\/\/\/\/Eg8Blmv\/\/\/\/\/EQ4Blmv\/\/\/\/\/EAwBlmv\/\/\/\/\/EhABlmv\/\/\/\/\/EQ8Blmv\/\/\/\/\/EA8Blmv\/\/\/\/\/ExIBlmv\/\/\/\/\/EREBlmv\/\/\/\/\/EA8Blmv\/\/\/\/\/EhMBlmv\/\/\/\/\/EREBlmv\/\/\/\/\/DxABlmv\/\/\/\/\/EBIBlmv\/\/\/\/\/EBABlmv\/\/\/\/\/DhABlmv\/\/\/\/\/EBEBljf\/\/\/\/\/FQ4QAAAAAIAC\/v7t3N28q7ybmYqJZ2hnRVhGBRSKAZYW\/\/\/\/\/wssA1QAX1UVIjMFJleaqqrd7d0Blmv\/\/\/\/\/7xABlmv\/\/\/\/\/8BABlmv\/\/\/\/\/8RABlmv\/\/\/\/\/7RMBlmv\/\/\/\/\/7RMBlmv\/\/\/\/\/7xIBlmv\/\/\/\/\/6hcBlmv\/\/\/\/\/7BYBlmv\/\/\/\/\/7RUBlmv\/\/\/\/\/6xkBlmv\/\/\/\/\/7RcBlmv\/\/\/\/\/7xUBlmv\/\/\/\/\/7hgBlmv\/\/\/\/\/7xUBlmv\/\/\/\/\/8hMBlmv\/\/\/\/\/8RMBljf\/\/\/\/\/CvQRVVUF6+rHp6V0Y3NiwwGWFv\/\/\/\/8HPAQ8AAAAQCBCUaTF5QGWN\/\/\/\/\/8bBhAAAAAAoKoq5tXV1cTUtbTEpJOTdGN2VDUlFTY2h5iX6NfoAZZr\/\/\/\/\/wjvAZZr\/\/\/\/\/wjvAZZr\/\/\/\/\/wfwAZZr\/\/\/\/\/wntAZZr\/\/\/\/\/wfvAZZr\/\/\/\/\/wfwAZZr\/\/\/\/\/wfuAZY3\/\/\/\/\/wwH8KqqCgDm9sWllXRUVEQ1E0EBlmv\/\/\/\/\/BBABwhb\/\/\/\/\/BLQESAEAAEBggJABlmv\/\/\/\/\/\/xEBlmv\/\/\/\/\/ABMBlmv\/\/\/\/\/\/xYBlmv\/\/\/\/\/\/xkBlmv\/\/\/\/\/\/xYBlmv\/\/\/\/\/\/hMBlmv\/\/\/\/\/\/hQBljf\/\/\/\/\/Af4RAfIBljf\/\/\/\/\/Cf0QVQUA4sHCoZHBkIBwAZZr\/\/\/\/\/wMQAQAW\/\/\/\/\/wW4BUQAAAAhJBUbDgGWa\/\/\/\/\/8RAAGWa\/\/\/\/\/8VAQGWa\/\/\/\/\/8UAAGWa\/\/\/\/\/8SAAGWa\/\/\/\/\/8UAAGWa\/\/\/\/\/8RAAGWa\/\/\/\/\/8QAAGWN\/\/\/\/\/8WEgAAAABUVQUPDg8NCwwJCBsXFhRiYmV1maq73t3NAZY3\/\/\/\/\/wLwDgXv3gGWN\/\/\/\/\/8C8BAF\/+4Bljf\/\/\/\/\/FvAQVVVVAAAA7dz82rnYpqaUg3OBckQ1NSoqKh4NHQGWa\/\/\/\/\/8QAAGWN\/\/\/\/\/8BEAEADgGWa\/\/\/\/\/8RAAGWN\/\/\/\/\/8BEAAADgGWN\/\/\/\/\/8SEAAAAAAAAA8NDwwLDAkJGBgXOCdGRFRStQGWFv\/\/\/\/8F0AUQAaoCEiMZHR4Blmv\/\/\/\/\/Ff8Blmv\/\/\/\/\/EwABlmv\/\/\/\/\/EwABlmv\/\/\/\/\/Fv8Blmv\/\/\/\/\/FAABlmv\/\/\/\/\/FAABlmv\/\/\/\/\/FgABlmv\/\/\/\/\/FAABlmv\/\/\/\/\/EwABlmv\/\/\/\/\/FQABlmv\/\/\/\/\/EwABlmv\/\/\/\/\/EQABljf\/\/\/\/\/BRIAoAIODB0aGgGWa\/\/\/\/\/8j+wHoAAAAAAAAAAA="
    },
    {
      "word" : "1 2 3 4 5",
      "count" : 5,
      "type" : 3,
      "ink" : "UFdJQzEuMDUAAFAAHwEAAAAA\/\/8U\/\/\/\/\/wMAIAQBnACqqqqqqgJRVQAiNTQ0Rmh4eKuZiaqZeIh3dlZVNEcjQXFxgMLCsfLi4gGWa\/\/\/\/\/\/\/EAGWN\/\/\/\/\/8B\/hAB8QGWa\/\/\/\/\/\/+EQGWN\/\/\/\/\/8B\/xAB8gGWN\/\/\/\/\/8r\/xFVRFRVVVVVVRUAAPHS0cGwoZCBsIFxQXFDJSYXFxcKGRkcGxosGxsaKRgqJzdUMjMnKCkuLR4Blmv\/\/\/\/\/EQEBlmv\/\/\/\/\/EQEBlmv\/\/\/\/\/EAEBlmv\/\/\/\/\/FAEBlmv\/\/\/\/\/EQEBlmv\/\/\/\/\/EQEBljf\/\/\/\/\/DhIAAAAAAB8ODw0MDAoIGBcWN0a8AZYW\/\/\/\/\/xo0AqwAqqqqqgIABDBRcWFleImtfHxuTDwtKxscGRlIRmWUs7LxAZY3\/\/\/\/\/wH+EAH1AZZr\/\/\/\/\/\/kUAZZr\/\/\/\/\/\/gTAZZr\/\/\/\/\/\/kSAZZr\/\/\/\/\/\/YVAZZr\/\/\/\/\/\/cUAZZr\/\/\/\/\/\/gSAZZr\/\/\/\/\/\/cTAZY3\/\/\/\/\/xv5EFUVAKqqqirn5cW0k4JhYUQnGBgbLCw\/TT0\/Piw8KxgpJxcBlmv\/\/\/\/\/GPsBlhb\/\/\/\/\/BJQDOACqACM2ODoBlmv\/\/\/\/\/EPsBlmv\/\/\/\/\/EPwBlmv\/\/\/\/\/EvsBlmv\/\/\/\/\/E\/sBljf\/\/\/\/\/DRD8qgBAAU4uKykIJiVUc3HAssMBljf\/\/\/\/\/AvoQBfb4AZZr\/\/\/\/\/\/cSAZY3\/\/\/\/\/yX4EFVVoaqqKgBAVQH4+Ne2pZVjg1E1JycoS0xNT049Pz0bGwkYN0ZUcoGBwsTG+frqAZZr\/\/\/\/\/\/IQAZY3\/\/\/\/\/wHyEAHuAZZr\/\/\/\/\/+8QAZZr\/\/\/\/\/\/AOAZZr\/\/\/\/\/\/AMAZZr\/\/\/\/\/+4OAZZr\/\/\/\/\/\/ALAZZr\/\/\/\/\/\/AKAZY3\/\/\/\/\/wjvClVVAI59bEpJKBcWAZZr\/\/\/\/\/+oCAZYW\/\/\/\/\/wRUBQQAFQAxUYGQAZZr\/\/\/\/\/\/8QAZZr\/\/\/\/\/wARAZZr\/\/\/\/\/wASAZZr\/\/\/\/\/wAWAZZr\/\/\/\/\/\/8TAZZr\/\/\/\/\/\/8RAZZr\/\/\/\/\/\/8SAZY3\/\/\/\/\/xz\/EFVVAACqqqoA4vLRwrGhkcGAcVJFJxkICSw7O11cWmtZV1hWVgGWa\/\/\/\/\/8W7wGWFv\/\/\/\/8D+AUUABVBksEBlmv\/\/\/\/\/\/hABlmv\/\/\/\/\/\/RkBlmv\/\/\/\/\/\/BoBlmv\/\/\/\/\/\/BwBlmv\/\/\/\/\/+iABlmv\/\/\/\/\/+xwBlmv\/\/\/\/\/\/BoBlmv\/\/\/\/\/+xsBlmv\/\/\/\/\/\/BkBlmv\/\/\/\/\/\/RYBlmv\/\/\/\/\/\/RgBlmv\/\/\/\/\/\/RUBlmv\/\/\/\/\/\/xMBlmv\/\/\/\/\/\/hMBljf\/\/\/\/\/Cf8QAAAA8PDRsaNyY3ZFAZZr\/\/\/\/\/xEJAQAW\/\/\/\/\/whEBzwAVVUAIlJTUkKlt+gBljf\/\/\/\/\/LPYRVVVVAAAAAABAVVUA6djpyLenlYVzY0OCQyYYGBkLCxsNCwsLGhgZNydWRFNzcoGxoqTYybnNzb0Bljf\/\/\/\/\/AvAMBa+fAZZr\/\/\/\/\/+4JAZZr\/\/\/\/\/\/AIAZZr\/\/\/\/\/\/AGAZZr\/\/\/\/\/+4GAZY3\/\/\/\/\/wHwBQE\/AZYW\/\/\/\/\/w5oBzQAAACiCgIFCAkLDg0LHQwbHCopAZZr\/\/\/\/\/yD3AZYAAAAAAAAAAA=="
    },
    {
      "word" : "6 7 8 9 0",
      "count" : 5,
      "type" : 3,
      "ink" : "UFdJQzEuMDUAAGEAHwEAAAAA\/\/8U\/\/\/\/\/wMAC5ACCAD\/XxUTJRYWFhoJCg4NHgGWa\/\/\/\/\/\/wAwGWN\/\/\/\/\/8B8AQBTwGWa\/\/\/\/\/\/uBwGWa\/\/\/\/\/\/vCAGWa\/\/\/\/\/\/wCAGWa\/\/\/\/\/\/uDAGWa\/\/\/\/\/\/vDQGWa\/\/\/\/\/\/wDAGWa\/\/\/\/\/\/vEQGWa\/\/\/\/\/\/xEAGWa\/\/\/\/\/\/yEAGWa\/\/\/\/\/\/yFQGWa\/\/\/\/\/\/0FAGWa\/\/\/\/\/\/2EwGWa\/\/\/\/\/\/2FgGWa\/\/\/\/\/\/3FgGWa\/\/\/\/\/\/5FAGWa\/\/\/\/\/\/6FwGWa\/\/\/\/\/\/8FQGWa\/\/\/\/\/\/9FAGWa\/\/\/\/\/\/+FQGWa\/\/\/\/\/8AFAGWa\/\/\/\/\/8BEgGWa\/\/\/\/\/8DEwGWN\/\/\/\/\/8KBREAAAD2+NmqrIxrb049AZY3\/\/\/\/\/wIQAQofLQGWN\/\/\/\/\/8XEPyqqqr6\/z9eXY6LipmYl6Wlk6KhgJOUhYqKam5fTgGWa\/\/\/\/\/\/u\/QGWa\/\/\/\/\/\/v\/gGWa\/\/\/\/\/\/v\/wGWa\/\/\/\/\/\/tAQGWa\/\/\/\/\/\/vAgGWa\/\/\/\/\/\/wAwGWN\/\/\/\/\/8L7wVVVRVeTVxaWWdmVWRjQgGWa\/\/\/\/\/\/6EgGWFv\/\/\/\/8G+AI4AAAAMDIlGQwfAZZr\/\/\/\/\/xMAAZZr\/\/\/\/\/xEAAZZr\/\/\/\/\/xAAAZY3\/\/\/\/\/xIS\/yoiAFQFHx4eDBoKGAcJFjUzYGKDtcbHAZZr\/\/\/\/\/\/cQAZZr\/\/\/\/\/\/cQAZZr\/\/\/\/\/\/cQAZZr\/\/\/\/\/\/UTAZZr\/\/\/\/\/\/UTAZZr\/\/\/\/\/\/cTAZZr\/\/\/\/\/\/UWAZZr\/\/\/\/\/\/YVAZZr\/\/\/\/\/\/gTAZZr\/\/\/\/\/\/YWAZZr\/\/\/\/\/\/gUAZZr\/\/\/\/\/\/kSAZZr\/\/\/\/\/\/gTAZY3\/\/\/\/\/wH5EQH2AZY3\/\/\/\/\/wr6EFVVBdXFxJOSo3JiQqQBlhb\/\/\/\/\/BRwDCAEAAAMGBwsPAZZr\/\/\/\/\/xEAAZZr\/\/\/\/\/xUAAZZr\/\/\/\/\/xMAAZZr\/\/\/\/\/xIAAZYW\/\/\/\/\/wpsBSQAX1UFEiMGFihKOm5uXgGWN\/\/\/\/\/8C8AgFf48Bljf\/\/\/\/\/SfAJVVVVFQAAAAAAAFRVVVVV1b+qAp+Orp2bm5mIqIV1hIJicWFiVUZHOjsqLR0bLiwrKzopODc2RkRUYnJhoZOlyMjK7Nzc3r2rrZx7fFpZOTgmCBYzUmGhs6Po6NkBljf\/\/\/\/\/AgzwCvz8AZZr\/\/\/\/\/w7uAZZr\/\/\/\/\/w3wAZZr\/\/\/\/\/wzwAZZr\/\/\/\/\/w3uAZY3\/\/\/\/\/wEN8AL7AZZr\/\/\/\/\/wzvAZY3\/\/\/\/\/xIK8KqqqqoK6Pno1ufWtaWTc5NyQzI0IyJ5AZYW\/\/\/\/\/0AkBmQA\/\/\/\/f1VVVQUAAKiqqqpQVQAiMlVURUVERjY2NygnGRgIGCg4aGd3lqWUtLSi0rKwwaKilXZmWDk4Cxo6a4mJqaiXuJaVhGNSdSFQkaKi4\/T0AZZr\/\/\/\/\/\/wSAZZr\/\/\/\/\/\/wSAZZr\/\/\/\/\/\/wRAZZr\/\/\/\/\/\/wTAZZr\/\/\/\/\/\/wSAZZr\/\/\/\/\/\/wRAZZr\/\/\/\/\/\/wTAZZr\/\/\/\/\/\/wSAZZr\/\/\/\/\/\/0QAZZr\/\/\/\/\/\/0SAZY3\/\/\/\/\/w39EFVVAADj49KyspJxkYBRQyYGAZZr\/\/\/\/\/xP+AZYW\/\/\/\/\/xqIB2AAVVVVVVVVBRIjNUY3WVloeol4mpmZqbioyLbG1dXV9OTjAZY3\/\/\/\/\/wL+EQXy4QGWN\/\/\/\/\/8O\/xABAAAK4cDSspOGdmdZSisdHj0Bljf\/\/\/\/\/BRD7qgJvfr\/OvQGWN\/\/\/\/\/8CDfAK7PsBlmv\/\/\/\/\/Cu8Bljf\/\/\/\/\/AQnwAvgBlmv\/\/\/\/\/B+4Blmv\/\/\/\/\/BvABlmv\/\/\/\/\/BPABljf\/\/\/\/\/GgTvqv\/\/\/1dVBfLi8eDB08SlqIh4eltaPCsbHCtKe3qYqKaVAZZr\/\/\/\/\/\/EiAZYAAAAAAAAAAA=="
    },
    {
      "word" : "* ! $ ? ^",
      "count" : 5,
      "type" : 2,
      "ink" : "UFdJQzEuMDUAAHIAHwEAAAAA\/\/8U\/\/\/\/\/wMABhgBTAAFAAMxUXLY7AGWa\/\/\/\/\/8OEAGWa\/\/\/\/\/8TEwGWa\/\/\/\/\/8TEgGWa\/\/\/\/\/8REQGWa\/\/\/\/\/8UFAGWa\/\/\/\/\/8TEgGWa\/\/\/\/\/8SEQGWa\/\/\/\/\/8TEwGWa\/\/\/\/\/8SEgGWa\/\/\/\/\/8REQGWa\/\/\/\/\/8SEgGWN\/\/\/\/\/8BEBAA\/wGWN\/\/\/\/\/8OEA8AAAAA7s3evJuriYh4Z1ZmVUUBlmv\/\/\/\/\/DxEBlhb\/\/\/\/\/BLwCQABVABJGZ4oBlmv\/\/\/\/\/7w4Blmv\/\/\/\/\/7REBlmv\/\/\/\/\/7BIBlmv\/\/\/\/\/6BYBlmv\/\/\/\/\/6xMBlmv\/\/\/\/\/7hIBlmv\/\/\/\/\/6xQBlmv\/\/\/\/\/7RIBlmv\/\/\/\/\/7xIBlmv\/\/\/\/\/7RUBlmv\/\/\/\/\/7xIBlmv\/\/\/\/\/8REBlmv\/\/\/\/\/8hMBljf\/\/\/\/\/AfMRAfsBljf\/\/\/\/\/CvYQVVUB6cfGtZSEYlKCkQGWFv\/\/\/\/8FDAIgABUBITFxcOIBlmv\/\/\/\/\/\/RIBlmv\/\/\/\/\/\/BYBlmv\/\/\/\/\/+x0Blmv\/\/\/\/\/\/BoBlmv\/\/\/\/\/\/BkBlmv\/\/\/\/\/\/BsBlmv\/\/\/\/\/\/BoBlmv\/\/\/\/\/\/BgBlmv\/\/\/\/\/\/RwBlmv\/\/\/\/\/\/RkBlmv\/\/\/\/\/\/RcBlmv\/\/\/\/\/\/RkBlmv\/\/\/\/\/\/hcBlmv\/\/\/\/\/\/hQBlmv\/\/\/\/\/\/hYBlmv\/\/\/\/\/\/hIBlmv\/\/\/\/\/\/hABljf\/\/\/\/\/CP8QFVQA0cGxkHCSUcYBlhb\/\/\/\/\/BCQBWAGqACImGx0Blmv\/\/\/\/\/GP8Blmv\/\/\/\/\/G\/4Blmv\/\/\/\/\/Hf4Blmv\/\/\/\/\/Iv0Blmv\/\/\/\/\/Hv0Blmv\/\/\/\/\/Gf4Blmv\/\/\/\/\/Gf0Blmv\/\/\/\/\/Ff0Blmv\/\/\/\/\/E\/0Bljf\/\/\/\/\/CBL8qqoALz4sKzkoJyYBlmv\/\/\/\/\/FvoBlhb\/\/\/\/\/E7ADXACqAhARFYAwYLBAQDBAYHCxsKHg0cDx8dIBljf\/\/\/\/\/EP8QVVVVVQDh4eHhwtKyoZKBYXNjQ1O5AgAAFv\/\/\/\/8ImAMEAqr6AEQxM2RUdDIaAgAAFv\/\/\/\/8pUAV0AP\/\/f1VVVVUVAAAAQmJjVFRGNyY5GioOHR4\/Pk1tXWuLeoiIhoWUhIKRgYCCg3R3eGhcXFwBljf\/\/\/\/\/AhAFAE9OAZY3\/\/\/\/\/yoQBQAAAABVVVVVVVUPPk0\/PTtMO0lYV0ZUVFOSgZKThbi5qc28rL6unZ6OfG1sW0w7KRkoFhkYAZZr\/\/\/\/\/+v5AZYW\/\/\/\/\/wWwBDAAVQEyUqLi8QGWa\/\/\/\/\/\/\/FQGWa\/\/\/\/\/8AFAGWa\/\/\/\/\/\/\/EwGWa\/\/\/\/\/8AFwGWa\/\/\/\/\/8AFQGWa\/\/\/\/\/8AFQGWa\/\/\/\/\/8BGAGWa\/\/\/\/\/8AGAGWa\/\/\/\/\/8BFgGWa\/\/\/\/\/8AGgGWa\/\/\/\/\/8AFwGWa\/\/\/\/\/8AFgGWa\/\/\/\/\/8AGAGWa\/\/\/\/\/\/\/FQGWa\/\/\/\/\/\/\/EwGWa\/\/\/\/\/\/+FAGWN\/\/\/\/\/8J\/hFVBQDy8sGx0YFhMzsBlhb\/\/\/\/\/BQwFMAAAAIAwUIHwAZZr\/\/\/\/\/wESAZZr\/\/\/\/\/wATAZZr\/\/\/\/\/wEZAZZr\/\/\/\/\/wAXAZZr\/\/\/\/\/wAVAZZr\/\/\/\/\/wAYAZZr\/\/\/\/\/wAWAZZr\/\/\/\/\/wAVAZZr\/\/\/\/\/wAZAZZr\/\/\/\/\/wAXAZZr\/\/\/\/\/wAXAZZr\/\/\/\/\/wAaAZZr\/\/\/\/\/wAYAZZr\/\/\/\/\/wAVAZZr\/\/\/\/\/wAYAZZr\/\/\/\/\/wAUAZZr\/\/\/\/\/wATAZZr\/\/\/\/\/wATAZZr\/\/\/\/\/wASAZY7\/\/\/\/\/wEAEKsBlhb\/\/\/\/\/NrgFhAD\/qqqqCgAAQFVVVRUAAEFikXGDhaa6mop9bUw+LSweHAoLGihJR1ZlZGOBgZCyw7XWxre3t5aXhmVlVDNkUkMzQ0VUQwGWa\/\/\/\/\/8PEgGWFv\/\/\/\/8ILAaQAQAAADBQcGBwYaGRAZZr\/\/\/\/\/wUXAZYW\/\/\/\/\/zIQB7QAqqqqqqoCAAAAAAAAADJCQ2WGl9m4t7i3p6eWhYV0ZJVUZSRRYVFgcYFxcZKCgZOCg5SEhISFdHR0dHRTU2RjAZZr\/\/\/\/\/woQAZYAAAAAAAAAAA=="
    },
    {
      "word" : "& @ ( ) %",
      "count" : 5,
      "type" : 2,
      "ink" : "UFdJQzEuMDUAAEoAHwEAAAAA\/\/8U\/\/\/\/\/wMAR5QCGAL\/\/\/\/\/\/\/\/\/\/\/\/\/\/\/\/\/76qqAgAiI0U1NURFVlZWZ2Z3eId3iYd4iJmImZmIuqmZyrqpurq5ysm5yci42Li2x7amtbSUo6KCkYFgoXGCU0U1JRcYGAoLCh4+PgGWa\/\/\/\/\/8QBQGWN\/\/\/\/\/8BEAQATgGWa\/\/\/\/\/8RBgGWN\/\/\/\/\/8BEAUAbgGWN\/\/\/\/\/9bEAYAAEBVVVVVVVUBAACgqqqqqqqqigAAAH5tnIqIt6ak08HB49PU6OjZ69zL3s7Mz72srYuKinh4ZmVkk3OQcWNjVFZHRykqKRsMGyxMS2tqaXqIeJeHhoWFhIODc5Nzc0JCMkQTFQcWCQgIBwgJCQgKCQcBlmv\/\/\/\/\/HQABlhb\/\/\/\/\/UUwEyAD\/X1VVVRUAAICqqqoCAACqqqr+\/wMyMlU0KCgIFxc5OChIR0ZXRlVUU1OCcoCCU1NENjUmGBcXCRgXN0dGVmVUY2NSgmKhFhEiNTYnGCkbCQkpKDdXRlVlY2OCcXGAgnKGdnh8fGwBljf\/\/\/\/\/Au\/6D09PAZZr\/\/\/\/\/+7+AZZr\/\/\/\/\/+8AAZZr\/\/\/\/\/\/ABAZZr\/\/\/\/\/+0EAZY3\/\/\/\/\/wHvBQF\/AZY3\/\/\/\/\/wXvClUBz77+\/NoBlmv\/\/\/\/\/9hEBlmv\/\/\/\/\/+BEBlmv\/\/\/\/\/+hABlmv\/\/\/\/\/+hMBlmv\/\/\/\/\/\/BIBlmv\/\/\/\/\/\/REBlmv\/\/\/\/\/\/xQBlmv\/\/\/\/\/ABMBlmv\/\/\/\/\/AREBlmv\/\/\/\/\/BBMBlmv\/\/\/\/\/BREBlmv\/\/\/\/\/BhABljf\/\/\/\/\/BQgQAADpysysjQGWN\/\/\/\/\/8BEAgAbwGWa\/\/\/\/\/8QBAGWa\/\/\/\/\/8TBAGWa\/\/\/\/\/8RAgGWa\/\/\/\/\/8QAgGWa\/\/\/\/\/8SAAGWa\/\/\/\/\/8R\/gGWa\/\/\/\/\/8Q\/gGWa\/\/\/\/\/8R+wGWN\/\/\/\/\/8EEPqqAH9+fGoBlmv\/\/\/\/\/I+oBlhb\/\/\/\/\/BeAFHABVAUQyU4ToAZZr\/\/\/\/\/\/gRAZZr\/\/\/\/\/\/gRAZZr\/\/\/\/\/\/YXAZZr\/\/\/\/\/\/cUAZZr\/\/\/\/\/\/gTAZZr\/\/\/\/\/\/gVAZZr\/\/\/\/\/\/oTAZZr\/\/\/\/\/\/oTAZZr\/\/\/\/\/\/oVAZZr\/\/\/\/\/\/wUAZZr\/\/\/\/\/\/0TAZZr\/\/\/\/\/\/0VAZZr\/\/\/\/\/\/4TAZZr\/\/\/\/\/\/4SAZZr\/\/\/\/\/\/8UAZZr\/\/\/\/\/wASAZZr\/\/\/\/\/wARAZY3\/\/\/\/\/xABEgAAAAAA8eLjw7SllIR1ZVRmRUYlXgGWFv\/\/\/\/8UNAYoAAUAAAAAACFiYXKUtbSltbW01cS05MPD8tHSAZY3\/\/\/\/\/wIAEAXx8QGWa\/\/\/\/\/\/9EgGWa\/\/\/\/\/\/8EQGWa\/\/\/\/\/\/8EAGWa\/\/\/\/\/\/5EgGWN\/\/\/\/\/8B+hAB9gGWN\/\/\/\/\/8P+BBVVVUV59fnx6anloWGZERVNEPOAgAAFv\/\/\/\/8Q5AdIAFVVVVUAEiNVRWV0ZaanltjXyPr56QGWN\/\/\/\/\/8C9BEF+voBlmv\/\/\/\/\/9RIBljf\/\/\/\/\/AfYQAfoBljf\/\/\/\/\/C\/YRVVUV6ejZt6amdXR1Q4YBlhb\/\/\/\/\/MjwHrABVVVUFAACqqup\/VVUFAxMWFURGZYdlZXRzYpFwUkNERjYnKAgHGDc2VlRUY2NRknByVDc3BwYWNzZGdlVUU\/QCAAAW\/\/\/\/\/yi4BzwBVVUFAKqqqv9\/VQADIzYlVFVzc5GBkHFTNCcGJjU1VFRjcnJxcXFxkYJ1RSYmFgkmJTUlAZZr\/\/\/\/\/+8MAZYAAAAAAAAAAA=="
    },
    {
      "word" : "< > [ ] #",
      "count" : 5,
      "type" : 2,
      "ink" : "UFdJQzEuMDUAAEkAHwEAAAAA\/\/8U\/\/\/\/\/wMAN8gBkABVVVVVVVVVFQAAAAAAABMjRkZXaFhXaWhnaWhYamlYalhYaVdHV0VFV0VFQ0EyIzRJW2t\/bGtrWkhYR0ZINiQkNDM0NKoBlhb\/\/\/\/\/MWAClAAAAAAAAFRVVVVVVVUBEhQlJzpMS047Sjk5Jyg3JTg1RkNQQjNDV2doioqJnJuLnJqKi4l4h2dVZERDVEJSggGWFv\/\/\/\/8xsARYAP\/ff\/fXVVVVAQAAAAAiIzYlGBcIFxgaGgocCxkbGwkLGgoKCAgLCAgFFyYyMlFgUVJSc4Nzo6STxLS08+PjAZZr\/\/\/\/\/wIRAZY3\/\/\/\/\/wECEQDyAZZr\/\/\/\/\/wISAZZr\/\/\/\/\/wEQAZZr\/\/\/\/\/wEQAZZr\/\/\/\/\/wARAZY3\/\/\/\/\/wEAEADwAZY3\/\/\/\/\/xYAEEEUgKqqCtHAsJGAoXFwFQcFGBcWFSYnNydINycBlmv\/\/\/\/\/F\/YBlhb\/\/\/\/\/SBwFSAAAAAAAQFVVVUUEAABUVVVVVVUAEgUXCR0NDg4MCwwKCAUmUlJgYGGSopLDw8Li0dLh4tHy4dDx4MHgsLCwkJCwkHBhYDQmFxkZGQwbCgwbKRspGCgWJicWNDKFAZYW\/\/\/\/\/wYAB0AAVQUyYnKhwdIBljf\/\/\/\/\/Av4RBfLyAZZr\/\/\/\/\/\/0QAZY3\/\/\/\/\/wH+EAHzAZZr\/\/\/\/\/\/4TAZZr\/\/\/\/\/\/0RAZZr\/\/\/\/\/\/4RAZZr\/\/\/\/\/\/0UAZZr\/\/\/\/\/\/0TAZZr\/\/\/\/\/\/4SAZZr\/\/\/\/\/\/0UAZZr\/\/\/\/\/\/0TAZZr\/\/\/\/\/\/4SAZZr\/\/\/\/\/\/0UAZY3\/\/\/\/\/wv+EVVVAfLy4cLCkZGicWIoAZYW\/\/\/\/\/wRwB1QAVABAQXGhAZZr\/\/\/\/\/\/4SAZZr\/\/\/\/\/\/8UAZZr\/\/\/\/\/\/8VAZZr\/\/\/\/\/\/4ZAZZr\/\/\/\/\/\/8VAZZr\/\/\/\/\/\/4UAZZr\/\/\/\/\/\/8VAZZr\/\/\/\/\/\/8TAZZr\/\/\/\/\/\/4SAZZr\/\/\/\/\/\/8UAZZr\/\/\/\/\/\/8SAZZr\/\/\/\/\/\/4QAZY3\/\/\/\/\/w3\/ElVVVQHy4eHCsaGSgZJyUkOnAZYW\/\/\/\/\/wNIBsQAABQZHAGWa\/\/\/\/\/8QAQGWa\/\/\/\/\/8bAQGWa\/\/\/\/\/8fAgGWa\/\/\/\/\/8gAQGWa\/\/\/\/\/8mAgGWa\/\/\/\/\/8hAQGWa\/\/\/\/\/8dAQGWa\/\/\/\/\/8eAQGWa\/\/\/\/\/8aAQGWa\/\/\/\/\/8WAAGWa\/\/\/\/\/8XAAGWa\/\/\/\/\/8UAAGWa\/\/\/\/\/8RAAGWN\/\/\/\/\/8IEf+IWAAPHAsZBzQTJQGWa\/\/\/\/\/\/wCQGWFv\/\/\/\/8EJAZ0ASoAFBcZCwGWa\/\/\/\/\/8V\/wGWa\/\/\/\/\/8Y\/gGWa\/\/\/\/\/8b\/gGWa\/\/\/\/\/8h\/gGWa\/\/\/\/\/8d\/QGWa\/\/\/\/\/8a\/gGWa\/\/\/\/\/8a\/QGWa\/\/\/\/\/8Y\/gGWa\/\/\/\/\/8V\/gGWa\/\/\/\/\/8W\/gGWa\/\/\/\/\/8T\/wGWa\/\/\/\/\/8Q\/gGWN\/\/\/\/\/8MEf8qAlQAHxwcChgJBzZBQWJjAZZr\/\/\/\/\/\/YRAZYAAAAAAAAAAA=="
    },
    {
      "word" : "\/ = { } +",
      "count" : 5,
      "type" : 2,
      "ink" : "UFdJQzEuMDUAAB8AHwEAAAAA\/\/8U\/\/\/\/\/wMAElgCGABVVVVVBRQVFTVHWGp6apybi829zO\/v7QGWa\/\/\/\/\/\/vEgGWa\/\/\/\/\/\/xEQGWa\/\/\/\/\/\/yEQGWa\/\/\/\/\/\/vFAGWa\/\/\/\/\/\/yEwGWa\/\/\/\/\/\/yEQGWa\/\/\/\/\/\/xFAGWa\/\/\/\/\/\/zEQGWa\/\/\/\/\/\/1EQGWa\/\/\/\/\/\/zEQGWN\/\/\/\/\/8O9RBVVVUF6vrZyLenhYV1VGRURO0Blhb\/\/\/\/\/BmgC5ACqAiMkFhcdDwGWa\/\/\/\/\/8QAAGWa\/\/\/\/\/8T\/wGWN\/\/\/\/\/8MEACgqgIADg4cGxoZGBoYBwY8AZYW\/\/\/\/\/xdQAnQBqqqqqqoqExQUFxocLy8eLx0tHh0rHSspKhgXKScBlmv\/\/\/\/\/E\/kBTBb\/\/\/\/\/efQESABVVVVVVVUEAFBVVVVVVQEAAKIIVFVVVREAAAAAAIACExQ0RFZmh3d3h3ZmdnV0dGNzcmJigoKBcHFgcFBQQYFxUFEzJgUVBwgJCAoICQkJCRgXGBYmFBYVQQMFCQkICAgJCAkZBxcaCBkGCUciUmODhKSkk6OSgpGBgpFxcLGRYWJjZERFRkY2ODgnKRgYGBgHGgkJBwomVwGWFv\/\/\/\/9YeAU4AAAAAAAAAAAAVVVVVVUAAAAAAAAAQFUAEiQ0NjZFNUY1REZVRVZVVVVlVHVVY2RjUnNyYXJhYaCBcmNzhHVkdnZ1ZWZVVVQ0VUU0MnMFBgcIBwgHBwkJCQoKCQsLCQsKCgoJGAkYBhoHFwUiCBkKDwGWa\/\/\/\/\/\/wAAGWa\/\/\/\/\/\/wAAGWa\/\/\/\/\/\/uAAGWN\/\/\/\/\/9G8ABVVVVVAAAAAAAAAEBVVVVVpQoNDwwMDAsJCgkJCwkJBgkWCAUFFRYVNiYlNSU2NTU2RTVVRkVVRERUQ0N0Y4GBoZGBg4OVlZWWl4aHdnZmZkRmRTVTISOMAZYW\/\/\/\/\/w54B3AARQAAACFSYIGg0MCw0MDA8NDQAZY3\/\/\/\/\/wL\/EATg0QGWN\/\/\/\/\/8N\/xBVVVUA4eLy0cLBsaGRkXGxcgGWFv\/\/\/\/8F\/AYYAYoAEiYIGw0Blmv\/\/\/\/\/EQABljf\/\/\/\/\/ARABAA8Bljf\/\/\/\/\/EBEBAAAAAAAfHh8dHBwbGgoZFxoXFiR4AZYAAAAAAAAAAA=="
    },
    {
      "word" : "\\ ~ © ®",
      "count" : 4,
      "type" : 2,
      "ink" : "UFdJQzEuMDUAAFcAHwEAAAAA\/\/8U\/\/\/\/\/wMAK7wAQAABAAAAAAAAAAAAPEQSNEaamrrs2trpycjo2djp6Njp2MjYyMjYt6e3loaHhWVlZENkQ1VTEzkBlhb\/\/\/\/\/PnQCTAGqqqqqqgIAAAAAACCqqqoKIDJCQ0NVVFR1ZnV2ZlZXRkVYNxgWJiU0VVVVdXV1hnV1hnZmaFY3Ryc3KBgXGBgHKScXKCcmFycVJxYmKScBlmv\/\/\/\/\/E\/wBABb\/\/\/\/\/I1AF5AD\/VVVVVQAAACgiMzYWBxopKUlZSGlnVmVkZIRygXBSREQ2KCcaGhkaCBYaGAGWa\/\/\/\/\/8W+wEAFv\/\/\/\/8DyAU8AD8lKTwBlmv\/\/\/\/\/7P4Blmv\/\/\/\/\/6gABlmv\/\/\/\/\/6AIBlmv\/\/\/\/\/5AUBlmv\/\/\/\/\/6AYBlmv\/\/\/\/\/6QgBlmv\/\/\/\/\/6QoBlmv\/\/\/\/\/6wsBlmv\/\/\/\/\/7gsBlmv\/\/\/\/\/7Q4Bljf\/\/\/\/\/Ae8NAd4Bljf\/\/\/\/\/AvEQBfvqAZY3\/\/\/\/\/wL3EQX29gGWN\/\/\/\/\/8C\/BEF8vIBlmv\/\/\/\/\/AREBljf\/\/\/\/\/AQIQAPMBljf\/\/\/\/\/BQgRAAD4+f7ezQGWa\/\/\/\/\/8TCwGWa\/\/\/\/\/8SCAGWa\/\/\/\/\/8SBwGWa\/\/\/\/\/8XBgGWa\/\/\/\/\/8VBAGWa\/\/\/\/\/8VAgGWa\/\/\/\/\/8YAAGWa\/\/\/\/\/8W\/gGWa\/\/\/\/\/8U\/AGWa\/\/\/\/\/8W+QGWa\/\/\/\/\/8U+AGWa\/\/\/\/\/8S9wGWa\/\/\/\/\/8S8wGWN\/\/\/\/\/8BEPMC3gGWa\/\/\/\/\/8N8AGWN\/\/\/\/\/8BC\/AC+gGWa\/\/\/\/\/8I7QGWa\/\/\/\/\/8G7wGWa\/\/\/\/\/8F8AGWa\/\/\/\/\/8E7gGWa\/\/\/\/\/8B7gGWa\/\/\/\/\/8B7wGWa\/\/\/\/\/\/97QGWa\/\/\/\/\/\/87wGWa\/\/\/\/\/\/77wGWa\/\/\/\/\/\/37gGWN\/\/\/\/\/8Q9\/D\/\/39VAOjcy5yNfFxNOzobCRgoNiYBlmv\/\/\/\/\/7wsBlhb\/\/\/\/\/TyAHgAABAAD4\/6qqqqoKAFRVFQAAAAAAAEQwUHKRsqKBwZFwYZFQgYKBgZGhoJCgkIGTcnNlVFRFNjU5JygXFhUzM1FhcGJTU1NFRDNGM0VkAhUWJiY4ODdYR1dYZ1ZXVkVVRTVWRc0Blhb\/\/\/\/\/BugHDAD\/DxMkFSssHgGWa\/\/\/\/\/\/u\/wGWa\/\/\/\/\/\/u\/wGWa\/\/\/\/\/\/wAAGWa\/\/\/\/\/\/tAQGWa\/\/\/\/\/\/uAgGWa\/\/\/\/\/\/wAgGWa\/\/\/\/\/\/tBQGWN\/\/\/\/\/8B7wUBbwGWN\/\/\/\/\/8L7wdVVRWPfayrqcjHxeXz4wGWN\/\/\/\/\/8CABAA8OIBljf\/\/\/\/\/BQYQAADnyO7OrwGWa\/\/\/\/\/8VCgGWa\/\/\/\/\/8UCAGWa\/\/\/\/\/8TBgGWa\/\/\/\/\/8ZBQGWa\/\/\/\/\/8XAwGWa\/\/\/\/\/8XAgGWa\/\/\/\/\/8aAAGWa\/\/\/\/\/8Y\/gGWa\/\/\/\/\/8W\/AGWa\/\/\/\/\/8Y+gGWa\/\/\/\/\/8V+QGWa\/\/\/\/\/8U+AGWa\/\/\/\/\/8U9gGWN\/\/\/\/\/8BEvYCrwGWN\/\/\/\/\/8IEPSqqgC8utnHxtPh0AGWN\/\/\/\/\/8C+\/AP+OkBljf\/\/\/\/\/AvLvD+7fAZZr\/\/\/\/\/+30AZZr\/\/\/\/\/\/D3AZZr\/\/\/\/\/\/D4AZY3\/\/\/\/\/wLv+g9fPgGWN\/\/\/\/\/8I8P5fVQAdHRwaKSg3NgGWa\/\/\/\/\/\/qDgGWAAAAAAAAAAA="
    }
  ],
  "device_os" : "iOS",
  "device_model" : "iPad6,7",
  "device_uuid" : "67AF2937-2B66-442C-97E9-65F995BDADB0"
}