{
  "system_name" : "iPhone OS",
  "device_model" : "iPad6,3",
  "system_version" : "9.3.1",
  "total_words" : 21,
  "completed_word" : 21,
  "language_name" : "English",
  "app" : "WritePad iPad",
  "sub_language" : "en_US",
  "device_name" : "Shannon's iPad",
  "language" : "en",
  "words" : [
    {
      "word" : "the",
      "count" : 1,
      "type" : 1,
      "ink" : "UFdJQzEuMDUAAD0APwEAAAD\/AAAU\/\/\/\/\/ywBAAMkA5wAElBQ0gGWa\/\/\/\/\/\/+EAGWa\/\/\/\/\/\/9EQGWa\/\/\/\/\/\/7GgGWa\/\/\/\/\/\/6GwGWa\/\/\/\/\/\/6GgGWa\/\/\/\/\/\/5HwGWa\/\/\/\/\/\/5HQGWa\/\/\/\/\/\/6GgGWa\/\/\/\/\/\/5GgGWa\/\/\/\/\/\/7FgGWa\/\/\/\/\/\/7EwGWN\/\/\/\/\/8L\/BFVVT\/jw6OCYmJCQhJRcgGWa\/\/\/\/\/\/96gEAFv\/\/\/\/8DgAJWASsyQVwBlmv\/\/\/\/\/EvkBlmv\/\/\/\/\/GPYBlmv\/\/\/\/\/IvEBlmv\/\/\/\/\/IfEBlmv\/\/\/\/\/H\/IBlmv\/\/\/\/\/I\/ABlmv\/\/\/\/\/H\/EBlmv\/\/\/\/\/HPQBlmv\/\/\/\/\/HPMBlmv\/\/\/\/\/GPQBlmv\/\/\/\/\/FfYBlmv\/\/\/\/\/FPcBljf\/\/\/\/\/BhD4qgB+bEgmBpABlhb\/\/\/\/\/CLwDiACqAABQYFFjI2LC4QGWa\/\/\/\/\/8BEQGWa\/\/\/\/\/8AFwGWa\/\/\/\/\/8AGAGWa\/\/\/\/\/8AGAGWa\/\/\/\/\/\/\/HQGWa\/\/\/\/\/\/+GwGWa\/\/\/\/\/\/+GgGWa\/\/\/\/\/\/+GwGWa\/\/\/\/\/\/+FgGWa\/\/\/\/\/\/+FAGWN\/\/\/\/\/8O\/hJVRagK8tGxkXGBYIFRI0SWxtcBlmv\/\/\/\/\/Ce4Blmv\/\/\/\/\/B+8Blmv\/\/\/\/\/B\/ABljf\/\/\/\/\/EAfvqqoCAAD31talhHRkRCcWRWWE1OPyAZZr\/\/\/\/\/wISAZZr\/\/\/\/\/wERAZZr\/\/\/\/\/wEQAZY3\/\/\/\/\/w0AEAAAAADx0NGgkLCAcVJDIiUGAZZr\/\/\/\/\/xIAAQAW\/\/\/\/\/xX8BHYBqqqq\/1UBMEJhg4RzlHRjhHJxUUU1FhcYapuqAZZr\/\/\/\/\/\/UQAZZr\/\/\/\/\/\/URAZZr\/\/\/\/\/\/cQAZZr\/\/\/\/\/\/cUAZZr\/\/\/\/\/\/oTAZZr\/\/\/\/\/\/oRAZY3\/\/\/\/\/xH8ExUAAKoC89LRoICDVFRHJycaHBtfb40Bljf\/\/\/\/\/BRD1qgK+vN27mQGWa\/\/\/\/\/8f3QGWFv\/\/\/\/8W6ARKAQIAQFVVBSQiVHaXuJZ1lINQQ0RZW1ttXEpKSTgBlmv\/\/\/\/\/4w8BlgAAAAAAAAAA"
    },
    {
      "word" : "quick",
      "count" : 1,
      "type" : 1,
      "ink" : "UFdJQzEuMDUAAGkAPwEAAAD\/AAAU\/\/\/\/\/ywBABHMAkAB\/\/9fVQFBcaGBc1NGJxcYCCpKSq6tzgGWa\/\/\/\/\/\/vEQGWa\/\/\/\/\/\/yEQGWa\/\/\/\/\/\/yEQGWa\/\/\/\/\/\/zFAGWa\/\/\/\/\/\/2EwGWa\/\/\/\/\/\/3EgGWa\/\/\/\/\/\/7EgGWN\/\/\/\/\/8H\/RABKOHUl3g+Hj8Blmv\/\/\/\/\/EvcBljf\/\/\/\/\/ARD2Ar8Blmv\/\/\/\/\/EPABlmv\/\/\/\/\/Du8Blmv\/\/\/\/\/DfABlmv\/\/\/\/\/DuwBlmv\/\/\/\/\/C+4Blmv\/\/\/\/\/Cu8Bljf\/\/\/\/\/CQjvqkIB98W1g1ICQcHjAZZr\/\/\/\/\/\/0QAZZr\/\/\/\/\/\/oZAZZr\/\/\/\/\/\/oZAZZr\/\/\/\/\/\/kZAZZr\/\/\/\/\/\/kfAZZr\/\/\/\/\/\/kcAZZr\/\/\/\/\/\/oaAZZr\/\/\/\/\/\/ocAZZr\/\/\/\/\/\/sZAZZr\/\/\/\/\/\/sXAZZr\/\/\/\/\/\/sXAZZr\/\/\/\/\/\/0UAZZr\/\/\/\/\/\/0RAZY3\/\/\/\/\/xH9EhUAgKoC49LBsICCY1Q3KBgrXGvN3fsBlmv\/\/\/\/\/DOwBlmv\/\/\/\/\/CuwBlmv\/\/\/\/\/COwBlmv\/\/\/\/\/COoBlmv\/\/\/\/\/Be0Blmv\/\/\/\/\/BPABljf\/\/\/\/\/CAHv\/\/8A4sSpmWpfPj8Bljf\/\/\/\/\/CO8AVVUAHx4+S0lYVkQBlmv\/\/\/\/\/9BABlhb\/\/\/\/\/BT4DWgEKACIzM4LCAZZr\/\/\/\/\/wETAZZr\/\/\/\/\/wETAZZr\/\/\/\/\/wEUAZZr\/\/\/\/\/wIYAZZr\/\/\/\/\/wIVAZZr\/\/\/\/\/wMTAZY3\/\/\/\/\/wsEEwCAKvTktZRlNgYnibjYAZZr\/\/\/\/\/wvrAZZr\/\/\/\/\/wvqAZZr\/\/\/\/\/wrpAZZr\/\/\/\/\/wzkAZZr\/\/\/\/\/wnmAZZr\/\/\/\/\/wjoAZZr\/\/\/\/\/wfnAZZr\/\/\/\/\/wbsAZZr\/\/\/\/\/wXuAZY3\/\/\/\/\/wkD8KpfAdOysYBSIxVCUgGWa\/\/\/\/\/\/8EgGWFv\/\/\/\/8FeAQgAVUBITKCorIBlmv\/\/\/\/\/\/hIBlmv\/\/\/\/\/\/RQBlmv\/\/\/\/\/\/RUBlmv\/\/\/\/\/\/RkBlmv\/\/\/\/\/\/RYBlmv\/\/\/\/\/\/hMBlmv\/\/\/\/\/\/hUBljf\/\/\/\/\/Cf8RFcED8fHBkLGAgCFRAZZr\/\/\/\/\/\/7oAZYW\/\/\/\/\/wNqBKwAADNmiQGWa\/\/\/\/\/8oJwEBFv\/\/\/\/8JlAUmAf9VASMkJhorO5\/O3gGWa\/\/\/\/\/\/yEgGWa\/\/\/\/\/\/0EgGWa\/\/\/\/\/\/1EgGWa\/\/\/\/\/\/3EwGWN\/\/\/\/\/8O+RFVAYAK9vTTo8GgdEQ1FicaHCwBlmv\/\/\/\/\/EPkBljf\/\/\/\/\/AhD3Dq8hAZYa\/\/\/\/\/wXyBUgAGjxranoBlmv\/\/\/\/\/\/hABlmv\/\/\/\/\/\/RQBlmv\/\/\/\/\/\/RcBlmv\/\/\/\/\/+yMBlmv\/\/\/\/\/+yQBlmv\/\/\/\/\/\/CUBlmv\/\/\/\/\/+i0Blmv\/\/\/\/\/\/CkBlmv\/\/\/\/\/\/CYBlmv\/\/\/\/\/\/ScBlmv\/\/\/\/\/\/SABlmv\/\/\/\/\/\/hoBlmv\/\/\/\/\/\/xcBljf\/\/\/\/\/Df8SAKiqAuCxkWIkJUaIh4a4qbkBlmv\/\/\/\/\/I9gBlhb\/\/\/\/\/F2oGEAFfVVVVAAAVGDtLfb+9vO3KucilpZKBYWRVV0s9TQGWa\/\/\/\/\/8UAwGWa\/\/\/\/\/8TAwGWa\/\/\/\/\/8UAgGWa\/\/\/\/\/8XAgGWa\/\/\/\/\/8UAgGWa\/\/\/\/\/8SAgGWN\/\/\/\/\/8CEQEALRoBlmv\/\/\/\/\/IQYBlgAAAAAAAAAA"
    },
    {
      "word" : "brown",
      "count" : 1,
      "type" : 1,
      "ink" : "UFdJQzEuMDUAAG8APwEAAAD\/AAAU\/\/\/\/\/ywBAAKSAjYABRS1AZZr\/\/\/\/\/\/sSAZZr\/\/\/\/\/\/oYAZZr\/\/\/\/\/\/kgAZZr\/\/\/\/\/\/obAZZr\/\/\/\/\/\/sXAZZr\/\/\/\/\/\/sZAZZr\/\/\/\/\/\/wVAZZr\/\/\/\/\/\/0UAZZr\/\/\/\/\/\/wZAZZr\/\/\/\/\/\/sZAZZr\/\/\/\/\/\/saAZZr\/\/\/\/\/\/scAZZr\/\/\/\/\/\/wXAZZr\/\/\/\/\/\/wUAZZr\/\/\/\/\/\/wTAZY3\/\/\/\/\/wn9EFWlAtPjs6KjYiBigwGWa\/\/\/\/\/8H7wGWa\/\/\/\/\/8J7QGWa\/\/\/\/\/8K7AGWa\/\/\/\/\/8O5gGWa\/\/\/\/\/8O6AGWa\/\/\/\/\/8O6QGWa\/\/\/\/\/8Q6QGWN\/\/\/\/\/8RDe6qqgoAAPvcuqmbe3psOjoYFzV1g5LxAZZr\/\/\/\/\/\/8RAZZr\/\/\/\/\/\/4SAZZr\/\/\/\/\/\/wXAZZr\/\/\/\/\/\/sVAZZr\/\/\/\/\/\/oTAZZr\/\/\/\/\/\/gVAZZr\/\/\/\/\/\/gTAZZr\/\/\/\/\/\/cQAZY3\/\/\/\/\/xH1EVVVVa0C6srMnIpsa0o6OSgrGBchM0QBlmv\/\/\/\/\/FfEBlhb\/\/\/\/\/BFYDJgFVABIxovIBlmv\/\/\/\/\/\/xIBlmv\/\/\/\/\/ABoBlmv\/\/\/\/\/\/xgBlmv\/\/\/\/\/ABYBlmv\/\/\/\/\/\/xcBlmv\/\/\/\/\/ABMBljf\/\/\/\/\/BwARVCrwwaFRgbHCAZZr\/\/\/\/\/wTvAZZr\/\/\/\/\/wTwAZZr\/\/\/\/\/wTwAZY3\/\/\/\/\/w4G76qqqgr21ti4iItqWTs5JyknGAGWa\/\/\/\/\/8c+wGWFv\/\/\/\/8FLAQ2AVUBExVVdZYBlmv\/\/\/\/\/+hIBlmv\/\/\/\/\/+hUBlmv\/\/\/\/\/+hgBlmv\/\/\/\/\/+hwBlmv\/\/\/\/\/\/BgBlmv\/\/\/\/\/\/RQBljf\/\/\/\/\/Cv4TAaAK4bCRclMmFneXpgGWa\/\/\/\/\/8I7wGWa\/\/\/\/\/8I8AGWa\/\/\/\/\/8G7wGWa\/\/\/\/\/8H7QGWN\/\/\/\/\/8BBu4C9AGWN\/\/\/\/\/8NBO\/q\/x8A89PgwaOkdWRmRApAwAGWFv\/\/\/\/8ExAQ6AVUAIkJj5QGWa\/\/\/\/\/\/7FAGWa\/\/\/\/\/\/7FgGWa\/\/\/\/\/\/6HQGWa\/\/\/\/\/\/8GQGWa\/\/\/\/\/\/9FwGWa\/\/\/\/\/\/+FQGWN\/\/\/\/\/8u\/hEBqKqqqioAAACAqgrywJFiNRRkc3PExMTm1sXHppaGZVRnNQhSYXGhoaCxopKDY1NVRgUmNXeHl9n5AZZr\/\/\/\/\/wnwAZZr\/\/\/\/\/wvrAZZr\/\/\/\/\/wrrAZZr\/\/\/\/\/wnsAZZr\/\/\/\/\/wnoAZZr\/\/\/\/\/wjrAZZr\/\/\/\/\/wfuAZY3\/\/\/\/\/wYF72oF5bPDIkJSAZZr\/\/\/\/\/\/UYAZYW\/\/\/\/\/wQUBiABQAAyUlHhAZZr\/\/\/\/\/\/4TAZZr\/\/\/\/\/\/0XAZZr\/\/\/\/\/\/sfAZZr\/\/\/\/\/\/sbAZZr\/\/\/\/\/\/wYAZZr\/\/\/\/\/\/sYAZZr\/\/\/\/\/\/wUAZY3\/\/\/\/\/wf8EFUq47KSoyBggAGWa\/\/\/\/\/8D8AGWa\/\/\/\/\/8F7wGWa\/\/\/\/\/8H7gGWa\/\/\/\/\/8K6QGWa\/\/\/\/\/8K6wGWa\/\/\/\/\/8K7AGWa\/\/\/\/\/8N6gGWa\/\/\/\/\/8M7QGWa\/\/\/\/\/8M7wGWN\/\/\/\/\/8JDu+qAgDbuqp4VwY0ZPIBlmv\/\/\/\/\/AREBlmv\/\/\/\/\/ABQBlmv\/\/\/\/\/\/xsBlmv\/\/\/\/\/ABkBlmv\/\/\/\/\/\/xgBlmv\/\/\/\/\/\/xsBlmv\/\/\/\/\/\/xcBlmv\/\/\/\/\/ABYBlmv\/\/\/\/\/ABcBlmv\/\/\/\/\/\/xUBlmv\/\/\/\/\/ABIBljf\/\/\/\/\/BQATAADw0MCwkQGWa\/\/\/\/\/8DIwFWAAAAAAAAAAA="
    },
    {
      "word" : "fox",
      "count" : 1,
      "type" : 1,
      "ink" : "UFdJQzEuMDUAADwAPwEAAAD\/AAAY\/\/\/\/\/ywBAAg+ArwBsNDR0sPl5dUBlmv\/\/\/\/\/EPYBlmv\/\/\/\/\/FPMBlmv\/\/\/\/\/GfIBlmv\/\/\/\/\/H\/ABlmv\/\/\/\/\/G\/IBlmv\/\/\/\/\/F\/UBlmv\/\/\/\/\/F\/UBlmv\/\/\/\/\/E\/gBlmv\/\/\/\/\/EfgBljf\/\/\/\/\/DxD6qnpVFW1aSjg2WEMDIyYlJCNFZwGWFv\/\/\/\/8S2gJOArv6\/\/8PMUBhUIBwcUJDU2NSY3KUo7T1AZZr\/\/\/\/\/\/vwAZZr\/\/\/\/\/\/vvAZZr\/\/\/\/\/\/rrAZZr\/\/\/\/\/\/vrAZZr\/\/\/\/\/\/vsAZZr\/\/\/\/\/\/vpAZZr\/\/\/\/\/\/vsAZZr\/\/\/\/\/\/ztAZZr\/\/\/\/\/\/zrAZZr\/\/\/\/\/\/3tAZZr\/\/\/\/\/\/3uAZZr\/\/\/\/\/\/3uAZY3\/\/\/\/\/wr+8KuqCuLgwKCzpaerjIwBlmv\/\/\/\/\/EfgBlmv\/\/\/\/\/EfkBlmv\/\/\/\/\/EPkBlmv\/\/\/\/\/E\/oBlmv\/\/\/\/\/EvwBlmv\/\/\/\/\/EPwBljf\/\/\/\/\/AxL9Oj8dEwGWFv\/\/\/\/8P4gNIAf9XVRUTIzUYFxhIWGemtrTz8uEBljf\/\/\/\/\/EQEQAACgqgLSxLand3paWhwNLG2Mi9rp9wGWa\/\/\/\/\/8G7gGWN\/\/\/\/\/8BBfAC8wGWN\/\/\/\/\/8RAPD\/\/1VVAeLTyZmKXk49Hx08a2l2hXRyAZZr\/\/\/\/\/\/oaAZYW\/\/\/\/\/wJOBewABSTHAZZr\/\/\/\/\/\/YVAZZr\/\/\/\/\/\/QbAZZr\/\/\/\/\/\/AqAZZr\/\/\/\/\/\/EpAZZr\/\/\/\/\/\/IpAZZr\/\/\/\/\/\/IsAZZr\/\/\/\/\/\/UiAZZr\/\/\/\/\/\/ccAZZr\/\/\/\/\/\/gXAZY3\/\/\/\/\/wv5ElX9P+a3lWYVJVWUo5MyAZYW\/\/\/\/\/wa0BPoAAAAxYWCCoqMBlmv\/\/\/\/\/BhABljf\/\/\/\/\/AQcQAPgBlmv\/\/\/\/\/DBMBlmv\/\/\/\/\/DBEBlmv\/\/\/\/\/DBABljf\/\/\/\/\/Ag8RAO\/OAZZr\/\/\/\/\/xANAZY3\/\/\/\/\/wEQCgCeAZY3\/\/\/\/\/wgQCQAAAH59bVtJSkg4AZZr\/\/\/\/\/x4MAT0AAAAAAAAAAA=="
    },
    {
      "word" : "jumps",
      "count" : 1,
      "type" : 1,
      "ink" : "UFdJQzEuMDUAAEkAPwEAAAD\/AAAU\/\/\/\/\/ywBAAbGAgQBAQBBcJCBgXEBlmv\/\/\/\/\/AxMBlmv\/\/\/\/\/BRsBlmv\/\/\/\/\/BR8Blmv\/\/\/\/\/CCsBlmv\/\/\/\/\/CCYBlmv\/\/\/\/\/ByMBlmv\/\/\/\/\/CCQBlmv\/\/\/\/\/CB4Blmv\/\/\/\/\/CBoBlmv\/\/\/\/\/CBkBlmv\/\/\/\/\/BxMBljf\/\/\/\/\/DwYRAABUPebGppV1U2RCQBUHGA4dLgGWa\/\/\/\/\/\/u\/QGWa\/\/\/\/\/\/u\/gGWa\/\/\/\/\/\/w\/QGWa\/\/\/\/\/\/s\/AGWa\/\/\/\/\/\/v\/QGWa\/\/\/\/\/\/w\/QGWN\/\/\/\/\/8L7\/v\/\/ytOTVxJSFdUQ3FR0wGWSv\/\/\/\/+yAnAAAfAW\/\/\/\/\/wdmA0gBAAAjM1JSs9LiAZZr\/\/\/\/\/wMTAZY3\/\/\/\/\/wEDEQDzAZY3\/\/\/\/\/ywDEQAAAKqqqqqqqqqqAOPDw6ODc1JDVDQkJSVEY3NyopKCkXFxgWKSUEFgUHFxkXGScZCBkIBwcJCxAZYW\/\/\/\/\/wI2BEoBATHCAZZr\/\/\/\/\/wQTAZZr\/\/\/\/\/wUXAZZr\/\/\/\/\/wYfAZZr\/\/\/\/\/wUcAZZr\/\/\/\/\/wQYAZZr\/\/\/\/\/wMXAZY3\/\/\/\/\/woCEYCqCtLScTMwYXHCwuIBlmv\/\/\/\/\/Au8Blmv\/\/\/\/\/A\/ABlmv\/\/\/\/\/A\/ABljf\/\/\/\/\/LATvqqoCAAAAqKqqKgAA88PFpIR1VEQmBURjc5OSkqOikpJyYXJRUyNCU6W1xubVtaWEdIVUEzNiwuMBlmv\/\/\/\/\/AhABlmv\/\/\/\/\/AxMBlmv\/\/\/\/\/AhIBlmv\/\/\/\/\/AhEBljf\/\/\/\/\/DAMRAAAAAPPj5LSTlHNTdVRVRgGWa\/\/\/\/\/8QCwGWFv\/\/\/\/8D3AV8AQAgMdABlmv\/\/\/\/\/ARIBlmv\/\/\/\/\/ABYBlmv\/\/\/\/\/AR0Blmv\/\/\/\/\/ARoBlmv\/\/\/\/\/ABcBlmv\/\/\/\/\/ARcBlmv\/\/\/\/\/ARUBlmv\/\/\/\/\/ARIBljf\/\/\/\/\/BwERACrhsbFxEXHQAZZr\/\/\/\/\/wDwAZZr\/\/\/\/\/wDuAZZr\/\/\/\/\/\/\/oAZZr\/\/\/\/\/\/\/nAZZr\/\/\/\/\/\/\/oAZZr\/\/\/\/\/\/\/kAZZr\/\/\/\/\/wDmAZZr\/\/\/\/\/\/\/nAZZr\/\/\/\/\/wDmAZZr\/\/\/\/\/wHpAZZr\/\/\/\/\/wHsAZY3\/\/\/\/\/w0B7KoqAADy0rOCY0YWRnWE1ePzAZZr\/\/\/\/\/wITAZZr\/\/\/\/\/wESAZZr\/\/\/\/\/wEQAZY3\/\/\/\/\/w8AEVVVVRXy4sSjhGVlRUY2NUc1NmUCAAAW\/\/\/\/\/wXMBgQBVQEEBlqs7QGWa\/\/\/\/\/\/xEQGWN\/\/\/\/\/8n9BBVAQAAAABVVVUV2tmmlaNwQzQ2OCgoOTk4WHd2pZSTopGBkoKEhoeIq6uaupmHhmVkAZZr\/\/\/\/\/\/MSAZYAAAAAAAAAAA=="
    },
    {
      "word" : "over",
      "count" : 1,
      "type" : 1,
      "ink" : "UFdJQzEuMDUAADQAPwEAAAD\/AAAU\/\/\/\/\/ywBAAsAAwQB\/1UVIiQ1KRhGV1a5udoBljf\/\/\/\/\/AvURBfn5AZY3\/\/\/\/\/xb4EFUVAACqCvbl08OSwaFydGV3aFlKOzosS2zM3PoBlmv\/\/\/\/\/CuwBlmv\/\/\/\/\/COwBlmv\/\/\/\/\/BusBlmv\/\/\/\/\/BukBlmv\/\/\/\/\/BOwBlmv\/\/\/\/\/A+8Bljf\/\/\/\/\/EAHu\/\/9XVQDx0sSUdWdGNhooNUQzU1NSAZZr\/\/\/\/\/\/kVAZYW\/\/\/\/\/wMqAxwBABU5TQGWN\/\/\/\/\/8BEAwA\/wGWa\/\/\/\/\/8NEwGWa\/\/\/\/\/8NFwGWa\/\/\/\/\/8LFQGWa\/\/\/\/\/8JEgGWa\/\/\/\/\/8JEgGWN\/\/\/\/\/8LCBAAoCrXt6Z0hkMjY7LS0gGWa\/\/\/\/\/8C7AGWa\/\/\/\/\/8D7QGWa\/\/\/\/\/8D7QGWa\/\/\/\/\/8E6AGWa\/\/\/\/\/8D6QGWa\/\/\/\/\/8D6QGWa\/\/\/\/\/8E6AGWa\/\/\/\/\/8E6wGWa\/\/\/\/\/8D7QGWN\/\/\/\/\/8GA++qAvKyw3IlKgGWFv\/\/\/\/8cQASIAaCqqqrqX1UAJAcYKV5tbJ6dm7y5qaeVhJRzUEMnGDhJeru62QGWN\/\/\/\/\/8C9xAF9+YBlmv\/\/\/\/\/\/BIBlmv\/\/\/\/\/\/BABlmv\/\/\/\/\/\/hABljf\/\/\/\/\/EQARAACgqgLhwsamhnlZST0MHT5MS0lINgGWa\/\/\/\/\/8T9wGWFv\/\/\/\/8EdAUcAQAAMVFQ4QGWa\/\/\/\/\/8BFAGWa\/\/\/\/\/8BGAGWa\/\/\/\/\/8CHQGWa\/\/\/\/\/8CGQGWa\/\/\/\/\/8CFQGWN\/\/\/\/\/8LAxQAoCry06KSYpMhYbHQ8QGWa\/\/\/\/\/8C6gGWa\/\/\/\/\/8C6gGWa\/\/\/\/\/8D6gGWa\/\/\/\/\/8E5wGWa\/\/\/\/\/8E6gGWa\/\/\/\/\/8D7AGWa\/\/\/\/\/8E7AGWN\/\/\/\/\/8KBO+qqgr05ca3mGhXWDZFAZZr\/\/\/\/\/xL1AQAAAAAAAAAAAA=="
    },
    {
      "word" : "lazy",
      "count" : 1,
      "type" : 1,
      "ink" : "UFdJQzEuMDUAADkAPwEAAAD\/AAAU\/\/\/\/\/ywBAAWeAlAAAAAwYYFxgQGWa\/\/\/\/\/8AGAGWa\/\/\/\/\/8BIQGWa\/\/\/\/\/8BKQGWa\/\/\/\/\/8BNQGWa\/\/\/\/\/8BLQGWa\/\/\/\/\/8AKQGWa\/\/\/\/\/8AKAGWa\/\/\/\/\/8BIAGWa\/\/\/\/\/8AHAGWa\/\/\/\/\/8BGAGWa\/\/\/\/\/8BFAGWN\/\/\/\/\/8HARAAKsGicYQkY2IBlmv\/\/\/\/\/CewBlhb\/\/\/\/\/BX4DLgFXARQFWYu8AZZr\/\/\/\/\/\/ISAZZr\/\/\/\/\/\/QSAZZr\/\/\/\/\/\/USAZZr\/\/\/\/\/\/UVAZZr\/\/\/\/\/\/gTAZZr\/\/\/\/\/\/kQAZY3\/\/\/\/\/zH6ERWAqqqqqqoAAAAAAALkw+KQY0MFNHSElMS0xOTUw9XEtbWlpJaEZXZFBTSElLT11NX11dTEtIOEY1NUQxctAZYW\/\/\/\/\/z0QBDABgqoCAFVVVVUBoKqqqqqqAoADBRkbHR8cGwoIFzZEY5Ghs9XHtsmnh5eHhnV1ZJRikUM0JicIJzhGRUQ0IzIzRSMkFRUVJhYnJyg3JxUBlmv\/\/\/\/\/EvoBlhb\/\/\/\/\/BRwFFgEAACFQcYDyAZZr\/\/\/\/\/wQTAZZr\/\/\/\/\/wQUAZZr\/\/\/\/\/wYYAZY3\/\/\/\/\/woGEgCgCvbGl3Y3FxZ5mKcBlmv\/\/\/\/\/Cu8Blmv\/\/\/\/\/Cu8Blmv\/\/\/\/\/Ce8Blmv\/\/\/\/\/C+wBlmv\/\/\/\/\/Cu0Blmv\/\/\/\/\/CPABljf\/\/\/\/\/CQnvqkIB98W1hGICkLHBAZZr\/\/\/\/\/\/8SAZZr\/\/\/\/\/wASAZZr\/\/\/\/\/\/8RAZZr\/\/\/\/\/wIWAZZr\/\/\/\/\/wMUAZZr\/\/\/\/\/wQTAZZr\/\/\/\/\/wgUAZZr\/\/\/\/\/wcSAZZr\/\/\/\/\/wgQAZY3\/\/\/\/\/wgJEQAAAPrZ+unI+fbWAZY3\/\/\/\/\/wgEEFBVAPPi8dTG26yeAZZr\/\/\/\/\/+0JAZZr\/\/\/\/\/+0GAZZr\/\/\/\/\/+0FAZZr\/\/\/\/\/+oEAZZr\/\/\/\/\/+wDAZZr\/\/\/\/\/+0DAZZr\/\/\/\/\/+sBAZZr\/\/\/\/\/+4AAZZr\/\/\/\/\/+\/\/AZY3\/\/\/\/\/wvv\/v\/\/Pz4tO0o3RkVDY0KhAZYAAAAAAAAAAA=="
    },
    {
      "word" : "dog",
      "count" : 1,
      "type" : 1,
      "ink" : "UFdJQzEuMDUAACYAPwEAAAD\/AAAU\/\/\/\/\/ywBABFkA0YB\/\/9fVQEiJDVWV1ZnRzYpCQlbeorq+QGWa\/\/\/\/\/\/4EAGWa\/\/\/\/\/\/4FQGWa\/\/\/\/\/\/7EwGWa\/\/\/\/\/\/8EgGWa\/\/\/\/\/\/+FQGWa\/\/\/\/\/\/\/EQGWa\/\/\/\/\/8AEAGWN\/\/\/\/\/8OAxAAAKoK1MaoiVlMKysuTWy+zdsBlmv\/\/\/\/\/De0Blmv\/\/\/\/\/C+wBlmv\/\/\/\/\/CesBlmv\/\/\/\/\/CuIBlmv\/\/\/\/\/B+MBlmv\/\/\/\/\/BuIBlmv\/\/\/\/\/Bd4Blmv\/\/\/\/\/A+IBlmv\/\/\/\/\/A+cBlmv\/\/\/\/\/AOYBlmv\/\/\/\/\/\/usBlmv\/\/\/\/\/\/e4Bljf\/\/\/\/\/Cvvv\/18M5baXdmY5cpKwMQGWFv\/\/\/\/86CgSWAar+f1UVAACoqqr+f1UVADFDc1JgYWNkVkUYGCdYd4bF08PhwrSniGhaSjocGipraonJx8f11LOxkoJnWUodDBtMSkhXRUNQQs4Blhb\/\/\/\/\/CCQFFAH\/VwAkNTYmJjp8ngGWN\/\/\/\/\/8C7w8F\/vwBljf\/\/\/\/\/FPURVQEAqqoA6NfVtKOQcWJVNTYYGTlrmqrr6ukBljf\/\/\/\/\/JgnwqioAAAAAAABVBebV47OSomERUWBho7Ok1te36unJ++rK6riomIZ1dGRCYWNUemxtAZZr\/\/\/\/\/+4GAZZr\/\/\/\/\/+0GAZZr\/\/\/\/\/+0FAZZr\/\/\/\/\/+gFAZZr\/\/\/\/\/+oFAZZr\/\/\/\/\/+oFAZZr\/\/\/\/\/+gFAZZr\/\/\/\/\/+sEAZZr\/\/\/\/\/+wDAZZr\/\/\/\/\/+wEAZY3\/\/\/\/\/wruA1UVAD8\/OzpKNmJDMqYBlgAAAAAAAAAA"
    },
    {
      "word" : "A B C D E",
      "count" : 5,
      "type" : 4,
      "ink" : "UFdJQzEuMDUAAHkAPwEAAAD\/AAAY\/\/\/\/\/ywBAAMkAlQAKUpZAZZr\/\/\/\/\/\/kUAZZr\/\/\/\/\/\/YcAZZr\/\/\/\/\/\/QkAZZr\/\/\/\/\/\/AuAZZr\/\/\/\/\/\/EoAZZr\/\/\/\/\/\/IkAZZr\/\/\/\/\/\/EkAZZr\/\/\/\/\/\/MfAZZr\/\/\/\/\/\/QbAZZr\/\/\/\/\/\/MbAZZr\/\/\/\/\/\/QWAZZr\/\/\/\/\/\/YSAZY3\/\/\/\/\/wz3EVWlqgDYt4Z1VGUwYoPVxbQCAAAW\/\/\/\/\/wT4AXoAAABAgbHTAZZr\/\/\/\/\/wQVAZZr\/\/\/\/\/wQXAZZr\/\/\/\/\/wUXAZZr\/\/\/\/\/wcgAZZr\/\/\/\/\/wcgAZZr\/\/\/\/\/wYfAZZr\/\/\/\/\/wchAZZr\/\/\/\/\/wUaAZZr\/\/\/\/\/wQVAZY3\/\/\/\/\/wsDEwAAFeOykYFhcWCAQVKzAZYW\/\/\/\/\/wa8AaABqgojNTVZW2wBlmv\/\/\/\/\/FfQBlmv\/\/\/\/\/F\/QBljv\/\/\/\/\/ARjyqQGWFv\/\/\/\/8FMAOUAFUBIzOVxOMBlmv\/\/\/\/\/+xgBlmv\/\/\/\/\/\/BkBlmv\/\/\/\/\/\/RsBlmv\/\/\/\/\/\/CIBlmv\/\/\/\/\/\/R8Blmv\/\/\/\/\/\/R0Blmv\/\/\/\/\/\/h0Blmv\/\/\/\/\/\/hgBlmv\/\/\/\/\/\/hQBljf\/\/\/\/\/B\/4SlSvRsdEgQXDgAZZr\/\/\/\/\/wHvAZZr\/\/\/\/\/wDuAZZr\/\/\/\/\/wLmAZZr\/\/\/\/\/wPlAZZr\/\/\/\/\/wPkAZZr\/\/\/\/\/wXeAZZr\/\/\/\/\/wXhAZZr\/\/\/\/\/wbiAZZr\/\/\/\/\/wfiAZZr\/\/\/\/\/wbmAZZr\/\/\/\/\/wXqAZZr\/\/\/\/\/wbtAZY3\/\/\/\/\/wsG8KoCFNW1hWRJU3KC0OHSAZY3\/\/\/\/\/xr8EFUVAAAAAAXU1LSkc4RjYCQmFhsaGz08PGx6eLe1xOHx4gGWN\/\/\/\/\/8T+hBVVVVVKebX2ci5uomIaVlISjgnOicGEjYBlhb\/\/\/\/\/D9oElgCq6lcVQHBwcXCQcFM1CCk5jZysAZZr\/\/\/\/\/\/MQAZZr\/\/\/\/\/\/MRAZZr\/\/\/\/\/\/URAZZr\/\/\/\/\/\/QXAZZr\/\/\/\/\/\/YVAZZr\/\/\/\/\/\/gUAZZr\/\/\/\/\/\/gYAZZr\/\/\/\/\/\/oWAZZr\/\/\/\/\/\/oUAZZr\/\/\/\/\/\/wWAZZr\/\/\/\/\/\/0UAZZr\/\/\/\/\/\/0RAZZr\/\/\/\/\/\/4SAZY3\/\/\/\/\/wf\/EAAA8PLVxaqbawGWN\/\/\/\/\/8CEAUATz4Blmv\/\/\/\/\/EgABlmv\/\/\/\/\/Ef0Blmv\/\/\/\/\/EfwBlmv\/\/\/\/\/EvkBljf\/\/\/\/\/CRD5qqoBf498e3pYRldDAZYW\/\/\/\/\/wPwBYgAFSJT9AGWa\/\/\/\/\/\/7GAGWa\/\/\/\/\/\/8HQGWa\/\/\/\/\/\/7JQGWa\/\/\/\/\/\/8IQGWa\/\/\/\/\/\/9HQGWa\/\/\/\/\/\/9HgGWa\/\/\/\/\/\/+GQGWa\/\/\/\/\/\/\/FQGWa\/\/\/\/\/\/\/FQGWN\/\/\/\/\/8G\/xBBBNGwkIGwGAGWFv\/\/\/\/8FxgVyAAIAIgQVF50Blmv\/\/\/\/\/EQ0Blmv\/\/\/\/\/FBEBlmv\/\/\/\/\/FxYBlmv\/\/\/\/\/ExUBlmv\/\/\/\/\/EBMBlmv\/\/\/\/\/DxQBljf\/\/\/\/\/AQsSAPkBljf\/\/\/\/\/BgcQQAXVxNLR0vcBljf\/\/\/\/\/AfcQAfkBlmv\/\/\/\/\/8hMBlmv\/\/\/\/\/8hABlmv\/\/\/\/\/8RABlmv\/\/\/\/\/7hEBlmv\/\/\/\/\/7w8Blmv\/\/\/\/\/7w0Bljf\/\/\/\/\/C+4NVdUqv66Oa1laNnEiMzUBlmv\/\/\/\/\/FvABlhb\/\/\/\/\/B44HaAD\/FTM1WCZarN8Blmv\/\/\/\/\/7RQBlmv\/\/\/\/\/8BMBlmv\/\/\/\/\/8hEBlmv\/\/\/\/\/8hUBlmv\/\/\/\/\/9hMBlmv\/\/\/\/\/9xEBlmv\/\/\/\/\/+BMBljf\/\/\/\/\/KfoQVRUAAAAAqqqqqgLk5MOiopGBoJCBsqKyxKOjpHNzU0RENyYXJjdYWEhZWEdHRzVXVVVE2wIAABb\/\/\/\/\/BdQGTgGqAiEyRlhaAZZr\/\/\/\/\/xH4AZZr\/\/\/\/\/xL5AZZr\/\/\/\/\/xP4AZZr\/\/\/\/\/xb4AZZr\/\/\/\/\/xP6AZZr\/\/\/\/\/xH6AZYAAAAAAAAAAA=="
    },
    {
      "word" : "F G H I J",
      "count" : 5,
      "type" : 4,
      "ink" : "UFdJQzEuMDUAAIMAPwEAAAD\/AAAU\/\/\/\/\/ywBAASqAZQAVQAxYbLRAZZr\/\/\/\/\/\/8QAZZr\/\/\/\/\/\/4YAZZr\/\/\/\/\/\/0ZAZZr\/\/\/\/\/\/0aAZZr\/\/\/\/\/\/0hAZZr\/\/\/\/\/\/wfAZZr\/\/\/\/\/\/0dAZZr\/\/\/\/\/\/0fAZZr\/\/\/\/\/\/4cAZZr\/\/\/\/\/\/4ZAZZr\/\/\/\/\/\/4YAZZr\/\/\/\/\/\/8UAZY3\/\/\/\/\/wn\/EUWqAvHBkLExYZJi1gGWFv\/\/\/\/8GigGgAKoKMmV3rK6fAZZr\/\/\/\/\/xb0AZZr\/\/\/\/\/xfzAZZr\/\/\/\/\/xjzAZZr\/\/\/\/\/x3xAZZr\/\/\/\/\/xnzAZZr\/\/\/\/\/xj1AZZr\/\/\/\/\/xj3AZZr\/\/\/\/\/xT4AZY3\/\/\/\/\/wUR+6oCTzw6LBkBlmv\/\/\/\/\/Ff0Blhb\/\/\/\/\/A6ABjgErMmaMAZZr\/\/\/\/\/xD3AZZr\/\/\/\/\/xzwAZZr\/\/\/\/\/x3vAZZr\/\/\/\/\/x\/vAZZr\/\/\/\/\/yDuAZZr\/\/\/\/\/xnyAZY7\/\/\/\/\/wET9bABlhb\/\/\/\/\/DMADVAD\/VVUAFCcYGQgqOkqMnKzvAZZr\/\/\/\/\/\/MQAZZr\/\/\/\/\/\/MQAZZr\/\/\/\/\/\/EWAZZr\/\/\/\/\/\/MXAZZr\/\/\/\/\/\/QXAZZr\/\/\/\/\/\/QbAZZr\/\/\/\/\/\/cZAZZr\/\/\/\/\/\/gYAZZr\/\/\/\/\/\/oaAZZr\/\/\/\/\/\/sXAZZr\/\/\/\/\/\/0UAZZr\/\/\/\/\/\/8VAZZr\/\/\/\/\/wASAZZr\/\/\/\/\/wEQAZY3\/\/\/\/\/xEFEAAAgKoC5bbIqZl8bEw\/Dg5Pbn3Ny9kBljf\/\/\/\/\/AgnwCvb2AZY3\/\/\/\/\/xgE8Or\/f1VVAQDjwsCihIdYSDsrGgsKGRknFjc1U2JQUaUBlhb\/\/\/\/\/A4IENAAVQXGSAZZr\/\/\/\/\/\/4aAZZr\/\/\/\/\/\/0kAZZr\/\/\/\/\/\/wrAZZr\/\/\/\/\/\/w3AZZr\/\/\/\/\/\/0wAZZr\/\/\/\/\/\/0sAZZr\/\/\/\/\/\/0rAZZr\/\/\/\/\/\/0jAZZr\/\/\/\/\/\/4dAZZr\/\/\/\/\/\/4aAZZr\/\/\/\/\/\/4VAZY3\/\/\/\/\/wn+EJWqAtGRcRFCg\/b4+AGWa\/\/\/\/\/8L7AGWa\/\/\/\/\/8L7QGWa\/\/\/\/\/8L7QGWa\/\/\/\/\/8O6QGWa\/\/\/\/\/8N6wGWa\/\/\/\/\/8N7QGWa\/\/\/\/\/8N7AGWN\/\/\/\/\/8MDPCqqqoA+9q4h4ZmRVdFNDOIAZYW\/\/\/\/\/wZ6BQIAVQUiQmOEk5IBlmv\/\/\/\/\/\/BkBlmv\/\/\/\/\/+iIBlmv\/\/\/\/\/+ioBlmv\/\/\/\/\/9zYBlmv\/\/\/\/\/+S8Blmv\/\/\/\/\/+ikBlmv\/\/\/\/\/+ygBlmv\/\/\/\/\/\/CIBlmv\/\/\/\/\/\/BwBlmv\/\/\/\/\/\/RoBlmv\/\/\/\/\/\/hUBljf\/\/\/\/\/Cf4SBQAA4cGAkGFCMxUFAZZr\/\/\/\/\/xL9AQAa\/\/\/\/\/wOIBhwAoLIDAZZr\/\/\/\/\/\/8RAZZr\/\/\/\/\/\/0aAZZr\/\/\/\/\/\/wiAZZr\/\/\/\/\/\/ouAZZr\/\/\/\/\/\/oqAZZr\/\/\/\/\/\/knAZZr\/\/\/\/\/\/koAZZr\/\/\/\/\/\/khAZZr\/\/\/\/\/\/sdAZZr\/\/\/\/\/\/scAZZr\/\/\/\/\/\/wXAZZr\/\/\/\/\/\/wUAZY3\/\/\/\/\/w79EVWBqgriwsOBkWMEJTU1NEZUqgGWFv\/\/\/\/8EhAcgAFcAIlOi8wGWa\/\/\/\/\/\/8GgGWa\/\/\/\/\/\/7GwGWa\/\/\/\/\/\/6HQGWa\/\/\/\/\/\/6IQGWa\/\/\/\/\/\/7GwGWa\/\/\/\/\/\/8GAGWa\/\/\/\/\/\/9GAGWa\/\/\/\/\/\/+FQGWa\/\/\/\/\/\/+EgGWa\/\/\/\/\/\/\/EwGWN\/\/\/\/\/8B\/xEA8AGWN\/\/\/\/\/8VARAAAABAVQHiwtTEpLWUlIRjU3NjYlBSY2WZi50Blmv\/\/\/\/\/7woBlmv\/\/\/\/\/7wkBlmv\/\/\/\/\/8AgBlmv\/\/\/\/\/7AgBlmv\/\/\/\/\/7QcBlmv\/\/\/\/\/7wcBljf\/\/\/\/\/Ce0GVdUDT009OhgqFzahAZYW\/\/\/\/\/xJkB2gAVd3\/qwoFCQkKCRkJFxcWJSclJRQXGT8Blmv\/\/\/\/\/Ef0Blmv\/\/\/\/\/EfwBlmv\/\/\/\/\/FfsBlmv\/\/\/\/\/FPoBlmv\/\/\/\/\/E\/sBlmv\/\/\/\/\/FPkBlmv\/\/\/\/\/EvoBlmv\/\/\/\/\/EfsBljf\/\/\/\/\/BRD8qgJOPDwrKgGWa\/\/\/\/\/8l+QGWAAAAAAAAAAA="
    },
    {
      "word" : "K L M N O",
      "count" : 5,
      "type" : 4,
      "ink" : "UFdJQzEuMDUAAKoAPwEAAAD\/AAAU\/\/\/\/\/ywBAALkAXwAAECQAZZr\/\/\/\/\/\/4TAZZr\/\/\/\/\/\/4bAZZr\/\/\/\/\/\/0gAZZr\/\/\/\/\/\/srAZZr\/\/\/\/\/\/snAZZr\/\/\/\/\/\/skAZZr\/\/\/\/\/\/klAZZr\/\/\/\/\/\/sfAZZr\/\/\/\/\/\/saAZZr\/\/\/\/\/\/sZAZZr\/\/\/\/\/\/0WAZZr\/\/\/\/\/\/0SAZY3\/\/\/\/\/wj9EVUBAOLBoYFxUiMeAZYa\/\/\/\/\/wTGAl4ArC1tfgGWa\/\/\/\/\/\/zEQGWa\/\/\/\/\/\/vFgGWa\/\/\/\/\/\/uGAGWa\/\/\/\/\/\/oHgGWa\/\/\/\/\/\/rGgGWa\/\/\/\/\/\/tFwGWa\/\/\/\/\/\/sFgGWN\/\/\/\/\/8Q7xNVVQAAAP7+u5mXZmRhUVNXWEpdTk8Blmv\/\/\/\/\/EgUBlmv\/\/\/\/\/EQUBlmv\/\/\/\/\/EQUBlmv\/\/\/\/\/FAcBlmv\/\/\/\/\/EgcBlmv\/\/\/\/\/EAcBlmv\/\/\/\/\/EggBljf\/\/\/\/\/CxAIAAAgfo98WltKODsoCCcBlmv\/\/\/\/\/FPoBlhb\/\/\/\/\/BcoDfABVAQQHGDbWAZZr\/\/\/\/\/\/kTAZZr\/\/\/\/\/\/cYAZZr\/\/\/\/\/\/YgAZZr\/\/\/\/\/\/gdAZZr\/\/\/\/\/\/kZAZZr\/\/\/\/\/\/kaAZZr\/\/\/\/\/\/sWAZZr\/\/\/\/\/\/wUAZZr\/\/\/\/\/\/4TAZY3\/\/\/\/\/w3+EFUAAADi0bGRkXNjZ0dJPC0sAZY3\/\/\/\/\/xEQAKqqqqoCHi4\/PkxNOzkpJiY2JFVDQ8gBlhr\/\/\/\/\/BOoEhgAaO2tqAZZr\/\/\/\/\/\/4TAZZr\/\/\/\/\/\/0bAZZr\/\/\/\/\/\/0iAZZr\/\/\/\/\/\/0qAZZr\/\/\/\/\/\/0jAZZr\/\/\/\/\/\/4fAZZr\/\/\/\/\/\/4cAZZr\/\/\/\/\/\/4XAZZr\/\/\/\/\/\/8UAZY3\/\/\/\/\/wb\/EZEK0bBRsdHyAZZr\/\/\/\/\/wPoAZZr\/\/\/\/\/wPnAZZr\/\/\/\/\/wTnAZZr\/\/\/\/\/wbiAZZr\/\/\/\/\/wXkAZZr\/\/\/\/\/wbnAZZr\/\/\/\/\/wblAZZr\/\/\/\/\/wboAZZr\/\/\/\/\/wXrAZZr\/\/\/\/\/wXtAZY3\/\/\/\/\/wkF8KoCAMSkg2MlNZTD8wGWa\/\/\/\/\/8DFgGWa\/\/\/\/\/8DFgGWa\/\/\/\/\/8CFQGWa\/\/\/\/\/8CGAGWa\/\/\/\/\/8DFAGWa\/\/\/\/\/8CEgGWN\/\/\/\/\/8LAhEAoCrispKCYYMiYrPU9AGWa\/\/\/\/\/8H6wGWa\/\/\/\/\/8G6wGWa\/\/\/\/\/8H6gGWa\/\/\/\/\/8J5wGWa\/\/\/\/\/8H6QGWa\/\/\/\/\/8I6wGWa\/\/\/\/\/8H6wGWN\/\/\/\/\/8IB\/CqAgDmxZRzR4LC4QGWa\/\/\/\/\/8BGAGWa\/\/\/\/\/8AGAGWa\/\/\/\/\/8BGAGWa\/\/\/\/\/8AHAGWa\/\/\/\/\/8BGQGWa\/\/\/\/\/8AFgGWa\/\/\/\/\/8AFwGWa\/\/\/\/\/8AFQGWa\/\/\/\/\/8AEgGWa\/\/\/\/\/8BEwGWN\/\/\/\/\/8BABIA8QGWa\/\/\/\/\/8BEgGWN\/\/\/\/\/8BARAA8gGWa\/\/\/\/\/8CEQGWN\/\/\/\/\/8BAxAA4gGWN\/\/\/\/\/8FBBAAANXUtpZ1AZZr\/\/\/\/\/xYWAZYW\/\/\/\/\/wNkBpYAADBR8AGWa\/\/\/\/\/8AFAGWa\/\/\/\/\/8AGAGWa\/\/\/\/\/\/\/JAGWa\/\/\/\/\/\/+JAGWa\/\/\/\/\/\/9IwGWa\/\/\/\/\/\/9JgGWa\/\/\/\/\/\/9IQGWa\/\/\/\/\/\/9GwGWa\/\/\/\/\/\/9GgGWa\/\/\/\/\/\/+FgGWa\/\/\/\/\/\/\/EQGWN\/\/\/\/\/8J\/xBV\/QOykaJiFDFRYdIBlmv\/\/\/\/\/\/\/ABlmv\/\/\/\/\/\/+8Blmv\/\/\/\/\/\/ugBlmv\/\/\/\/\/\/+cBlmv\/\/\/\/\/AOgBlmv\/\/\/\/\/\/+IBlmv\/\/\/\/\/AOQBlmv\/\/\/\/\/\/+cBlmv\/\/\/\/\/AeQBlmv\/\/\/\/\/AegBlmv\/\/\/\/\/AuoBlmv\/\/\/\/\/AusBljf\/\/\/\/\/CQLuqgoA8dKygnQzRJO0AZZr\/\/\/\/\/wUUAZZr\/\/\/\/\/wUVAZZr\/\/\/\/\/wUWAZZr\/\/\/\/\/wYaAZZr\/\/\/\/\/wcYAZZr\/\/\/\/\/wcWAZZr\/\/\/\/\/wgXAZZr\/\/\/\/\/wcSAZY3\/\/\/\/\/wkHEACgAte2hJZVJWGSwgGWa\/\/\/\/\/8D7AGWa\/\/\/\/\/8C6gGWa\/\/\/\/\/8D6AGWa\/\/\/\/\/8D3wGWa\/\/\/\/\/8D4AGWa\/\/\/\/\/8D4QGWa\/\/\/\/\/8D3QGWa\/\/\/\/\/8C4AGWa\/\/\/\/\/8B4gGWa\/\/\/\/\/8B5AGWa\/\/\/\/\/8B6QGWN\/\/\/\/\/8IAe6qCgDwwJGQYGATmgGWFv\/\/\/\/8LnAeEAKpeFUBignGRYiEyU7XnAZZr\/\/\/\/\/\/gQAZZr\/\/\/\/\/\/YXAZZr\/\/\/\/\/\/cXAZZr\/\/\/\/\/\/gVAZZr\/\/\/\/\/\/cZAZZr\/\/\/\/\/\/oXAZZr\/\/\/\/\/\/oVAZZr\/\/\/\/\/\/sWAZZr\/\/\/\/\/\/0TAZZr\/\/\/\/\/\/0SAZZr\/\/\/\/\/\/4SAZY3\/\/\/\/\/w3\/EAEAqALR0LKTlmdoKgsafay6AZZr\/\/\/\/\/wzvAZZr\/\/\/\/\/wruAZZr\/\/\/\/\/wnuAZZr\/\/\/\/\/wnoAZZr\/\/\/\/\/wjoAZZr\/\/\/\/\/wbqAZZr\/\/\/\/\/wbmAZZr\/\/\/\/\/wTqAZZr\/\/\/\/\/wPsAZZr\/\/\/\/\/wHrAZY3\/\/\/\/\/w0A7v9\/VQHy9LamiFlJC0taemhWAZZr\/\/\/\/\/+0PAZYAAAAAAAAAAA=="
    },
    {
      "word" : "P Q R S T",
      "count" : 5,
      "type" : 4,
      "ink" : "UFdJQzEuMDUAAI0APwEAAAD\/AAAU\/\/\/\/\/ywBAAMkAWoAACBC8gGWa\/\/\/\/\/8CFwGWa\/\/\/\/\/8CHQGWa\/\/\/\/\/8CKQGWa\/\/\/\/\/8BJgGWa\/\/\/\/\/8BJAGWa\/\/\/\/\/8BJwGWa\/\/\/\/\/8BIgGWa\/\/\/\/\/8AHgGWa\/\/\/\/\/8AHwGWa\/\/\/\/\/8BGwGWa\/\/\/\/\/8AFwGWa\/\/\/\/\/8AFgGWN\/\/\/\/\/8HABIAPPDQoJAgUdEBlmv\/\/\/\/\/\/\/ABlmv\/\/\/\/\/\/u8Blhb\/\/\/\/\/EgYB4gD7\/6uqCjFAYWJicnJygYCAo6aWq5yMfwGWN\/\/\/\/\/8BEPoCXwGWa\/\/\/\/\/8S\/QGWa\/\/\/\/\/8Q\/wGWa\/\/\/\/\/8QAAGWN\/\/\/\/\/8UEgIAAEBVVQA\/X359e6qnptXS0uLkxdq6q66OjwGWa\/\/\/\/\/\/vBgGWN\/\/\/\/\/8B8AYBTwGWN\/\/\/\/\/8I8ANVVQA+LRsZFhckSAGWFv\/\/\/\/8DCgNiABcVCAoBlmv\/\/\/\/\/7wgBlmv\/\/\/\/\/7g0Blmv\/\/\/\/\/7RMBlmv\/\/\/\/\/6xwBlmv\/\/\/\/\/8B0Blmv\/\/\/\/\/8hwBlmv\/\/\/\/\/9CIBlmv\/\/\/\/\/+B8Blmv\/\/\/\/\/+R0Blmv\/\/\/\/\/\/B8Blmv\/\/\/\/\/\/hsBlmv\/\/\/\/\/ABgBlmv\/\/\/\/\/AhgBlmv\/\/\/\/\/AxMBljf\/\/\/\/\/DAQQAACoAPa2lohoSTsbC0x8mwGWa\/\/\/\/\/8N8AGWa\/\/\/\/\/8L7wGWa\/\/\/\/\/8K7wGWa\/\/\/\/\/8K5wGWa\/\/\/\/\/8I5QGWa\/\/\/\/\/8I5QGWa\/\/\/\/\/8H4AGWa\/\/\/\/\/8F4wGWa\/\/\/\/\/8D5gGWa\/\/\/\/\/8B5AGWa\/\/\/\/\/\/\/6QGWa\/\/\/\/\/\/97AGWN\/\/\/\/\/8L+e3\/fxX4ybx6akspCQkXJQGWa\/\/\/\/\/\/tBgGWFv\/\/\/\/8SAAOcAQAAAAAAITJTdGV0qLnb3ruaiWlINyYlAZZr\/\/\/\/\/xIGAZYW\/\/\/\/\/wS8A8gAAgASMmKSAZZr\/\/\/\/\/wMSAZZr\/\/\/\/\/wQVAZZr\/\/\/\/\/wUWAZZr\/\/\/\/\/wYfAZZr\/\/\/\/\/wceAZZr\/\/\/\/\/wccAZZr\/\/\/\/\/wgfAZZr\/\/\/\/\/wcaAZZr\/\/\/\/\/wcWAZZr\/\/\/\/\/wcUAZY3\/\/\/\/\/wkGEQD4A9a1hGN1gkFygQGWa\/\/\/\/\/\/98AGWa\/\/\/\/\/\/97gGWa\/\/\/\/\/\/97QGWa\/\/\/\/\/\/85QGWa\/\/\/\/\/\/95QGWa\/\/\/\/\/\/95QGWa\/\/\/\/\/\/83wGWa\/\/\/\/\/\/+4gGWa\/\/\/\/\/\/+4wGWa\/\/\/\/\/\/\/3wGWa\/\/\/\/\/\/\/5AGWa\/\/\/\/\/\/\/5gGWa\/\/\/\/\/8B5QGWa\/\/\/\/\/8D6gGWa\/\/\/\/\/8D7AGWN\/\/\/\/\/8LB+6qAgDnx5p5SQtKasnY5wGWa\/\/\/\/\/8FEwGWa\/\/\/\/\/8FEwGWa\/\/\/\/\/8DEwGWa\/\/\/\/\/8BFgGWa\/\/\/\/\/\/+FAGWa\/\/\/\/\/\/+EwGWa\/\/\/\/\/\/6EwGWN\/\/\/\/\/8h+RFVVVUAAAAAAADo6rqajGpZWTY2RUNBU1V4eWqMfGt+fHt9jHqceWl5V1cBlmv\/\/\/\/\/GBMBlhb\/\/\/\/\/GdQFggD6VVVVVQAAUHCERQgpOW59jK+urb2rmbiWhJGDhIqMjgGWa\/\/\/\/\/8SCQGWa\/\/\/\/\/8SCAGWa\/\/\/\/\/8RCAGWa\/\/\/\/\/8TCQGWa\/\/\/\/\/8SCQGWa\/\/\/\/\/8QCAGWN\/\/\/\/\/8CEAsAvr0Blmv\/\/\/\/\/CxABljf\/\/\/\/\/AQkQAPYBlmv\/\/\/\/\/BhMBljf\/\/\/\/\/AQQQAOMBljf\/\/\/\/\/CAIQUFUA4cDSs5Wqm4sBlmv\/\/\/\/\/8AgBlmv\/\/\/\/\/7wYBlmv\/\/\/\/\/7wUBlmv\/\/\/\/\/7QQBlmv\/\/\/\/\/7gQBlmv\/\/\/\/\/8AIBljf\/\/\/\/\/Ce8C9f8DHhsaOEZ0c4EjAZYW\/\/\/\/\/wP4BjIAFSIywgGWa\/\/\/\/\/\/+EQGWa\/\/\/\/\/\/\/FgGWa\/\/\/\/\/\/+IgGWa\/\/\/\/\/\/+IgGWa\/\/\/\/\/\/+IgGWa\/\/\/\/\/\/+JwGWa\/\/\/\/\/\/+IwGWa\/\/\/\/\/\/\/IAGWa\/\/\/\/\/\/\/IAGWa\/\/\/\/\/\/\/HAGWa\/\/\/\/\/8AFwGWa\/\/\/\/\/8BFgGWN\/\/\/\/\/8HAhEAPOKykmKTEYcBlhb\/\/\/\/\/BhgG0AC\/CkFRgZCBYgGWa\/\/\/\/\/8Q9wGWa\/\/\/\/\/8Y9QGWa\/\/\/\/\/8f9AGWa\/\/\/\/\/8s8QGWa\/\/\/\/\/8o8gGWa\/\/\/\/\/8m8wGWa\/\/\/\/\/8o8gGWa\/\/\/\/\/8k9AGWa\/\/\/\/\/8g9AGWa\/\/\/\/\/8f9AGWa\/\/\/\/\/8a9gGWO\/\/\/\/\/8BF\/ipAZYAAAAAAAAAAA=="
    },
    {
      "word" : "U V W",
      "count" : 3,
      "type" : 4,
      "ink" : "UFdJQzEuMDUAAGsAPwEAAAD\/AAAU\/\/\/\/\/ywBAAQCAbAACgBBYTLAAZZr\/\/\/\/\/wASAZZr\/\/\/\/\/\/8dAZZr\/\/\/\/\/wAcAZZr\/\/\/\/\/wAcAZZr\/\/\/\/\/wAhAZZr\/\/\/\/\/wIeAZZr\/\/\/\/\/wIbAZZr\/\/\/\/\/wQcAZZr\/\/\/\/\/wUXAZZr\/\/\/\/\/wYUAZY3\/\/\/\/\/wsIEwCAKvjYuYlpShkZWouqAZZr\/\/\/\/\/w3uAZZr\/\/\/\/\/wztAZZr\/\/\/\/\/wvsAZZr\/\/\/\/\/wzjAZZr\/\/\/\/\/wvjAZZr\/\/\/\/\/wriAZZr\/\/\/\/\/wncAZZr\/\/\/\/\/wjeAZZr\/\/\/\/\/wbgAZZr\/\/\/\/\/wbeAZZr\/\/\/\/\/wTkAZZr\/\/\/\/\/wPnAZZr\/\/\/\/\/wHqAZY3\/\/\/\/\/woB7f4fAPDRoXGDUjJxYmIBlmv\/\/\/\/\/DBkBlhb\/\/\/\/\/A8YCjAADglDxAZZr\/\/\/\/\/wMXAZZr\/\/\/\/\/wQeAZZr\/\/\/\/\/wYnAZZr\/\/\/\/\/wYjAZZr\/\/\/\/\/wYhAZZr\/\/\/\/\/wchAZZr\/\/\/\/\/wYdAZZr\/\/\/\/\/wcZAZZr\/\/\/\/\/wgXAZZr\/\/\/\/\/wcUAZY3\/\/\/\/\/wsGEAAAKue2hodVVkgmVnW2AZZr\/\/\/\/\/wbsAZZr\/\/\/\/\/wbpAZZr\/\/\/\/\/wbnAZZr\/\/\/\/\/wfdAZZr\/\/\/\/\/wbeAZZr\/\/\/\/\/wXfAZZr\/\/\/\/\/wXZAZZr\/\/\/\/\/wXdAZZr\/\/\/\/\/wPfAZZr\/\/\/\/\/wPeAZZr\/\/\/\/\/wLkAZZr\/\/\/\/\/wLnAZZr\/\/\/\/\/wHqAZY3\/\/\/\/\/wkB7qoCAOCxkHEiI2Rk2AGWGv\/\/\/\/8GIASUAJKjtRZFdAGWa\/\/\/\/\/8DEAGWa\/\/\/\/\/8DFAGWa\/\/\/\/\/8CFwGWa\/\/\/\/\/8CIQGWa\/\/\/\/\/8BIQGWa\/\/\/\/\/8BIQGWa\/\/\/\/\/8BJwGWa\/\/\/\/\/8AJAGWa\/\/\/\/\/8AIgGWa\/\/\/\/\/8CIwGWa\/\/\/\/\/8CHQGWa\/\/\/\/\/8CGQGWa\/\/\/\/\/8EGQGWa\/\/\/\/\/8EFAGWN\/\/\/\/\/8KBBEAgAr0xZR0VEQFNUXWAZZr\/\/\/\/\/wfwAZZr\/\/\/\/\/wftAZZr\/\/\/\/\/wnkAZZr\/\/\/\/\/wriAZZr\/\/\/\/\/wriAZZr\/\/\/\/\/wvbAZZr\/\/\/\/\/wreAZZr\/\/\/\/\/wrgAZZr\/\/\/\/\/wrdAZZr\/\/\/\/\/wngAZZr\/\/\/\/\/wjkAZZr\/\/\/\/\/wfkAZZr\/\/\/\/\/wbqAZY3\/\/\/\/\/wYF7SoA46NiMpHRAZZr\/\/\/\/\/wAWAZZr\/\/\/\/\/wAXAZZr\/\/\/\/\/wAYAZZr\/\/\/\/\/wAcAZZr\/\/\/\/\/wAYAZZr\/\/\/\/\/wAVAZZr\/\/\/\/\/wIVAZZr\/\/\/\/\/wETAZY3\/\/\/\/\/wwCEAAAqgDzw5OUYlNkNBQ1VdgBlmv\/\/\/\/\/CPABlmv\/\/\/\/\/CO0Blmv\/\/\/\/\/C+QBlmv\/\/\/\/\/CuMBlmv\/\/\/\/\/CuMBlmv\/\/\/\/\/CtsBlmv\/\/\/\/\/Cd4Blmv\/\/\/\/\/COEBlmv\/\/\/\/\/B98Blmv\/\/\/\/\/BeQBlmv\/\/\/\/\/BOcBlmv\/\/\/\/\/A+kBlmv\/\/\/\/\/Au4Blmv\/\/\/\/\/AvABljf\/\/\/\/\/BwHwAgChoyBQYEGzAZYAAAAAAAAAAA=="
    },
    {
      "word" : "X Y Z",
      "count" : 3,
      "type" : 4,
      "ink" : "UFdJQzEuMDUAAFUAPwEAAAD\/AAAU\/\/\/\/\/ywBAAS2AggAVQAzY6OzAZZr\/\/\/\/\/\/chAZZr\/\/\/\/\/\/UsAZZr\/\/\/\/\/\/I0AZZr\/\/\/\/\/+5CAZZr\/\/\/\/\/\/A6AZZr\/\/\/\/\/\/E0AZZr\/\/\/\/\/\/A0AZZr\/\/\/\/\/\/IsAZZr\/\/\/\/\/\/MlAZZr\/\/\/\/\/\/IjAZZr\/\/\/\/\/\/QcAZZr\/\/\/\/\/\/UXAZY3\/\/\/\/\/wr1FFX1D\/m4mHZWF0V0ZNcBlhb\/\/\/\/\/BdABegAAACI1h7jYAZZr\/\/\/\/\/w0XAZZr\/\/\/\/\/wwYAZZr\/\/\/\/\/wwaAZZr\/\/\/\/\/xAiAZZr\/\/\/\/\/w8gAZZr\/\/\/\/\/w8eAZZr\/\/\/\/\/xEiAZZr\/\/\/\/\/xAdAZZr\/\/\/\/\/w8ZAZZr\/\/\/\/\/xAZAZZr\/\/\/\/\/w4UAZY3\/\/\/\/\/w4NEQAAAAr9zKqKaVc4OCcZGAgbKAGWa\/\/\/\/\/8U+wEAGv\/\/\/\/8D7ANcALoaSgGWa\/\/\/\/\/8CEQGWa\/\/\/\/\/8DFwGWa\/\/\/\/\/8FHQGWa\/\/\/\/\/8IJAGWa\/\/\/\/\/8HHgGWa\/\/\/\/\/8HGQGWa\/\/\/\/\/8JFwGWa\/\/\/\/\/8HEgGWN\/\/\/\/\/8PBhAAAKAq56aVdWVFRiYmCChIeml4AZZr\/\/\/\/\/x7lAQAW\/\/\/\/\/wbwBEIAVQUiQ2SWlZUBlmv\/\/\/\/\/+BMBlmv\/\/\/\/\/+BYBlmv\/\/\/\/\/9xoBlmv\/\/\/\/\/8yYBlmv\/\/\/\/\/8yYBlmv\/\/\/\/\/8ycBlmv\/\/\/\/\/8DIBlmv\/\/\/\/\/8jABlmv\/\/\/\/\/8i8Blmv\/\/\/\/\/8y8Blmv\/\/\/\/\/9SUBlmv\/\/\/\/\/+BwBlmv\/\/\/\/\/+RcBljf\/\/\/\/\/EPoSVVUEoADUtJNzk4KRgYBxYFFSAyOLAgAAFv\/\/\/\/8EogWOAKAAJgQZHQGWa\/\/\/\/\/8Q\/wGWa\/\/\/\/\/8W\/wGWa\/\/\/\/\/8V\/wGWa\/\/\/\/\/8T\/wGWa\/\/\/\/\/8U\/wGWa\/\/\/\/\/8RAAGWN\/\/\/\/\/8MEP8AAFQADw0LCgkWODVgg6T7AZZr\/\/\/\/\/\/MSAZZr\/\/\/\/\/\/ESAZZr\/\/\/\/\/+wXAZZr\/\/\/\/\/+wVAZZr\/\/\/\/\/+0UAZZr\/\/\/\/\/+sVAZZr\/\/\/\/\/+0SAZZr\/\/\/\/\/+4QAZZr\/\/\/\/\/+4QAZY3\/\/\/\/\/xDwDlVVBQAA38+tm5p4dmVzYmJkVkw8PgGWa\/\/\/\/\/8TAQGWa\/\/\/\/\/8T\/wGWa\/\/\/\/\/8U\/gGWa\/\/\/\/\/8Z+wGWa\/\/\/\/\/8Y+gGWa\/\/\/\/\/8Y+gGWa\/\/\/\/\/8c9gGWa\/\/\/\/\/8a9QGWa\/\/\/\/\/8Y9gGWa\/\/\/\/\/8Z9AGWa\/\/\/\/\/8U9wGWN\/\/\/\/\/8DEfkqf2tIAZZr\/\/\/\/\/xzzAZYAAAAAAAAAAA=="
    },
    {
      "word" : "1 2 3 4 5",
      "count" : 5,
      "type" : 3,
      "ink" : "UFdJQzEuMDUAAFAAPwEAAAD\/AAAU\/\/\/\/\/ywBAAOcAVgAACBQ8AGWa\/\/\/\/\/8AFgGWa\/\/\/\/\/8AGwGWa\/\/\/\/\/8AJwGWa\/\/\/\/\/8AJQGWa\/\/\/\/\/8AIwGWa\/\/\/\/\/\/\/KAGWa\/\/\/\/\/8AJAGWa\/\/\/\/\/\/\/IQGWa\/\/\/\/\/8AIQGWa\/\/\/\/\/\/\/HQGWa\/\/\/\/\/8AGQGWa\/\/\/\/\/\/\/GAGWa\/\/\/\/\/\/\/FAGWN\/\/\/\/\/8JABEFoALhwZCgYDQ1I4sBlhb\/\/\/\/\/Bj4CogCqCjEjJDhKWwGWN\/\/\/\/\/8LEPqqAgBNTS0aGRg3RYSjwgGWa\/\/\/\/\/8AEQGWa\/\/\/\/\/\/9EQGWa\/\/\/\/\/\/8EgGWa\/\/\/\/\/\/6FgGWa\/\/\/\/\/\/5FAGWa\/\/\/\/\/\/5EwGWa\/\/\/\/\/\/4FAGWa\/\/\/\/\/\/5EgGWa\/\/\/\/\/\/6EAGWN\/\/\/\/\/8R+hBVFQAAAObFxLSioqGQkpOFeFpLLh4NAZY3\/\/\/\/\/wIQ\/Qo\/XgGWa\/\/\/\/\/8R+QGWN\/\/\/\/\/8BEPkCfwGWa\/\/\/\/\/8S9wGWa\/\/\/\/\/8R+AGWa\/\/\/\/\/8R9wGWN\/\/\/\/\/8FEfeqAn5rbFtJAZZr\/\/\/\/\/yXwAZYW\/\/\/\/\/wQoBGoAAgAoBAkMAZZr\/\/\/\/\/xABAZZr\/\/\/\/\/xQBAZY3\/\/\/\/\/z8RAQAAVVVVVQAAAABAVVVVVQUfHhwZODZEgYGj2Ona\/Nu6u5mHdlVDZFJQUlNmdmeJmom8qpmYl4aFdHKBcWGGdniLe3t8a1paSUdHNiU1JEUBlhb\/\/\/\/\/BnwFSABVBRIjZHOi9AGWa\/\/\/\/\/\/7EAGWa\/\/\/\/\/\/7EQGWa\/\/\/\/\/\/6FAGWa\/\/\/\/\/\/7EwGWa\/\/\/\/\/\/7EAGWN\/\/\/\/\/8i\/BJVAQAAqqqqqgrz0tKxkYByUkU1JhgpGQsLGj48TW5sW3xqaXl4dnZlU4RzAZZr\/\/\/\/\/wjwAZYW\/\/\/\/\/wMqBjQAFUJh8wGWa\/\/\/\/\/\/8FAGWa\/\/\/\/\/\/8GAGWa\/\/\/\/\/\/6IgGWa\/\/\/\/\/\/7IgGWa\/\/\/\/\/\/6IQGWa\/\/\/\/\/\/5JgGWa\/\/\/\/\/\/5IgGWa\/\/\/\/\/\/6HwGWa\/\/\/\/\/\/6HwGWa\/\/\/\/\/\/6GwGWa\/\/\/\/\/\/8FwGWa\/\/\/\/\/\/8FgGWN\/\/\/\/\/8M\/RJVAQAA8tKxkbGAYVJUNCYnAZZr\/\/\/\/\/xcEAZYW\/\/\/\/\/xRGB1gAV1UVAAAAFSdIaay5yNfFs8Gho7e3uNra2fsBljf\/\/\/\/\/AQkQAPkBlmv\/\/\/\/\/CBMBlmv\/\/\/\/\/BhABlmv\/\/\/\/\/BRABlmv\/\/\/\/\/BBEBljf\/\/\/\/\/GQMQQFVVVfX\/A\/PxwLGjhXVpaUlNPC0vHhwOCxsqKSdHRVUBlmv\/\/\/\/\/8e8Blhb\/\/\/\/\/BBoHyACqABIjSl4Blmv\/\/\/\/\/EfoBlmv\/\/\/\/\/GPgBlmv\/\/\/\/\/FfgBlmv\/\/\/\/\/E\/gBlmv\/\/\/\/\/FPcBlmv\/\/\/\/\/EvgBlmv\/\/\/\/\/EPkBljf\/\/\/\/\/BxD5qipvXE06KTsYAZZr\/\/\/\/\/xT9AQEAAAAAAAAAAA=="
    },
    {
      "word" : "6 7 8 9 0",
      "count" : 5,
      "type" : 3,
      "ink" : "UFdJQzEuMDUAAGYAPwEAAAD\/AAAU\/\/\/\/\/ywBAAmSAYIA\/1UBIiM0FiZHmbjIAZZr\/\/\/\/\/\/YSAZZr\/\/\/\/\/\/YRAZZr\/\/\/\/\/\/gSAZZr\/\/\/\/\/\/YWAZZr\/\/\/\/\/\/gUAZZr\/\/\/\/\/\/kUAZZr\/\/\/\/\/\/oYAZZr\/\/\/\/\/\/wWAZZr\/\/\/\/\/\/wVAZZr\/\/\/\/\/\/4YAZZr\/\/\/\/\/wAWAZZr\/\/\/\/\/wEUAZZr\/\/\/\/\/wQVAZY3\/\/\/\/\/wcEEgAA9unJqo1+TQGWN\/\/\/\/\/8CEAIIDx4Bljf\/\/\/\/\/BRH6qgKPru\/t7AGWN\/\/\/\/\/8gC++q+l9VVVUAAADo19a1k4BhQjcoCDxce727utnYxtXEs8GRg4RVVEc3NgGWa\/\/\/\/\/8cCQGWFv\/\/\/\/8EiAKWAAAAIiUXGgGWa\/\/\/\/\/8TAQGWa\/\/\/\/\/8VAQGWa\/\/\/\/\/8YAAGWa\/\/\/\/\/8dAAGWa\/\/\/\/\/8Z\/wGWa\/\/\/\/\/8V\/wGWa\/\/\/\/\/8V\/gGWN\/\/\/\/\/8LEv6qChU\/TzspOxc0QqHE9gGWa\/\/\/\/\/\/3GgGWa\/\/\/\/\/\/1GwGWa\/\/\/\/\/\/1HQGWa\/\/\/\/\/\/yJQGWa\/\/\/\/\/\/0IQGWa\/\/\/\/\/\/1HwGWa\/\/\/\/\/\/0IAGWa\/\/\/\/\/\/2HAGWa\/\/\/\/\/\/4GQGWa\/\/\/\/\/\/3GAGWa\/\/\/\/\/\/5FAGWN\/\/\/\/\/8J+hFVoQL2tJSTYTMkJUUBlmv\/\/\/\/\/GPIBABb\/\/\/\/\/CqIEogC7VwVBUIFQJAYpfa28AZZr\/\/\/\/\/\/MRAZZr\/\/\/\/\/\/UQAZZr\/\/\/\/\/\/cQAZY3\/\/\/\/\/xT4ElUAgKqqAPbl4sGglHVWOCkYK0tarKu6++n3AZY3\/\/\/\/\/xUH76r+\/1VVAeXk4sKwopJkZkY2KQgHOTc3RkVEzAIAABb\/\/\/\/\/HXIEaAFfVQEAAKqqAiQlJlaE1cOy0rCwooNkVkc2KBgIKjhZeYmYyNfXAZZr\/\/\/\/\/wbwAZY3\/\/\/\/\/wEE8ALkAZY3\/\/\/\/\/xEC8Pr\/VVUB0cGyk3RYSCgaSFiHdmR0VFMBlmv\/\/\/\/\/9RABlhb\/\/\/\/\/GOwFuACqqqr+f1UAITNDZURDZHRzo4NycGJSVkc3Gxs8j67NAZZr\/\/\/\/\/\/IRAZZr\/\/\/\/\/\/QSAZZr\/\/\/\/\/\/USAZZr\/\/\/\/\/\/cVAZZr\/\/\/\/\/\/kTAZZr\/\/\/\/\/\/oRAZY3\/\/\/\/\/xv9EQWAqqqqKgDhsaOEZSkZGlxbe628zOzKybiohnVkUwMxYuABlmv\/\/\/\/\/\/xABlmv\/\/\/\/\/\/xEBlmv\/\/\/\/\/\/hYBlmv\/\/\/\/\/\/xQBlmv\/\/\/\/\/\/hIBlmv\/\/\/\/\/\/xQBlmv\/\/\/\/\/\/xIBlmv\/\/\/\/\/\/xABljf\/\/\/\/\/FP8QBAAAgKoA4LGgkICwkXFxYpNjY1MDIzRlhXUBlmv\/\/\/\/\/EuABlhb\/\/\/\/\/D3wHpgD\/\/38VQWGRoYFhYlJTdUYWN1faAZZr\/\/\/\/\/\/YQAZZr\/\/\/\/\/\/YSAZZr\/\/\/\/\/\/MbAZZr\/\/\/\/\/\/QcAZZr\/\/\/\/\/\/UcAZZr\/\/\/\/\/\/UgAZZr\/\/\/\/\/\/YdAZZr\/\/\/\/\/\/kbAZZr\/\/\/\/\/\/kcAZZr\/\/\/\/\/\/sYAZZr\/\/\/\/\/\/0XAZZr\/\/\/\/\/\/0WAZZr\/\/\/\/\/\/8UAZZr\/\/\/\/\/wAQAZY3\/\/\/\/\/wsBEAAAKuO0pnZmSRoJbIy8AZZr\/\/\/\/\/w\/uAZZr\/\/\/\/\/w7sAZZr\/\/\/\/\/w3sAZZr\/\/\/\/\/w\/kAZZr\/\/\/\/\/w7kAZZr\/\/\/\/\/w3lAZZr\/\/\/\/\/wzhAZZr\/\/\/\/\/wrkAZZr\/\/\/\/\/wnmAZZr\/\/\/\/\/wflAZZr\/\/\/\/\/wXpAZZr\/\/\/\/\/wTsAZZr\/\/\/\/\/wHtAZY3\/\/\/\/\/w0A7\/9\/VQHSxaZ3WjoqLExrzuzrAZY3\/\/\/\/\/wX0EVUB+ujIpoQBlmv\/\/\/\/\/8RgBlgAAAAAAAAAA"
    },
    {
      "word" : "* ! $ ? ^",
      "count" : 5,
      "type" : 2,
      "ink" : "UFdJQzEuMDUAAIQAPwEAAAD\/AAAY\/\/\/\/\/ywBAANwATQAKkprAZZr\/\/\/\/\/\/oRAZZr\/\/\/\/\/\/kXAZZr\/\/\/\/\/\/kcAZZr\/\/\/\/\/\/cjAZZr\/\/\/\/\/\/gfAZZr\/\/\/\/\/\/obAZZr\/\/\/\/\/\/obAZZr\/\/\/\/\/\/sWAZZr\/\/\/\/\/\/sTAZY3\/\/\/\/\/w38ElXV\/wPlxJWFVFcmJTRDg4KCAZZr\/\/\/\/\/\/nfAZYW\/\/\/\/\/xkGAW4AAAAAAABQARI0NUVVeJmp7NzL7cu6uoiHZ1VEU0NBFQsBlhb\/\/\/\/\/BQABBAGqAjEyZniKAZZr\/\/\/\/\/xH0AZZr\/\/\/\/\/xT0AZZr\/\/\/\/\/xTzAZZr\/\/\/\/\/xnxAZZr\/\/\/\/\/xT0AZY7\/\/\/\/\/wES9rsBlhb\/\/\/\/\/BJICegAAAGJQoOABlmv\/\/\/\/\/\/hkBlmv\/\/\/\/\/\/h4Blmv\/\/\/\/\/\/SABlmv\/\/\/\/\/\/SQBlmv\/\/\/\/\/\/R8Blmv\/\/\/\/\/\/hkBlmv\/\/\/\/\/\/xgBlmv\/\/\/\/\/\/xMBljf\/\/\/\/\/Bf8QQQHxwKCxkQGWa\/\/\/\/\/\/9FAGWSv\/\/\/\/+CAkQCAdAW\/\/\/\/\/wuSBGYAVVUVExU3OEhLOzpNPk4Blmv\/\/\/\/\/7wMBlmv\/\/\/\/\/8AQBlmv\/\/\/\/\/8AMBlmv\/\/\/\/\/7QMBlmv\/\/\/\/\/7gQBlmv\/\/\/\/\/7gQBlmv\/\/\/\/\/7QYBlmv\/\/\/\/\/7wYBlmv\/\/\/\/\/8AcBljf\/\/\/\/\/CPAJVQEAjIuopqSylpgBlmv\/\/\/\/\/EAkBlmv\/\/\/\/\/EgcBlmv\/\/\/\/\/EgUBlmv\/\/\/\/\/GAYBlmv\/\/\/\/\/FwYBlmv\/\/\/\/\/FQUBlmv\/\/\/\/\/GAYBlmv\/\/\/\/\/FQcBlmv\/\/\/\/\/EgYBlmv\/\/\/\/\/EgoBljf\/\/\/\/\/BBAKAACt6\/j3AZZr\/\/\/\/\/wMTAZZr\/\/\/\/\/wESAZZr\/\/\/\/\/wASAZZr\/\/\/\/\/\/0TAZY3\/\/\/\/\/wf7EFUV9enJup6NfgGWN\/\/\/\/\/8C7wYFT04Bljf\/\/\/\/\/CPAC9f8ALh4eLkys2ugBlmv\/\/\/\/\/+ekBlmv\/\/\/\/\/++gBljv\/\/\/\/\/AfznuwGWFv\/\/\/\/8GuANkAAAAQnJyo8PkAZZr\/\/\/\/\/wUYAZZr\/\/\/\/\/wYaAZZr\/\/\/\/\/wUbAZZr\/\/\/\/\/wcmAZZr\/\/\/\/\/wUlAZZr\/\/\/\/\/wQlAZZr\/\/\/\/\/wQrAZZr\/\/\/\/\/wMmAZZr\/\/\/\/\/wIjAZZr\/\/\/\/\/wIkAZZr\/\/\/\/\/wEeAZZr\/\/\/\/\/wEaAZZr\/\/\/\/\/wAXAZY3\/\/\/\/\/woBEgCqCuDhkRRDYmNzY1MBlmv\/\/\/\/\/C\/ABJhr\/\/\/\/\/ARoEWgBAAZZr\/\/\/\/\/wAQAZZr\/\/\/\/\/wEZAZZr\/\/\/\/\/wAfAZZr\/\/\/\/\/wIzAZZr\/\/\/\/\/wM1AZZr\/\/\/\/\/wQ3AZZr\/\/\/\/\/wY8AZZr\/\/\/\/\/wcyAZZr\/\/\/\/\/wYrAZZr\/\/\/\/\/wcoAZZr\/\/\/\/\/wYiAZY7\/\/\/\/\/wEGHqoBlhb\/\/\/\/\/CyYFoACqqioyU0RFNDYmNkpcXgGWa\/\/\/\/\/8S+QGWN\/\/\/\/\/8NEfuqKgAAT08+LCwaGRgoNnaElAGWa\/\/\/\/\/8CEAGWa\/\/\/\/\/8BEQGWa\/\/\/\/\/8AEwGWa\/\/\/\/\/\/8GgGWa\/\/\/\/\/\/6GgGWa\/\/\/\/\/\/5GgGWa\/\/\/\/\/\/1HQGWa\/\/\/\/\/\/2GQGWa\/\/\/\/\/\/3FgGWa\/\/\/\/\/\/1FgGWN\/\/\/\/\/8V9hJVVRUAAAD52qiXZ1VERURUUkFCRTZHJicWGR0Blkr\/\/\/\/\/sgWQAgEAFv\/\/\/\/8EpAYyAaoAQHCy9AGWa\/\/\/\/\/8G7wGWa\/\/\/\/\/8K6QGWa\/\/\/\/\/8K6AGWa\/\/\/\/\/8K6QGWa\/\/\/\/\/8M5gGWa\/\/\/\/\/8L6QGWa\/\/\/\/\/8K6wGWa\/\/\/\/\/8J7AGWN\/\/\/\/\/8NCPCqKgAA17WUc3NDJDJSYrPC4wGWa\/\/\/\/\/8CEwGWa\/\/\/\/\/8CEgGWa\/\/\/\/\/8CEwGWa\/\/\/\/\/8CFwGWa\/\/\/\/\/8BFgGWa\/\/\/\/\/8BFgGWa\/\/\/\/\/8AGAGWa\/\/\/\/\/8AFwGWa\/\/\/\/\/8AFQGWa\/\/\/\/\/8AFwGWa\/\/\/\/\/\/\/FQGWa\/\/\/\/\/8AEwGWN\/\/\/\/\/8CABIA8LABlmv\/\/\/\/\/ACQBlgAAAAAAAAAA"
    },
    {
      "word" : "& @ ( ) %",
      "count" : 5,
      "type" : 2,
      "ink" : "UFdJQzEuMDUAAKMAPwEAAAD\/AAAU\/\/\/\/\/ywBACEYAjYC\/\/\/\/\/\/\/\/\/\/8DIiQlRkdGVlZVZWZlh5aWt7amx7a21cWk1MOz4sLC8vHhAZZr\/\/\/\/\/wDvAZZr\/\/\/\/\/\/\/wAZZr\/\/\/\/\/wDwAZZr\/\/\/\/\/wDtAZZr\/\/\/\/\/wLvAZZr\/\/\/\/\/wLwAZY3\/\/\/\/\/ykD7qqqqioCAAAAVVUB9OPk1bW1hXRlVVU3NykqCRgpKDhYaXiqqLjX1rTT08HhxMTZurrezr4Blmv\/\/\/\/\/7Q4Blmv\/\/\/\/\/7g4Blmv\/\/\/\/\/7w4Blmv\/\/\/\/\/6xIBlmv\/\/\/\/\/7BEBlmv\/\/\/\/\/7hEBlmv\/\/\/\/\/7hQBlmv\/\/\/\/\/8BMBlmv\/\/\/\/\/8hIBlmv\/\/\/\/\/9BUBlmv\/\/\/\/\/9hIBlmv\/\/\/\/\/+BEBlmv\/\/\/\/\/+hIBljf\/\/\/\/\/CvsQBQAA5PHRs6aXeG1dPwGWa\/\/\/\/\/8TAgGWa\/\/\/\/\/8TAAGWa\/\/\/\/\/8S\/wGWa\/\/\/\/\/8W\/QGWa\/\/\/\/\/8T\/AGWa\/\/\/\/\/8S\/AGWa\/\/\/\/\/8S+gGWN\/\/\/\/\/8ZEPqqqqr6\/\/8Dbm1cWllYR1ZURHNzgaChssXGtsmpmat8ewGWN\/\/\/\/\/8B8PsDPwGWa\/\/\/\/\/\/w\/gGWa\/\/\/\/\/\/tAQGWa\/\/\/\/\/\/uAwGWa\/\/\/\/\/\/vBQGWN\/\/\/\/\/8F7wlVAa\/N2simAZZr\/\/\/\/\/\/ElAZYW\/\/\/\/\/wfyAywB\/xUkJTknWJvcAZZr\/\/\/\/\/\/AUAZZr\/\/\/\/\/\/MTAZZr\/\/\/\/\/\/QTAZZr\/\/\/\/\/\/YVAZZr\/\/\/\/\/\/gSAZZr\/\/\/\/\/\/oQAZY3\/\/\/\/\/xD8EBUAqqoAxLKhcGJlRRYVFWd2hufm9QGWa\/\/\/\/\/8G7AGWa\/\/\/\/\/8E7gGWa\/\/\/\/\/8E7wGWa\/\/\/\/\/8E7QGWN\/\/\/\/\/8cA++qCgAAAKCqAPLhsZGhYCGAkLDx4OHiw7SWZldIKCgpOWepubgBlmv\/\/\/\/\/Ce4Blmv\/\/\/\/\/CewBlmv\/\/\/\/\/COwBlmv\/\/\/\/\/B+UBlmv\/\/\/\/\/BuYBlmv\/\/\/\/\/BOYBlmv\/\/\/\/\/AuQBlmv\/\/\/\/\/AOkBlmv\/\/\/\/\/\/+sBljf\/\/\/\/\/AvrtD\/nLAZZr\/\/\/\/\/+36AZZr\/\/\/\/\/+v+AZZr\/\/\/\/\/+sCAZZr\/\/\/\/\/+QLAZZr\/\/\/\/\/+UPAZZr\/\/\/\/\/+YRAZZr\/\/\/\/\/+QZAZZr\/\/\/\/\/+kaAZZr\/\/\/\/\/+sZAZZr\/\/\/\/\/+0eAZZr\/\/\/\/\/\/IcAZZr\/\/\/\/\/\/UbAZZr\/\/\/\/\/\/ccAZZr\/\/\/\/\/\/saAZZr\/\/\/\/\/\/0WAZZr\/\/\/\/\/wAYAZZr\/\/\/\/\/wMUAZZr\/\/\/\/\/wQRAZZr\/\/\/\/\/wgSAZY3\/\/\/\/\/wUKEAAD+u7erzEBlhr\/\/\/\/\/CI4FOAALDR4tPV5\/fgGWa\/\/\/\/\/\/zEQGWa\/\/\/\/\/\/xFwGWa\/\/\/\/\/\/vGwGWa\/\/\/\/\/\/qJAGWa\/\/\/\/\/\/uIQGWa\/\/\/\/\/\/vIAGWa\/\/\/\/\/\/wIgGWa\/\/\/\/\/\/zHgGWa\/\/\/\/\/\/2GwGWa\/\/\/\/\/\/3HQGWa\/\/\/\/\/\/6GQGWa\/\/\/\/\/\/7FwGWa\/\/\/\/\/\/9FwGWa\/\/\/\/\/\/+EwGWa\/\/\/\/\/\/\/EQGWN\/\/\/\/\/8LAhEAAADjxceoiGtcPC0aGAGWa\/\/\/\/\/8ZAQEAFv\/\/\/\/8FlAVUAAAABAUFd9oBlmv\/\/\/\/\/CxEBlmv\/\/\/\/\/DRsBlmv\/\/\/\/\/ChoBlmv\/\/\/\/\/CBkBlmv\/\/\/\/\/Bx8Blmv\/\/\/\/\/BR0Blmv\/\/\/\/\/AxsBlmv\/\/\/\/\/Ah8Blmv\/\/\/\/\/ABsBlmv\/\/\/\/\/ABkBlmv\/\/\/\/\/\/RkBlmv\/\/\/\/\/\/BYBlmv\/\/\/\/\/\/BMBlmv\/\/\/\/\/+RQBlmv\/\/\/\/\/+RIBlmv\/\/\/\/\/+BABljf\/\/\/\/\/DPgQVVVVAOfHx6WVhWRjZEJCQgGWFv\/\/\/\/8CsgcuAAUj6AGWa\/\/\/\/\/\/zFgGWa\/\/\/\/\/\/wHQGWa\/\/\/\/\/\/nLgGWa\/\/\/\/\/\/oMAGWa\/\/\/\/\/\/nMAGWa\/\/\/\/\/\/nNAGWa\/\/\/\/\/\/rKQGWa\/\/\/\/\/\/vIQGWa\/\/\/\/\/\/xHQGWa\/\/\/\/\/\/0FgGWN\/\/\/\/\/8J9hFVrQLop5WGUyNRQYYBlhb\/\/\/\/\/B\/QGaABVFQMVFjlHV\/gBlmv\/\/\/\/\/+BUBlmv\/\/\/\/\/9xoBlmv\/\/\/\/\/+B8Blmv\/\/\/\/\/+hoBlmv\/\/\/\/\/\/RUBljf\/\/\/\/\/Df8TAKCqAvHCpWVFFzZHiKem9\/cBlmv\/\/\/\/\/B\/ABlmv\/\/\/\/\/BuwBlmv\/\/\/\/\/Bu0Blmv\/\/\/\/\/Be0Blmv\/\/\/\/\/Be0Bljf\/\/\/\/\/DwPvqn5VJfPiwaHAgiQkdJSj8+LSMAGWFv\/\/\/\/8FrAcAAV8BFCU5jK4Blmv\/\/\/\/\/7hIBlmv\/\/\/\/\/8RMBlmv\/\/\/\/\/8xUBlmv\/\/\/\/\/8hoBlmv\/\/\/\/\/9RkBlmv\/\/\/\/\/9xkBlmv\/\/\/\/\/+BoBlmv\/\/\/\/\/+hcBlmv\/\/\/\/\/+xMBljf\/\/\/\/\/Cv0SAYAK4sCgcmE1BWWXtgGWa\/\/\/\/\/8K7QGWa\/\/\/\/\/8J6wGWa\/\/\/\/\/8J6wGWa\/\/\/\/\/8L5QGWa\/\/\/\/\/8J5gGWa\/\/\/\/\/8J6AGWa\/\/\/\/\/8I5gGWa\/\/\/\/\/8G6gGWa\/\/\/\/\/8E7QGWN\/\/\/\/\/8LAu76VxXhsIVXKU2Mq9yphwGWa\/\/\/\/\/\/oGgGWAAAAAAAAAAA="
    },
    {
      "word" : "< > [ ] #",
      "count" : 5,
      "type" : 2,
      "ink" : "UFdJQzEuMDUAAHQAPwEAAAD\/AAAU\/\/\/\/\/ywBAAYyAm4AVQUEBQdNb58Blmv\/\/\/\/\/7QsBlmv\/\/\/\/\/7wsBlmv\/\/\/\/\/8AoBlmv\/\/\/\/\/7gwBljf\/\/\/\/\/AfAKAa4Bljf\/\/\/\/\/FPAMVVVVFQAAr52tiol5eGZ3h3WmhISCgGJmSUoBlmv\/\/\/\/\/EQIBlmv\/\/\/\/\/EgIBlmv\/\/\/\/\/EgEBlmv\/\/\/\/\/FwEBlmv\/\/\/\/\/FgABlmv\/\/\/\/\/FQABlmv\/\/\/\/\/FwEBlmv\/\/\/\/\/FgABlmv\/\/\/\/\/EwEBlmv\/\/\/\/\/FAQBljf\/\/\/\/\/ARIEAF8Bljf\/\/\/\/\/CBEIAAAAbn5vXk09LBsBlmv\/\/\/\/\/JQMBlhr\/\/\/\/\/BK4CcgAaMkZnAZZr\/\/\/\/\/xEGAZZr\/\/\/\/\/xUGAZZr\/\/\/\/\/xgFAZZr\/\/\/\/\/x0FAZZr\/\/\/\/\/xkEAZZr\/\/\/\/\/xcDAZZr\/\/\/\/\/xcDAZZr\/\/\/\/\/xQCAZZr\/\/\/\/\/xIBAZZr\/\/\/\/\/xIBAZY3\/\/\/\/\/xAQAgAAQFUAHy4sK0pIN2VUY4CTpOr8\/QGWa\/\/\/\/\/\/uFQGWa\/\/\/\/\/\/uFAGWa\/\/\/\/\/\/uFAGWa\/\/\/\/\/\/rGAGWa\/\/\/\/\/\/sFQGWa\/\/\/\/\/\/uFQGWa\/\/\/\/\/\/tFQGWN\/\/\/\/\/8M8BJVVaoA\/v7MqolnViMSRjZGAZZr\/\/\/\/\/xvxAZYW\/\/\/\/\/xgqBVQA\/\/9fVVVVADJDVGVVNDgrHR8NDAsZKCg3NmaFlNTT4gGWa\/\/\/\/\/\/\/EgGWa\/\/\/\/\/\/\/EQGWa\/\/\/\/\/\/\/EQGWa\/\/\/\/\/8BFAGWa\/\/\/\/\/8CEgGWa\/\/\/\/\/8BEQGWa\/\/\/\/\/8DEgGWa\/\/\/\/\/8CEQGWa\/\/\/\/\/8BEAGWa\/\/\/\/\/8CEQGWN\/\/\/\/\/8BARAA8QGWN\/\/\/\/\/8CABEA8OABljf\/\/\/\/\/JAARQVSqqqqqqqqqAPHg4MGwwZGBGBIjJhcXKhoqHR0tHh4sHSoqKTcmSTZFREMzqQGWFv\/\/\/\/8EuAVAAAAAIRUYGgGWa\/\/\/\/\/8QAQGWa\/\/\/\/\/8SAAGWa\/\/\/\/\/8RAAGWa\/\/\/\/\/8UAQGWN\/\/\/\/\/8XEQAAAAAAVRUODhsaGRcmODVUQmJhYJGAkbGxseLi0gGWN\/\/\/\/\/8f\/hBVAAAAAEBVFfLh8dGwwaGClGNjVFNEVFNDZXNjYnNCQkNneIm\/rq8Blmv\/\/\/\/\/7AsBlmv\/\/\/\/\/7gsBlmv\/\/\/\/\/7gkBlmv\/\/\/\/\/6woBlmv\/\/\/\/\/7AgBlmv\/\/\/\/\/7ggBlmv\/\/\/\/\/7AYBljf\/\/\/\/\/Ce8FVbUCTy8sKhsJNmJ3AZYW\/\/\/\/\/wRKB7AAQAAGIFDzAZZr\/\/\/\/\/\/wYAZZr\/\/\/\/\/\/odAZZr\/\/\/\/\/\/gmAZZr\/\/\/\/\/\/giAZZr\/\/\/\/\/\/gfAZZr\/\/\/\/\/\/kfAZZr\/\/\/\/\/\/saAZZr\/\/\/\/\/\/sXAZZr\/\/\/\/\/\/wUAZY3\/\/\/\/\/wf9EdUq4\/OCMZKTtAGWGv\/\/\/\/8EvgeGAKIhYHoBlmv\/\/\/\/\/\/BABlmv\/\/\/\/\/+xMBlmv\/\/\/\/\/+xQBlmv\/\/\/\/\/+B0Blmv\/\/\/\/\/+RsBlmv\/\/\/\/\/+hoBlmv\/\/\/\/\/+R0Blmv\/\/\/\/\/+xkBlmv\/\/\/\/\/\/BUBlmv\/\/\/\/\/\/RUBlmv\/\/\/\/\/\/BMBljf\/\/\/\/\/C\/0QVVUV88OSlGRVRjc3HAkBlmv\/\/\/\/\/6P4B6xb\/\/\/\/\/BfIGHgGqAkA0NjlPAZZr\/\/\/\/\/xH8AZZr\/\/\/\/\/xP7AZZr\/\/\/\/\/xr5AZZr\/\/\/\/\/xn5AZZr\/\/\/\/\/xj4AZZr\/\/\/\/\/xz3AZZr\/\/\/\/\/xr4AZZr\/\/\/\/\/xf5AZY3\/\/\/\/\/wQV+koAPyokQgGWa\/\/\/\/\/\/wEwGWFv\/\/\/\/8DyAaSASkTFzgBlmv\/\/\/\/\/FvkBlmv\/\/\/\/\/HfYBlmv\/\/\/\/\/IvUBlmv\/\/\/\/\/KvIBlmv\/\/\/\/\/JPQBlmv\/\/\/\/\/IPYBlmv\/\/\/\/\/HfcBlmv\/\/\/\/\/GPkBljv\/\/\/\/\/ARP6mwGWAAAAAAAAAAA="
    },
    {
      "word" : "\/ = { } +",
      "count" : 5,
      "type" : 2,
      "ink" : "UFdJQzEuMDUAAFIAPwEAAAD\/AAAU\/\/\/\/\/ywBAAZKAlIAVQUDIyV7vN8Blmv\/\/\/\/\/7RUBlmv\/\/\/\/\/7xYBlmv\/\/\/\/\/7xYBlmv\/\/\/\/\/7B4Blmv\/\/\/\/\/7R0Blmv\/\/\/\/\/7xwBlmv\/\/\/\/\/6yEBlmv\/\/\/\/\/7R8Blmv\/\/\/\/\/7xwBlmv\/\/\/\/\/7B0Blmv\/\/\/\/\/7xkBlmv\/\/\/\/\/8RUBlmv\/\/\/\/\/8RUBljf\/\/\/\/\/EPMRVVWFqgD82siXlnVTdFNiA0U0RVVFAZZr\/\/\/\/\/xbuAZYW\/\/\/\/\/wW0AiABBQAUJSElGQGWa\/\/\/\/\/8RAAGWa\/\/\/\/\/8S\/wGWa\/\/\/\/\/8S\/gGWa\/\/\/\/\/8W\/QGWa\/\/\/\/\/8U\/AGWa\/\/\/\/\/8T\/AGWa\/\/\/\/\/8U\/AGWa\/\/\/\/\/8S\/QGWN\/\/\/\/\/8HEP6qED8tKiwIRMQBlhr\/\/\/\/\/A8ICfgEMlKYBlmv\/\/\/\/\/EfwBlmv\/\/\/\/\/FPoBlmv\/\/\/\/\/GPkBlmv\/\/\/\/\/HvgBlmv\/\/\/\/\/GfkBlmv\/\/\/\/\/FvsBlmv\/\/\/\/\/FvsBlmv\/\/\/\/\/EvwBljf\/\/\/\/\/AxD9Kj8tKgGWa\/\/\/\/\/8k+QGWFv\/\/\/\/8F2ARaAF8BExhZe74Blmv\/\/\/\/\/7g8Bljf\/\/\/\/\/X\/AOVVUAAAAAQFVVVRUAAABQVVVVVVUAAAAA7v7rysi3lcOAZEY2OioqHRsbDBoaGRgXKSU2QhUlFigoJyk3Jyg2JUc1RnMDBQYHFwgYCBoXJxUlIDNFRVWJiJm6urrburm5qIeWdHRzY2FgYWJ1ZlZpWlpOPy4vDAkBlmv\/\/\/\/\/H\/4Blhb\/\/\/\/\/BUYFagAAAAIUKCgtAZZr\/\/\/\/\/xIEAZZr\/\/\/\/\/xQEAZZr\/\/\/\/\/xoFAZZr\/\/\/\/\/xYFAZZr\/\/\/\/\/xQDAZZr\/\/\/\/\/xIEAZY3\/\/\/\/\/1QQBAAAVFVVVVUAAAAAVVUAAAAAAABVVQBNTEk4VkVTYXByhod3e3t7fWxbXFtJWFdGZlRyUGNFJigXGhoZChkIChcoMyIzJSQmFBcoQCMjNDRWRlZnZmZ2ZXSVpKTT0sLx4dHgsrOmmIiOb28Blmv\/\/\/\/\/7QQBlmv\/\/\/\/\/7QQBlmv\/\/\/\/\/7wMBlmv\/\/\/\/\/7QMBljf\/\/\/\/\/Ce8C1f8DHh8MGiknNWRyAZZr\/\/\/\/\/\/\/tAZYW\/\/\/\/\/wVoB6AAVQExYqHB4QGWa\/\/\/\/\/\/\/FQGWa\/\/\/\/\/\/\/FwGWa\/\/\/\/\/\/\/GAGWa\/\/\/\/\/\/\/HgGWa\/\/\/\/\/\/+HAGWa\/\/\/\/\/\/9GwGWa\/\/\/\/\/\/9HAGWa\/\/\/\/\/\/9GQGWa\/\/\/\/\/\/9FQGWa\/\/\/\/\/\/8FQGWa\/\/\/\/\/\/8EgGWN\/\/\/\/\/8P\/BBV1f8\/9bWVhVZFFxY2Z2ZlhoV1AZZr\/\/\/\/\/\/DlAZYW\/\/\/\/\/we+BoIBqiohMTVGN21vAZZr\/\/\/\/\/xD6AZZr\/\/\/\/\/xX4AZZr\/\/\/\/\/xT4AZZr\/\/\/\/\/xP4AZZr\/\/\/\/\/xf4AZZr\/\/\/\/\/xX4AZZr\/\/\/\/\/xT5AZZr\/\/\/\/\/xX5AZZr\/\/\/\/\/xP7AZZr\/\/\/\/\/xD7AZY3\/\/\/\/\/wUR\/SoAPy0cCgkBlmv\/\/\/\/\/HgQBAAAAAAAAAAAA"
    },
    {
      "word" : "\\ ~ © ®",
      "count" : 4,
      "type" : 2,
      "ink" : "UFdJQzEuMDUAADcAPwEAAAD\/AAAU\/\/\/\/\/ywBAAVCAWwABQATMVK12AGWa\/\/\/\/\/8JEAGWa\/\/\/\/\/8NFQGWa\/\/\/\/\/8MEwGWa\/\/\/\/\/8MEgGWa\/\/\/\/\/8THQGWa\/\/\/\/\/8WIgGWa\/\/\/\/\/8ZJAGWa\/\/\/\/\/8fLQGWa\/\/\/\/\/8bJgGWa\/\/\/\/\/8ZIQGWa\/\/\/\/\/8ZIQGWa\/\/\/\/\/8WGwGWa\/\/\/\/\/8TFgGWN\/\/\/\/\/8JEhQAQAL\/zqyKaFlFQUQCAAAW\/\/\/\/\/zLSAlABr6qqCgAAAACgqqqqClFxsra328qqm4lYWTc3CDZFlqa258anuKiIiXhXWTg3FwcXOFdomaio2Le2xqSEk3LFAgAAFv\/\/\/\/8JmgWaAP9VASM0RjkKG26dvQGWa\/\/\/\/\/\/xEgGWa\/\/\/\/\/\/yEwGWa\/\/\/\/\/\/0EwGWa\/\/\/\/\/\/0GQGWa\/\/\/\/\/\/2FwGWa\/\/\/\/\/\/4FwGWa\/\/\/\/\/\/7GAGWa\/\/\/\/\/\/8FQGWa\/\/\/\/\/\/+EgGWN\/\/\/\/\/8OABEAAKoK4rOnhmdKKRo8W2y+zcwBlmv\/\/\/\/\/De8Blmv\/\/\/\/\/DO8Blmv\/\/\/\/\/C+8Blmv\/\/\/\/\/CusBlmv\/\/\/\/\/CO0Blmv\/\/\/\/\/B+4Blmv\/\/\/\/\/Be4Bljf\/\/\/\/\/FgTw6v\/\/V1UF4+GwkpR0VVdGRignJgcXNUZEVHNzggGWa\/\/\/\/\/\/5IQGWFv\/\/\/\/8MzgXYAP9VVQAjJTcpCShqmqrr6dgBljf\/\/\/\/\/EfkQVQUAqgLW1cWjknFiUlU2JhkpKm5tfgGWN\/\/\/\/\/8FEPeqAo9+fWpZAZZr\/\/\/\/\/xvwAZYW\/\/\/\/\/yAuB3oA\/1dVVQUAoKoAIjNEZ0UnWYvN3Mvq59blxLLBsJKVd1dLKwsuXW2tzdsBlmv\/\/\/\/\/C\/ABljf\/\/\/\/\/AQnwAvgBljf\/\/\/\/\/Ggbwqv\/\/X1VVBfXk0cChpYZnako6KxsqGxopWklXVkVEQ1NCAZZr\/\/\/\/\/\/YRATgW\/\/\/\/\/wX0BpIAAABBcWDB8AGWa\/\/\/\/\/8AEgGWa\/\/\/\/\/8AFQGWN\/\/\/\/\/84ABIAqO7\/7qqqCkBVVVUFAADwwKCAwUBggJDBwNHh0bHBkJGgcWJkRkdJOyoZKxgICRdDYWJ1ZYiHZ3hmZmdVREJCUVBhYXZpawGWa\/\/\/\/\/8SBAGWa\/\/\/\/\/8TBAGWa\/\/\/\/\/8TAwGWa\/\/\/\/\/8ZAQGWa\/\/\/\/\/8YAAGWa\/\/\/\/\/8W\/wGWAAAAAAAAAAA="
    }
  ],
  "device_os" : "iOS",
  "device_idiom" : "iPad",
  "copyright" : "PhatWare Corp.",
  "device_uuid" : "25975D34-90EC-4763-A142-42B0184E129E"
}